Workbook

Sheet Pviots
A3: Count of Sample ID | B3: Column Labels
A4: Row Labels | B4: 45868 | C4: 45869 | D4: 45873 | E4: 45874 | F4: 45875 | G4: 45876 | H4: 45877 | I4: Grand Total
A5: Subramanian | B5: 101 | C5: 389 | D5: 146 | E5: 53 | F5: 137 | G5: 233 | H5: 48 | I5: 1107
A6: A.Banu | B6: 40 | C6: 106 | D6: 22 | I6: 168
A7: G.muthukumar | B7: 1 | C7: 6 | F7: 30 | G7: 61 | I7: 98
A8: Sinthanai selvi | B8: 24 | C8: 123 | I8: 147
A9: U.Amir nisha | B9: 36 | C9: 154 | D9: 65 | I9: 255
A10: priya | D10: 22 | E10: 25 | F10: 41 | G10: 61 | H10: 25 | I10: 174
A11: Immaculatebanumathi | D11: 37 | E11: 28 | F11: 53 | G11: 72 | H11: 23 | I11: 213
A12: pantyan | F12: 13 | G12: 39 | I12: 52
A13: Grand Total | B13: 101 | C13: 389 | D13: 146 | E13: 53 | F13: 137 | G13: 233 | H13: 48 | I13: 1107
A21: Date | B21: 45877 | G21: Date | H21: 45876
A22: Surveyor Vendor Name | B22: (All) | G22: Surveyor Vendor Name | H22: (All)
A24: Count of Sample ID | B24: Column Labels | G24: Count of Sample ID | H24: Column Labels
A25: Row Labels | B25: Greater than 3 Minutes | C25: Grand Total | G25: Row Labels | H25: 18-30 | I25: 31-45 | J25: 46-60 | K25: 60+ | L25: Grand Total
A26: priya | B26: 25 | C26: 25 | G26: G.muthukumar | H26: 23 | I26: 8 | J26: 24 | K26: 6 | L26: 61
A27: Immaculatebanumathi | B27: 23 | C27: 23 | G27: priya | H27: 11 | I27: 28 | J27: 17 | K27: 5 | L27: 61
A28: Grand Total | B28: 48 | C28: 48 | G28: Immaculatebanumathi | H28: 18 | I28: 26 | J28: 19 | K28: 9 | L28: 72
G29: pantyan | H29: 4 | I29: 13 | J29: 16 | K29: 6 | L29: 39
G30: Grand Total | H30: 56 | I30: 75 | J30: 76 | K30: 26 | L30: 233
A37: Date | B37: 45877
A39: Count of Sample ID | B39: Column Labels
A40: Row Labels | B40: ஆண்/Male | C40: பெண்/Female | D40: Grand Total
A41: Subramanian | B41: 0.39583333 | C41: 0.60416667 | D41: 1 | E41: Sample Count
A42: priya | B42: 0.4 | C42: 0.6 | D42: 1 | E42: 23
A43: Immaculatebanumathi | B43: 0.39130435 | C43: 0.60869565 | D43: 1 | E43: 29
A44: Grand Total | B44: 0.39583333 | C44: 0.60416667 | D44: 1 | E44: 30
E45: 13
E46: 95

Sheet Data Updation
A1: Date | B1: 45877 | D1: Date | E1: (All) | I1: DMK | J1: TVK | K1: AIADMK | L1: INC | M1: BJP | N1: NTK | O1: DMDK | P1: VCK | Q1: PMK | R1: CPI | S1: CPM | T1: Others
A2: Consider | B2: Yes | D2: Consider | E2: Yes | I2: =IFERROR(VLOOKUP(I1,$A$4:$B$15,2,0),0%) -> 0.4 | J2: =IFERROR(VLOOKUP(J1,$A$4:$B$15,2,0),0%) -> 0.13333333 | K2: =IFERROR(VLOOKUP(K1,$A$4:$B$15,2,0),0%) -> 0.36666667 | L2: =IFERROR(VLOOKUP(L1,$A$4:$B$15,2,0),0%) -> 0 | M2: =IFERROR(VLOOKUP(M1,$A$4:$B$15,2,0),0%) -> 0 | N2: =IFERROR(VLOOKUP(N1,$A$4:$B$15,2,0),0%) -> 0 | O2: =IFERROR(VLOOKUP(O1,$A$4:$B$15,2,0),0%) -> 0 | P2: =IFERROR(VLOOKUP(P1,$A$4:$B$15,2,0),0%) -> 0 | ... T2: =IFERROR(VLOOKUP(T1,$A$4:$B$15,2,0),0%) -> 0.1
I3: =IFERROR(VLOOKUP(I$1,$D$4:$E$19,2,0),0%) -> 0.38769531 | J3: =IFERROR(VLOOKUP(J$1,$D$4:$E$19,2,0),0%) -> 0.22363281 | K3: =IFERROR(VLOOKUP(K$1,$D$4:$E$19,2,0),0%) -> 0.31445312 | L3: =IFERROR(VLOOKUP(L$1,$D$4:$E$19,2,0),0%) -> 0.0087890625 | M3: =IFERROR(VLOOKUP(M$1,$D$4:$E$19,2,0),0%) -> 0.0068359375 | N3: =IFERROR(VLOOKUP(N$1,$D$4:$E$19,2,0),0%) -> 0.0078125 | O3: =IFERROR(VLOOKUP(O$1,$D$4:$E$19,2,0),0%) -> 0.012695312 | P3: =IFERROR(VLOOKUP(P$1,$D$4:$E$19,2,0),0%) -> 0 | ... T3: =IFERROR(VLOOKUP(T$1,$D$4:$E$19,2,0),0%) -> 0.034179688
A4: Row Labels | B4: Count of Sample ID | D4: Row Labels | E4: Count of Sample ID
A5: DMK | B5: 0.4 | D5: INC | E5: 0.0087890625
A6: AIADMK | B6: 0.36666667 | D6: DMK | E6: 0.38769531
A7: TVK | B7: 0.13333333 | D7: AIADMK | E7: 0.31445312
A8: Others | B8: 0.1 | D8: TVK | E8: 0.22363281
A9: Grand Total | B9: 1 | D9: DMDK | E9: 0.012695312
D10: BJP | E10: 0.0068359375
D11: CPM | E11: 0.00390625
D12: Others | E12: 0.034179688
D13: NTK | E13: 0.0078125
D14: Grand Total | E14: 1 | I14: Consider | J14: Yes
I16: Row Labels | J16: Count of Sample ID | L16: Count of Sample ID | M16: Column Labels
I17: 45868 | J17: 77 | L17: Row Labels | M17: AIADMK | N17: BJP | O17: CPM | P17: DMDK | Q17: DMK | R17: INC | S17: NTK | T17: Others | U17: TVK | V17: Grand Total
I18: 45869 | J18: 353 | L18: ANNAVASAL | M18: 45 | N18: 3 | O18: 4 | P18: 4 | Q18: 51 | R18: 5 | T18: 4 | U18: 31 | V18: 147
I19: 45873 | J19: 143 | L19: ATHIPALLAM | Q19: 1 | V19: 1
I20: 45874 | J20: 53 | L20: KILIKUDI | M20: 37 | Q20: 12 | U20: 22 | V20: 71
I21: 45875 | J21: 135 | L21: KUDUMIYANMALAI | M21: 28 | Q21: 46 | T21: 1 | U21: 29 | V21: 104
I22: 45876 | J22: 233 | L22: MANGUDI | M22: 40 | Q22: 29 | S22: 4 | U22: 14 | V22: 87
I23: 45877 | J23: 30 | L23: MUKKANNAMALAIPATTI | M23: 12 | P23: 7 | Q23: 42 | U23: 14 | V23: 75
I24: Grand Total | J24: 1024 | L24: PARAMBUR | M24: 25 | Q24: 45 | T24: 3 | U24: 12 | V24: 85
L25: RAJALIPATTI | M25: 12 | Q25: 25 | S25: 1 | U25: 2 | V25: 40
L26: VEERAPATTI | U26: 1 | V26: 1
L27: VIRALIMALAI | M27: 133 | N27: 4 | P27: 3 | Q27: 158 | R27: 4 | S27: 4 | T27: 24 | U27: 118 | V27: 448
L28: MATHUR | M28: 12 | Q28: 24 | T28: 4 | U28: 8 | V28: 48
L29: Grand Total | M29: 344 | N29: 7 | O29: 4 | P29: 14 | Q29: 433 | R29: 9 | S29: 9 | T29: 36 | U29: 251 | V29: 1107

Sheet Factor
F3: Party | G3: 2021
F4: ADMK | G4: 0.52826706
F5: DMK | G5: 0.40626503
A6: Consider | B6: Yes | F6: NTK | G6: 0.036371062
F7: Others | G7: =1-SUM(G4:G6) -> 0.02909685
A8: Row Labels | B8: Count | C8: %
A9: அதிமுக கூட்டணி / AIADMK Alliance | B9: 333 | C9: 333 | F9: 2021 Ae | G9: TBT | H9: Collected | I9: Collected % | J9: Factor
A10: திமுக கூட்டணி / DMK Alliance | B10: 456 | C10: 456 | F10: அதிமுக கூட்டணி / AIADMK Alliance | G10: 0.52826706 | H10: =VLOOKUP(F10,$A$8:$B$14,2,0) -> 333 | I10: =H10/SUM($H$10:$H$12) -> 0.40266022 | J10: =G10/I10 -> 1.3119425 | L10: increase to 40%
A11: பிற கட்சிகள் / Others | B11: 38 | C11: 38 | F11: திமுக கூட்டணி / DMK Alliance | G11: 0.40626503 | H11: =VLOOKUP(F11,$A$8:$B$14,2,0) -> 456 | I11: =H11/SUM($H$10:$H$12) -> 0.55139057 | J11: =G11/I11 -> 0.73680082
A12: நினைவில் இல்லை / Don’t Remember | B12: 154 | C12: 154 | F12: பிற கட்சிகள் / Others | G12: =1-SUM(G10:G11) -> 0.065467912 | H12: =VLOOKUP(F12,$A$8:$B$14,2,0) -> 38 | I12: =H12/SUM($H$10:$H$12) -> 0.045949214 | J12: =G12/I12 -> 1.4247885
A13: வாக்களிக்கவில்லை / Did not Vote | B13: 43 | C13: 43 | F13: நினைவில் இல்லை / Don’t Remember | J13: 1
A14: Grand Total | B14: 1024 | C14: 1024 | F14: வாக்களிக்கவில்லை / Did not Vote | J14: 1
A25: Consider | B25: Yes
F26: Gender | G26: TBT | H26: Collected | I26: Factor
A27: Row Labels | B27: Count | C27: % | F27: ஆண்/Male | G27: 0.5 | H27: =VLOOKUP(F27,$A$28:$C$29,3,0) -> 0.52246094 | I27: =G27/H27 -> 0.95700935
A28: ஆண்/Male | B28: 535 | C28: 0.52246094 | F28: பெண்/Female | G28: 0.5 | H28: =VLOOKUP(F28,$A$28:$C$29,3,0) -> 0.47753906 | I28: =G28/H28 -> 1.0470348
A29: பெண்/Female | B29: 489 | C29: 0.47753906
A30: Grand Total | B30: 1024 | C30: 1
A33: Consider | B33: Yes
A35: Row Labels | B35: Count | C35: % | F35: Age | G35: TBT | H35: Collected | I35: Factor
A36: 18-30 | B36: 210 | C36: 0.20507812 | F36: 18-30 | G36: 0.2 | H36: =VLOOKUP(F36,$A$35:$C$40,3,0) -> 0.20507812 | I36: =G36/H36 -> 0.9752381
A37: 31-45 | B37: 374 | C37: 0.36523438 | F37: 31-45 | G37: 0.4 | H37: =VLOOKUP(F37,$A$35:$C$40,3,0) -> 0.36523438 | I37: =G37/H37 -> 1.0951872
A38: 46-60 | B38: 291 | C38: 0.28417969 | F38: 46-60 | G38: 0.25 | H38: =VLOOKUP(F38,$A$35:$C$40,3,0) -> 0.28417969 | I38: =G38/H38 -> 0.87972509
A39: 60+ | B39: 149 | C39: 0.14550781 | F39: 60+ | G39: 0.15 | H39: =VLOOKUP(F39,$A$35:$C$40,3,0) -> 0.14550781 | I39: =G39/H39 -> 1.0308725
A40: Grand Total | B40: 1024 | C40: 1
B43: Consider | C43: Yes
B45: பதிலளித்தவரின் வயது/Age Group | C45: பாலினம்/Gender | D45: Count | E45: % | F45: TBT | G45: Factor
A46: =B46&C46 -> 18-30ஆண்/Male | B46: 18-30 | C46: ஆண்/Male | D46: 96 | E46: 0.09375 | F46: 0.1 | G46: =F46/E46 -> 1.0666667
A47: =B47&C47 -> 18-30பெண்/Female | B47: 18-30 | C47: பெண்/Female | D47: 114 | E47: 0.11132812 | F47: 0.1 | G47: =F47/E47 -> 0.89824561
A48: =B48&C48 -> 31-45ஆண்/Male | B48: 31-45 | C48: ஆண்/Male | D48: 189 | E48: 0.18457031 | F48: 0.2 | G48: =F48/E48 -> 1.0835979
A49: =B49&C49 -> 31-45பெண்/Female | B49: 31-45 | C49: பெண்/Female | D49: 185 | E49: 0.18066406 | F49: 0.2 | G49: =F49/E49 -> 1.107027
A50: =B50&C50 -> 46-60ஆண்/Male | B50: 46-60 | C50: ஆண்/Male | D50: 161 | E50: 0.15722656 | F50: 0.125 | G50: =F50/E50 -> 0.79503106
A51: =B51&C51 -> 46-60பெண்/Female | B51: 46-60 | C51: பெண்/Female | D51: 130 | E51: 0.12695312 | F51: 0.125 | G51: =F51/E51 -> 0.98461538
A52: =B52&C52 -> 60+ஆண்/Male | B52: 60+ | C52: ஆண்/Male | D52: 89 | E52: 0.086914062 | F52: 0.075 | G52: =F52/E52 -> 0.86292135
A53: =B53&C53 -> 60+பெண்/Female | B53: 60+ | C53: பெண்/Female | D53: 60 | E53: 0.05859375 | F53: 0.075 | G53: =F53/E53 -> 1.28
B54: Grand Total | D54: 1024 | E54: 1
B58: Consider | C58: Yes
F59: Caste | G59: TBT | H59: Collected | I59: Factor
B60: Row Labels | C60: Count | D60: % | F60: MUTTARAIYAR | G60: 0.28 | H60: =VLOOKUP(F60,$B$61:$D$70,3,0) -> 0.2265625 | I60: =G60/H60 -> 1.2358621
B61: CHOLIA VELLALAR | C61: 96 | D61: 0.09375 | F61: DEVENDRA KULA VELLALAR | G61: 0.16 | H61: =VLOOKUP(F61,$B$61:$D$70,3,0) -> 0.16015625 | I61: =G61/H61 -> 0.99902439
B62: CHRISTIAN | C62: 44 | D62: 0.04296875 | F62: MUKKULATHOR | G62: 0.129 | H62: =VLOOKUP(F62,$B$61:$D$70,3,0) -> 0.095703125 | I62: =G62/H62 -> 1.3479184
B63: DEVENDRA KULA VELLALAR | C63: 164 | D63: 0.16015625 | F63: PALLAR SC | G63: 0.1 | H63: =VLOOKUP(F63,$B$61:$D$70,3,0) -> 0.078125 | I63: =G63/H63 -> 1.28
B64: MUKKULATHOR | C64: 98 | D64: 0.095703125 | F64: CHOLIA VELLALAR | G64: 0.1 | H64: =VLOOKUP(F64,$B$61:$D$70,3,0) -> 0.09375 | I64: =G64/H64 -> 1.0666667
B65: MUSLIM | C65: 81 | D65: 0.079101562 | F65: URALI GOUNDER | G65: 0.09 | H65: =VLOOKUP(F65,$B$61:$D$70,3,0) -> 0.084960938 | I65: =G65/H65 -> 1.0593103
B66: MUTTARAIYAR | C66: 232 | D66: 0.2265625 | F66: MUSLIM | G66: 0.081 | H66: =VLOOKUP(F66,$B$61:$D$70,3,0) -> 0.079101562 | I66: =G66/H66 -> 1.024
B67: Others | C67: 142 | D67: 0.13867188 | F67: CHRISTIAN | G67: 0.04 | H67: =VLOOKUP(F67,$B$61:$D$70,3,0) -> 0.04296875 | I67: =G67/H67 -> 0.93090909
B68: PALLAR SC | C68: 80 | D68: 0.078125 | F68: OTHERS | G68: 0.02 | H68: =VLOOKUP(F68,$B$61:$D$70,3,0) -> 0.13867188 | I68: =G68/H68 -> 0.14422535
B69: URALI GOUNDER | C69: 87 | D69: 0.084960938
B70: Grand Total | C70: 1024 | D70: 1

Sheet PPT Pviots
A1: Consider | B1: Yes
I2: Age-Gender & 21 AeFactor | J2: 2021 Ae and Caste
A3: Row Labels | B3: Count | C3: Raw % | D3: Gender | E3: Age | F3: Age & Gender | G3: 2021 Ae | H3: Caste | I3: Multi Facto | J3: Sum of Multi Factor 2
A4: DMK | B4: 397 | C4: 0.38769531 | D4: 0.38711656 | E4: 0.38430942 | F4: 0.38530576 | G4: 0.31609844 | H4: 0.38892515 | I4: 0.31513381 | J4: 0.31352695 | K4: 0.32
A5: AIADMK | B5: 322 | C5: 0.31445312 | D5: 0.3135944 | E5: 0.31225091 | F5: 0.30939746 | G5: 0.35875957 | H5: 0.31526818 | I5: 0.35131283 | J5: 0.36392135 | K5: 0.35 | L5: -0.1
A6: TVK | B6: 229 | C6: 0.22363281 | D6: 0.22500812 | E6: 0.22820289 | F6: 0.23039608 | G6: 0.24576401 | H6: 0.22248309 | I6: 0.25294319 | J6: 0.24483304 | K6: 0.25 | L6: 0.15
A7: NTK | B7: 8 | C7: 0.0078125 | D7: 0.0079162128 | E7: 0.008439012 | F7: 0.0083761205 | G7: 0.0094718301 | H7: 0.0080718796 | I7: 0.010093741 | J7: 0.0093043308
A8: DMDK | B8: 13 | C8: 0.012695312 | D8: 0.012677025 | E8: 0.012873673 | F8: 0.01276921 | G8: 0.014354643 | H8: 0.013673207 | I8: 0.014356512 | J8: 0.015481501
A9: INC | B9: 9 | C9: 0.0087890625 | D9: 0.0084991304 | E9: 0.0085327905 | F9: 0.0075574577 | G9: 0.0070374503 | H9: 0.0088708703 | I9: 0.006170131 | J9: 0.0065150576
A10: BJP | B10: 7 | C10: 0.0068359375 | D10: 0.0070695488 | E10: 0.0072762188 | F10: 0.007262884 | G10: 0.0074452002 | H10: 0.0058681178 | I10: 0.0079117285 | J10: 0.0063360757
A11: CPM | B11: 4 | C11: 0.00390625 | D11: 0.0040899796 | E11: 0.0034364261 | F11: 0.0038461538 | G11: 0.0028781282 | H11: 0.003902439 | I11: 0.0028247002 | J11: 0.0028309926
A12: Others | B12: 35 | C12: 0.034179688 | D12: 0.034029012 | E12: 0.034678664 | F12: 0.035088874 | G12: 0.038190733 | H12: 0.032937071 | I12: 0.039253359 | J12: 0.037250705
A13: Grand Total | B13: 1024 | C13: 1 | D13: 1 | E13: 1 | F13: 1 | G13: 1 | H13: 1 | I13: 1 | J13: 1
A17: Consider | B17: Yes
A19: 2021 Ae | B19: Column Labels
A20: Row Labels | B20: DMK | C20: AIADMK | D20: TVK | E20: NTK | F20: DMDK | G20: INC | H20: BJP | I20: CPM | J20: Others | K20: Grand Total
A21: ஆண்/Male | B21: 0.32010819 | C21: 0.38696825 | D21: 0.21584999 | E21: 0.005571737 | F21: 0.01300072 | G21: 0.010947361 | H21: 0.0018572457 | I21: 0 | J21: 0.045696504 | K21: 1
A22: பெண்/Female | B22: 0.31165214 | C22: 0.32747983 | D22: 0.27893475 | E22: 0.013796523 | F22: 0.015855966 | G22: 0.0027018704 | H22: 0.013641511 | I22: 0.0060695961 | J22: 0.029867814 | K22: 1
A23: Grand Total | B23: 0.31609844 | C23: 0.35875957 | D23: 0.24576401 | E23: 0.0094718301 | F23: 0.014354643 | G23: 0.0070374503 | H23: 0.0074452002 | I23: 0.0028781282 | J23: 0.038190733 | K23: 1
C24: 34-35
B25: TVK Differnce female to male | D25: =D22-D21 -> 0.063084766
A26: Consider | B26: Yes
A28: 2021 Ae | B28: Column Labels
A29: Row Labels | B29: DMK | C29: AIADMK | D29: TVK | E29: NTK | F29: DMDK | G29: INC | H29: BJP | I29: CPM | J29: Others | K29: Grand Total
A30: 18-30 | B30: 0.30680541 | C30: 0.25755913 | D30: 0.39044867 | E30: 0.0068972833 | F30: 0 | G30: 0 | H30: 0 | I30: 0 | J30: 0.038289509 | K30: 1
A31: 31-45 | B31: 0.25378067 | C31: 0.33278653 | D31: 0.30785358 | E31: 0.021125923 | F31: 0.015319065 | G31: 0.003349622 | H31: 0.016911954 | I31: 0 | J31: 0.048872661 | K31: 1
A32: 46-60 | B32: 0.34474073 | C32: 0.45452574 | D32: 0.12789126 | E32: 0 | F32: 0.020311051 | G32: 0.010503453 | H32: 0.0035638713 | I32: 0.010503453 | J32: 0.027960437 | K32: 1
A33: 60+ | B33: 0.44209822 | C33: 0.38773805 | D33: 0.10019139 | E33: 0 | F33: 0.020666137 | G33: 0.020302436 | H33: 0 | I33: 0 | J33: 0.029003771 | K33: 1
A34: Grand Total | B34: 0.31609844 | C34: 0.35875957 | D34: 0.24576401 | E34: 0.0094718301 | F34: 0.014354643 | G34: 0.0070374503 | H34: 0.0074452002 | I34: 0.0028781282 | J34: 0.038190733 | K34: 1
A37: Consider | B37: Yes
A39: 2021 Ae | B39: Column Labels
A40: Row Labels | B40: DMK | C40: AIADMK | D40: TVK | E40: NTK | F40: DMDK | G40: INC | H40: BJP | I40: CPM | J40: Others | K40: Grand Total
A41: ஆண்/Male | B41: 0.32010819 | C41: 0.38696825 | D41: 0.21584999 | E41: 0.005571737 | F41: 0.01300072 | G41: 0.010947361 | H41: 0.0018572457 | I41: 0 | J41: 0.045696504 | K41: 1
A42: 18-30 | B42: 0.2887643 | C42: 0.27893334 | D42: 0.36633345 | E42: 0 | F42: 0 | G42: 0 | H42: 0 | I42: 0 | J42: 0.065968902 | K42: 1
A43: 31-45 | B43: 0.2925065 | C43: 0.30041927 | D43: 0.32308379 | E43: 0.015147075 | F43: 0.0201961 | G43: 0 | H43: 0 | I43: 0 | J43: 0.048647263 | K43: 1
A44: 46-60 | B44: 0.33660535 | C44: 0.52716569 | D44: 0.0655171 | E44: 0 | F44: 0 | G44: 0.01884982 | H44: 0.0063958328 | I44: 0 | J44: 0.045466203 | K44: 1
A45: 60+ | B45: 0.38887062 | C45: 0.45360527 | D45: 0.072260763 | E45: 0 | F45: 0.034697546 | G45: 0.034086907 | H45: 0 | I45: 0 | J45: 0.016478888 | K45: 1
A46: பெண்/Female | B46: 0.31165214 | C46: 0.32747983 | D46: 0.27893475 | E46: 0.013796523 | F46: 0.015855966 | G46: 0.0027018704 | H46: 0.013641511 | I46: 0.0060695961 | J46: 0.029867814 | K46: 1
A47: 18-30 | B47: 0.32295133 | C47: 0.23843024 | D47: 0.41203062 | E47: 0.013070017 | F47: 0 | G47: 0 | H47: 0 | I47: 0 | J47: 0.013517795 | K47: 1
A48: 31-45 | B48: 0.2141653 | C48: 0.36589727 | D48: 0.29227353 | E48: 0.027242106 | F48: 0.010330003 | G48: 0.0067761852 | H48: 0.034212377 | I48: 0 | J48: 0.049103236 | K48: 1
A49: 46-60 | B49: 0.35497867 | C49: 0.36311227 | D49: 0.20638578 | E49: 0 | F49: 0.045871417 | G49: 0 | H49: 0 | I49: 0.023721484 | J49: 0.005930371 | K49: 1
A50: 60+ | B50: 0.5204944 | C50: 0.29072561 | D50: 0.14132896 | E50: 0 | F50: 0 | G50: 0 | H50: 0 | I50: 0 | J50: 0.047451025 | K50: 1
A51: Grand Total | B51: 0.31609844 | C51: 0.35875957 | D51: 0.24576401 | E51: 0.0094718301 | F51: 0.014354643 | G51: 0.0070374503 | H51: 0.0074452002 | I51: 0.0028781282 | J51: 0.038190733 | K51: 1
A52: 60+ female | C52: from othrs
A55: Consider | B55: Yes
A57: 2021 Ae | B57: Column Labels
A58: Row Labels | B58: DMK | C58: AIADMK | D58: TVK | E58: NTK | F58: DMDK | G58: INC | H58: BJP | I58: CPM | J58: Others | K58: Grand Total
A59: MUTTARAIYAR | B59: 0.25091416 | C59: 0.45674938 | D59: 0.2193484 | E59: 0.015969838 | F59: 0.022753641 | G59: 0.01176659 | H59: 0 | I59: 0 | J59: 0.022497993 | K59: 1
A60: DEVENDRA KULA VELLALAR | B60: 0.27359388 | C60: 0.31108093 | D60: 0.32244103 | E60: 0 | F60: 0.024355036 | G60: 0.017944811 | H60: 0 | I60: 0.017944811 | J60: 0.0326395 | K60: 1
A61: MUKKULATHOR | B61: 0.31015057 | C61: 0.33438351 | D61: 0.33449992 | E61: 0 | F61: 0 | G61: 0 | H61: 0 | I61: 0 | J61: 0.020966005 | K61: 1
A62: PALLAR SC | B62: 0.37712866 | C62: 0.26529823 | D62: 0.30858426 | E62: 0 | F62: 0 | G62: 0 | H62: 0 | I62: 0 | J62: 0.048988859 | K62: 1
A63: CHOLIA VELLALAR | B63: 0.33196292 | C63: 0.32513646 | D63: 0.22265568 | E63: 0 | F63: 0.031277102 | G63: 0 | H63: 0 | I63: 0 | J63: 0.088967836 | K63: 1
A64: URALI GOUNDER | B64: 0.26874066 | C64: 0.49658552 | D64: 0.17170334 | E64: 0.048181882 | F64: 0 | G64: 0 | H64: 0 | I64: 0 | J64: 0.014788595 | K64: 1
A65: MUSLIM | B65: 0.55644178 | C65: 0.26007699 | D65: 0.12197459 | E65: 0 | F65: 0 | G65: 0 | H65: 0.041246392 | I65: 0 | J65: 0.02026025 | K65: 1
A66: CHRISTIAN | B66: 0.40794598 | C66: 0.21341379 | D66: 0.11521076 | E66: 0 | F66: 0.043687058 | G66: 0 | H66: 0.079158439 | I66: 0 | J66: 0.14058397 | K66: 1
A67: Others | B67: 0.31593748 | C67: 0.34320148 | D67: 0.27755534 | E67: 0.011123482 | F67: 0 | G67: 0.010242481 | H67: 0.0078071113 | I67: 0 | J67: 0.034132627 | K67: 1
A68: Grand Total | B68: 0.31609844 | C68: 0.35875957 | D68: 0.24576401 | E68: 0.0094718301 | F68: 0.014354643 | G68: 0.0070374503 | H68: 0.0074452002 | I68: 0.0028781282 | J68: 0.038190733 | K68: 1
A69: Party | B69: 0.32 | C69: 0.35 | D69: 0.25
A70: Cm
A72: Consider | B72: Yes
A74: 2021 Ae | B74: Column Labels
A75: Row Labels | B75: M.K. Stalin (DMK) | C75: EPS (AIADMK) | D75: Vijay (TVK) | E75: Seeman (NTK) | F75: Premalatha Vijayakanth (DMDK) | G75: Anbumani Ramadoss (PMK) | H75: Others | I75: Grand Total
A76: DMK Alliance | B76: 0.78508772 | C76: 0.032894737 | D76: 0.125 | E76: 0.0043859649 | F76: 0.0043859649 | G76: 0 | H76: 0.048245614 | I76: 1
A77: AIADMK Alliance | B77: 0.057057057 | C77: 0.54354354 | D77: 0.3033033 | E77: 0.027027027 | F77: 0.006006006 | G77: 0.003003003 | H77: 0.06006006 | I77: 1
A78: Others | B78: 0.13157895 | C78: 0.026315789 | D78: 0.36842105 | E78: 0.10526316 | F78: 0.10526316 | G78: 0 | H78: 0.26315789 | I78: 1
A79: Didn’t Vote/ Rember | B79: 0.36040609 | C79: 0.10659898 | D79: 0.45177665 | E79: 0.050761421 | F79: 0.030456853 | G79: 0 | H79: 0 | I79: 1
A80: Grand Total | B80: 0.35822807 | C80: 0.26458828 | D80: 0.2768075 | E80: 0.028301014 | F80: 0.015426407 | G80: 0.0012811939 | H80: 0.055367533 | I80: 1
A81: Didn’t Vote/ Rember | D81: Take From others
A82: Overall | C82: 25-27 | E82: Distrbute remaing to DMK and TVK
A83: Consider | B83: Yes | D83: increase from others for didn’t vote more than others
A85: 2021 Ae | B85: Column Labels
A86: Row Labels | B86: DMK | C86: AIADMK | D86: TVK | E86: NTK | F86: DMDK | G86: INC | H86: BJP | I86: CPM | J86: Others | K86: Grand Total
A87: DMK Alliance | B87: 0.67982456 | C87: 0.16447368 | D87: 0.098684211 | E87: 0 | F87: 0 | G87: 0.01754386 | H87: 0 | I87: 0.0087719298 | J87: 0.030701754 | K87: 1
A88: AIADMK Alliance | B88: 0.051051051 | C88: 0.61861862 | D88: 0.29129129 | E88: 0 | F88: 0 | G88: 0.003003003 | H88: 0.006006006 | I88: 0 | J88: 0.03003003 | K88: 1
A89: Others | B89: 0.18421053 | C89: 0.052631579 | D89: 0.26315789 | E89: 0.10526316 | F89: 0.10526316 | G89: 0 | H89: 0 | I89: 0 | J89: 0.28947368 | K89: 1
A90: Didn’t Vote/ Rember | B90: 0.31979695 | C90: 0.19796954 | D90: 0.39086294 | E90: 0.020304569 | F90: 0.045685279 | G90: 0 | H90: 0.025380711 | I90: 0 | J90: 0 | K90: 1
A91: Grand Total | B91: 0.31609844 | C91: 0.35875957 | D91: 0.24576401 | E91: 0.0094718301 | F91: 0.014354643 | G91: 0.0070374503 | H91: 0.0074452002 | I91: 0.0028781282 | J91: 0.038190733 | K91: 1
A94: 2021 Change Some From Dmk to AIADMK
A96: Consider | B96: Yes
A97: Vijays Impact
A98: 2021 Ae | B98: Column Labels
A99: Row Labels | B99: No | C99: Yes | D99: Grand Total
A100: DMK Alliance | B100: 0.56798246 | C100: 0.43201754 | D100: 1 | I100: =-1*B100 -> -0.56798246 | J100: =C100 -> 0.43201754
A101: AIADMK Alliance | B101: 0.43543544 | C101: 0.56456456 | D101: 1 | E101: Need clarity wether to increase are not | G101: 40-44% | I101: =-1*B101 -> -0.43543544 | J101: =C101 -> 0.56456456
A102: Others | B102: 0.34210526 | C102: 0.65789474 | D102: 1 | I102: =-1*B102 -> -0.34210526 | J102: =C102 -> 0.65789474
A103: Didn’t Vote/ Rember | B103: 0.33502538 | C103: 0.66497462 | D103: 1 | I103: =-1*B103 -> -0.33502538 | J103: =C103 -> 0.66497462
A104: Grand Total | B104: 0.45467317 | C104: 0.54532683 | D104: 1 | I104: =-1*B104 -> -0.45467317 | J104: =C104 -> 0.54532683
A108: Consider | B108: Yes
A109: Anti incumbency and Change factor
A110: 2021 Ae | B110: Column Labels
A111: Row Labels | B111: Yes | C111: No | D111: Not Sure | E111: Grand Total
A112: Satisfactory | B112: 0.34242574 | C112: 0.46883313 | D112: 0.18874113 | E112: 1 | F112: 0.33434727
A113: Needs improvement | B113: 0.60706155 | C113: 0.14889925 | D113: 0.2440392 | E113: 1 | F113: 0.40242493
A114: Unsatisfactory | B114: 0.77930045 | C114: 0.053987896 | D114: 0.16671166 | E114: 1 | F114: 0.2632278
A115: Grand Total | B115: 0.5527993 | C115: 0.24218596 | D115: 0.20501474 | E115: 1
A118: Consider | B118: Yes
A119: Anti incumbency and Cm Preference
A120: 2021 Ae | B120: Column Labels
A121: Row Labels | B121: M.K. Stalin (DMK) | C121: EPS (AIADMK) | D121: Vijay (TVK) | E121: Seeman (NTK) | F121: Premalatha Vijayakanth (DMDK) | G121: Anbumani Ramadoss (PMK) | H121: Others | I121: Grand Total
A122: Satisfactory | B122: 0.64429519 | C122: 0.12816338 | D122: 0.17808119 | E122: 0 | F122: 0.003952813 | G122: 0 | H122: 0.045507429 | I122: 1 | K122: =1-SUM(B122:E122) -> 0.049460242
...

Sheet Location and Caste
B1: Caste | C1: Required | D1: Collected | E1: Pending | F1: Collected % | K1: Date | L1: (All) | Q1: Consider | R1: All
A2: VIRALIMALAI | B2: MUTTARAIYAR | C2: 280 | D2: =VLOOKUP(B2,$K$5:$L$15,2,0) -> 232 | E2: =C2-D2 -> 48 | F2: =D2/C2 -> 0.82857143 | K2: Surveyor Vendor Name | L2: (All) | Q2: Date | R2: All
A3: VIRALIMALAI | B3: DEVENDRA KULA VELLALAR | C3: 160 | D3: =VLOOKUP(B3,$K$5:$L$15,2,0) -> 164 | E3: =C3-D3 -> -4 | F3: =D3/C3 -> 1.025 | K3: Surveyor Name | L3: (All)
A4: VIRALIMALAI | B4: MUKKULATHOR | C4: 129 | D4: =VLOOKUP(B4,$K$5:$L$15,2,0) -> 98 | E4: =C4-D4 -> 31 | F4: =D4/C4 -> 0.75968992 | K4: Consider | L4: Yes | Q4: Row Labels | R4: Distinct Count of Surveyor Name | S4: Count of Sample ID
A5: VIRALIMALAI | B5: PALLAR SC | C5: 100 | D5: =VLOOKUP(B5,$K$5:$L$15,2,0) -> 80 | E5: =C5-D5 -> 20 | F5: =D5/C5 -> 0.8 | Q5: Subramanian | R5: 7 | S5: 1107
A6: VIRALIMALAI | B6: CHOLIA VELLALAR | C6: 100 | D6: =VLOOKUP(B6,$K$5:$L$15,2,0) -> 96 | E6: =C6-D6 -> 4 | F6: =D6/C6 -> 0.96 | K6: Row Labels | L6: Count of Sample ID | Q6: Grand Total | R6: 7 | S6: 1107
A7: VIRALIMALAI | B7: URALI GOUNDER | C7: 90 | D7: =VLOOKUP(B7,$K$5:$L$15,2,0) -> 87 | E7: =C7-D7 -> 3 | F7: =D7/C7 -> 0.96666667 | K7: CHOLIA VELLALAR | L7: 96
A8: VIRALIMALAI | B8: MUSLIM | C8: 81 | D8: =VLOOKUP(B8,$K$5:$L$15,2,0) -> 81 | E8: =C8-D8 -> 0 | F8: =D8/C8 -> 1 | K8: CHRISTIAN | L8: 44
A9: VIRALIMALAI | B9: CHRISTIAN | C9: 40 | D9: =VLOOKUP(B9,$K$5:$L$15,2,0) -> 44 | E9: =C9-D9 -> -4 | F9: =D9/C9 -> 1.1 | K9: DEVENDRA KULA VELLALAR | L9: 164
A10: VIRALIMALAI | B10: OTHERS | C10: 20 | D10: =VLOOKUP(B10,$K$5:$L$15,2,0) -> 142 | E10: =C10-D10 -> -122 | F10: =D10/C10 -> 7.1 | K10: MUKKULATHOR | L10: 98
B11: Total | C11: 1000 | D11: =SUM(D2:D10) -> 1024 | E11: =C11-D11 -> -24 | F11: =D11/C11 -> 1.024 | K11: MUSLIM | L11: 81
A12: AC NAME | B12: TALUKA/BLOCK | C12: LOCALITY | D12: Required | E12: Collected | F12: Pending | K12: MUTTARAIYAR | L12: 232 | N12: Block | O12: Required | P12: Collected | Q12: Pedning | R12: Collected %
A13: VIRALIMALAI | B13: ILLUPUR | C13: METTUPATTI | D13: 40 | E13: =IFERROR(VLOOKUP(C13,$K$23:$L$46,2,0),0) -> 0 | F13: =D13-E13 -> 40 | K13: Others | L13: 142 | N13: ILLUPUR | O13: 571 | P13: 172 | Q13: =O13-P13 -> 399 | R13: =P13/O13 -> 0.30122592
A14: VIRALIMALAI | B14: ILLUPUR | C14: ELUVAMPATTI | D14: 40 | E14: =IFERROR(VLOOKUP(C14,$K$23:$L$46,2,0),0) -> 0 | F14: =D14-E14 -> 40 | K14: PALLAR SC | L14: 80 | N14: VIRALIMALAI | O14: 332 | P14: 224 | Q14: =O14-P14 -> 108 | R14: =P14/O14 -> 0.6746988
A15: VIRALIMALAI | B15: ILLUPUR | C15: MANGUDI | D15: 40 | E15: =IFERROR(VLOOKUP(C15,$K$23:$L$46,2,0),0) -> 86 | F15: =D15-E15 -> -46 | K15: URALI GOUNDER | L15: 87 | N15: KULATHUR | O15: 97 | P15: 24 | Q15: =O15-P15 -> 73 | R15: =P15/O15 -> 0.24742268
A16: VIRALIMALAI | B16: ILLUPUR | C16: KULATHUR | D16: 40 | E16: =IFERROR(VLOOKUP(C16,$K$23:$L$46,2,0),0) -> 0 | F16: =D16-E16 -> 40 | K16: Grand Total | L16: 1024
A17: VIRALIMALAI | B17: ILLUPUR | C17: MALAIKUDIPATTI | D17: 40 | E17: =IFERROR(VLOOKUP(C17,$K$23:$L$46,2,0),0) -> 0 | F17: =D17-E17 -> 40 | K17: Date | L17: (All)
A18: VIRALIMALAI | B18: ILLUPUR | C18: AGARAPATTI | D18: 40 | E18: =IFERROR(VLOOKUP(C18,$K$23:$L$46,2,0),0) -> 0 | F18: =D18-E18 -> 40 | K18: Surveyor Vendor Name | L18: (All)
A19: VIRALIMALAI | B19: ILLUPUR | C19: MEENAVELI | D19: 40 | E19: =IFERROR(VLOOKUP(C19,$K$23:$L$46,2,0),0) -> 0 | F19: =D19-E19 -> 40 | K19: Surveyor Name | L19: (All)
A20: VIRALIMALAI | B20: ILLUPUR | C20: ILLUPUR | D20: 40 | E20: =IFERROR(VLOOKUP(C20,$K$23:$L$46,2,0),0) -> 0 | F20: =D20-E20 -> 40 | K20: Consider | L20: Yes | R20: Consider | S20: Yes
A21: VIRALIMALAI | B21: ILLUPUR | C21: ANNAVASAL | D21: 40 | E21: =IFERROR(VLOOKUP(C21,$K$23:$L$46,2,0),0) -> 142 | F21: =D21-E21 -> -102
A22: VIRALIMALAI | B22: ILLUPUR | C22: MUKKANNAMALAIPATTI | D22: 40 | E22: =IFERROR(VLOOKUP(C22,$K$23:$L$46,2,0),0) -> 58 | F22: =D22-E22 -> -18 | K22: Row Labels | L22: Count of Sample ID | R22: Row Labels | S22: Count of Sample ID
A23: VIRALIMALAI | B23: ILLUPUR | C23: VEERAPATTI | D23: 40 | E23: =IFERROR(VLOOKUP(C23,$K$23:$L$46,2,0),0) -> 0 | F23: =D23-E23 -> 40 | K23: ANNAVASAL | L23: 142 | R23: ஆண்/Male | S23: 0.52246094
A24: VIRALIMALAI | B24: ILLUPUR | C24: KILIKUDI | D24: 40 | E24: =IFERROR(VLOOKUP(C24,$K$23:$L$46,2,0),0) -> 62 | F24: =D24-E24 -> -22 | K24: KILIKUDI | L24: 62 | R24: பெண்/Female | S24: 0.47753906
A25: VIRALIMALAI | B25: ILLUPUR | C25: PARAMBUR | D25: 40 | E25: =IFERROR(VLOOKUP(C25,$K$23:$L$46,2,0),0) -> 71 | F25: =D25-E25 -> -31 | K25: KUDUMIYANMALAI | L25: 91 | R25: Grand Total | S25: 1
A26: VIRALIMALAI | B26: ILLUPUR | C26: KUDUMIYANMALAI | D26: 40 | E26: =IFERROR(VLOOKUP(C26,$K$23:$L$46,2,0),0) -> 91 | F26: =D26-E26 -> -51 | K26: MANGUDI | L26: 86
A27: VIRALIMALAI | B27: VIRALIMALAI | C27: KALKUDI | D27: 40 | E27: =IFERROR(VLOOKUP(C27,$K$23:$L$46,2,0),0) -> 0 | F27: =D27-E27 -> 40 | K27: MUKKANNAMALAIPATTI | L27: 58
A28: VIRALIMALAI | B28: VIRALIMALAI | C28: VELUR | D28: 40 | E28: =IFERROR(VLOOKUP(C28,$K$23:$L$46,2,0),0) -> 0 | F28: =D28-E28 -> 40 | K28: PARAMBUR | L28: 71 | R28: Consider | S28: Yes
A29: VIRALIMALAI | B29: VIRALIMALAI | C29: VIRALIMALAI | D29: 40 | E29: =IFERROR(VLOOKUP(C29,$K$23:$L$46,2,0),0) -> 444 | F29: =D29-E29 -> -404 | K29: VIRALIMALAI | L29: 444
A30: VIRALIMALAI | B30: VIRALIMALAI | C30: ATHIPALLAM | D30: 40 | E30: =IFERROR(VLOOKUP(C30,$K$23:$L$46,2,0),0) -> 0 | F30: =D30-E30 -> 40 | K30: RAJALIPATTI | L30: 40 | R30: Row Labels | S30: Count of Sample ID
A31: VIRALIMALAI | B31: VIRALIMALAI | C31: NAMBANPATTI | D31: 40 | E31: =IFERROR(VLOOKUP(C31,$K$23:$L$46,2,0),0) -> 0 | F31: =D31-E31 -> 40 | K31: MATHUR | L31: 30 | R31: 18-30 | S31: 0.20507812
A32: VIRALIMALAI | B32: VIRALIMALAI | C32: RAJALIPATTI | D32: 40 | E32: =IFERROR(VLOOKUP(C32,$K$23:$L$46,2,0),0) -> 40 | F32: =D32-E32 -> 0 | K32: Grand Total | L32: 1024 | R32: 31-45 | S32: 0.36523438
A33: VIRALIMALAI | B33: VIRALIMALAI | C33: KODUMBALUR | D33: 40 | E33: =IFERROR(VLOOKUP(C33,$K$23:$L$46,2,0),0) -> 0 | F33: =D33-E33 -> 40 | R33: 46-60 | S33: 0.28417969
A34: VIRALIMALAI | B34: VIRALIMALAI | C34: RAJAGIRI | D34: 40 | E34: =IFERROR(VLOOKUP(C34,$K$23:$L$46,2,0),0) -> 0 | F34: =D34-E34 -> 40 | R34: 60+ | S34: 0.14550781
A35: VIRALIMALAI | B35: KULATHUR | C35: KUMARAMANGALAM | D35: 40 | E35: =IFERROR(VLOOKUP(C35,$K$23:$L$46,2,0),0) -> 0 | F35: =D35-E35 -> 40 | R35: Grand Total | S35: 1
A36: VIRALIMALAI | B36: KULATHUR | C36: MATHUR | D36: 40 | E36: =IFERROR(VLOOKUP(C36,$K$23:$L$46,2,0),0) -> 30 | F36: =D36-E36 -> 10
A37: VIRALIMALAI | B37: KULATHUR | C37: MANDAIYUR | D37: 40 | E37: =IFERROR(VLOOKUP(C37,$K$23:$L$46,2,0),0) -> 0 | F37: =D37-E37 -> 40
D38: =SUM(D13:D37) -> 1000 | E38: =SUM(E13:E37) -> 1024 | F38: =SUM(F13:F37) -> -24 | R38: Consider | S38: Yes
R39: Rev Caste | S39: Others
R41: Row Labels | S41: Count of Sample ID
R42: - | S42: 65
R43: Aantipandaram | S43: 4 | V43: Aantipandaram | AB43: {=_xlfn.UNIQUE(V43:V91)} -> Aantipandaram | AC43: Aantipandaram
R44: ambakajarar | S44: 1 | V44: Agamudaiyar | AB44: Agamudaiyar | AC44: Agamudaiyar
R45: Ambalakar | S45: 1 | V45: ambakajarar | AB45: ambakajarar | AC45: ambakajarar
R46: Amblkaarar | S46: 1 | V46: Ambalakar | AB46: Ambalakar | AC46: Ambalakar
R47: andipandaram | S47: 1 | AB47: 0 | AC47: andipandaram
R48: Arunthathiyar | S48: 1 | V48: andipandaram | AB48: andipandaram | AC48: Arunthathiyar
R49: backward class | S49: 1 | V49: Arunthathiyar | AB49: Arunthathiyar | AC49: Chettiyar
R50: Chettiyar | S50: 7 | AB50: Chettiyar | AC50: Gavundar
R51: hindu | S51: 1 | V51: Chettiyar | AB51: Gavundar | AC51: Hindu Vannar
R52: Hindu Vannar | S52: 1 | AB52: Hindu Vannar | AC52: Isai Vellalar
R53: Isai Vellalar | S53: 12 | V53: Gavundar | AB53: Isai Vellalar | AC53: Kammalar
R54: isaivellalar | S54: 2 | AB54: Kammalar | AC54: konar
R55: isaivellalar | S55: 2 | V55: Hindu Vannar | AB55: konar | AC55: Kuravar
R56: Kammalar | S56: 3 | V56: Isai Vellalar | AB56: Kuravar | AC56: kurumban
R57: konar | S57: 1 | AB57: kurumban | AC57: Mudhaliyar
R58: Kuravar | S58: 1 | AB58: Mudhaliyar | AC58: muthaliyar
R59: kurumban | S59: 1 | V59: Kammalar | AB59: muthaliyar | AC59: naidu
R60: Mudhaliyar | S60: 4 | V60: konar | AB60: naidu | AC60: pandaram
R61: muthaliyar | S61: 1 | V61: Kuravar | AB61: pandaram | AC61: paraiyar
R62: naidu | S62: 1 | V62: kurumban | AB62: paraiyar | AC62: pattaiyachi
R63: pandaram | S63: 3 | V63: Mudhaliyar | AB63: pattaiyachi | AC63: settiyar
R64: settiyar | S64: 1 | V64: muthaliyar | AB64: settiyar | AC64: soliavellar
R65: Udaiyar | S65: 1 | V65: naidu | AB65: soliavellar | AC65: Udaiyar
R66: vadugar | S66: 1 | V66: pandaram | AB66: Udaiyar | AC66: vadugar
R67: valaiyar | S67: 1 | V67: paraiyar | AB67: vadugar | AC67: valaiyar
R68: vaniyachettiyar | S68: 1 | AB68: valaiyar | AC68: vaniyachettiyar
R69: vannar | S69: 5 | V69: pattaiyachi | AB69: vaniyachettiyar | AC69: vannar
R70: vellan chettiyar | S70: 1 | V70: settiyar | AB70: vannar | AC70: vellan chettiyar
R71: vellanchettiyar | S71: 1 | V71: soliavellar | AB71: vellan chettiyar | AC71: viralur chettiyar
R72: viralur chettiyar | S72: 1 | V72: Udaiyar | AB72: viralur chettiyar | AC72: yadavar
R73: yadavar | S73: 3 | V73: vadugar | AB73: yadavar | AC73: கவுண்டர்
R74: செட்டியார் | S74: 1 | V74: valaiyar | AB74: கவுண்டர் | AC74: செட்டியார்
R75: நாயக்கர் | S75: 2 | V75: vaniyachettiyar | AB75: செட்டியார் | AC75: நாயக்கர்
R76: நாயக்கர் | S76: 1 | V76: vannar | AB76: நாயக்கர் | AC76: நாயக்கர்
R77: நாவிதர் | S77: 1 | V77: vellan chettiyar | AB77: நாயக்கர் | AC77: நாவிதர்
R78: யதாவ் | S78: 1 | AB78: நாவிதர் | AC78: யதாவ்
R79: யாதவ் | S79: 3 | V79: viralur chettiyar | AB79: யதாவ் | AC79: யாதவ்
R80: வண்ணார் | S80: 1 | V80: yadavar | AB80: யாதவ் | AC80: வண்ணார்
R81: வண்ணார் | S81: 1 | V81: கவுண்டர் | W81: =VLOOKUP(V81,$Y$81:$Z$92,2,0) -> Gounder | Y81: யதாவ் | Z81: Yadav | AB81: வண்ணார் | AC81: வண்ணார்
R82: Grand Total | S82: 142 | V82: செட்டியார் | W82: =VLOOKUP(V82,$Y$81:$Z$92,2,0) -> Chettiyar | Y82: நாயக்கர் | Z82: Nayak | AB82: வண்ணார்
V83: நாயக்கர் | W83: =VLOOKUP(V83,$Y$81:$Z$92,2,0) -> Nayak | Y83: வண்ணார் | Z83: Vannar
V84: நாயக்கர் | W84: =VLOOKUP(V84,$Y$81:$Z$92,2,0) -> Nayak | Y84: நாவிதர் | Z84: Navidar | AA84: Ambattar
V85: நாவிதர் | W85: =VLOOKUP(V85,$Y$81:$Z$92,2,0) -> Navidar | Y85: யாதவ் | Z85: Yadav
V86: யதாவ் | W86: =VLOOKUP(V86,$Y$81:$Z$92,2,0) -> Yadav | Y86: யாதவ் | Z86: Yadav
V87: யாதவ் | W87: =VLOOKUP(V87,$Y$81:$Z$92,2,0) -> Yadav | Y87: வண்ணார் | Z87: Vannar
V88: வண்ணார் | W88: =VLOOKUP(V88,$Y$81:$Z$92,2,0) -> Vannar | Y88: நாயக்கர் | Z88: Nayak
V89: வண்ணார் | W89: =VLOOKUP(V89,$Y$81:$Z$92,2,0) -> Vannar | Y89: நாயக்கர் | Z89: Nayak
Y90: யாதவ் | Z90: Yadav
Y91: கவுண்டர் | Z91: Gounder
Y92: செட்டியார் | Z92: Chettiyar

Sheet Data
A1: Sample ID | B1: Timestamp | C1: Date | D1: Location | E1: Address | F1: Audio Url | G1: Audio Duration (in secs) | H1: Offline Mode | I1: Surveyor Name | J1: Surveyor Phone Number | K1: Surveyor Vendor Name | L1: TALUKA/BLOCK | M1: LOCALITY | N1: பதிலளிப்பவர் பெயர்/Respondent Name | O1: பாலினம்/Gender | P1: பதிலளித்தவரின் மொபைல் எண்/Mobile Number | Q1: பதிலளித்தவரின் வயது/Age Group | R1: தொழில்/Occupation | S1: மாத வருமானம்/Monthly Income | T1: தமிழக முதல்வர் மு.க. ஸ்டாலின் தலைமையிலான தற்போதைய திமுக அரசின் செயல்திறனை நீங்கள் எப்படி மதிப்பீடு செய்கிறீர்கள்?/ How would you rate the performance of the current DMK-led government under Chief Minister M.K. Stalin? | U1: 2026 சட்டமன்றத் தேர்தலில் ஆட்சி மாற்றம் தேவை என நீங்கள் கருதுகிறீர்களா?/ Do you feel a change in government is needed in the 2026 assembly Elections? | V1: 2021 சட்டமன்றத் தேர்தலில் நீங்கள் எந்தக் கட்சிக்கு வாக்களித்தீர்கள்?/ Which party did you vote in 2021 Assembly Elections? | W1: தமிழகத்தின் அடுத்த முதல்வராக யாருக்கு நீங்கள் ஆதரவு அளிக்க விரும்புகிறீர்கள்?/ Who would you support as Tamil Nadu’s next Chief Minister? | X1: உங்கள் தொகுதியில் வெற்றி பெற வாய்ப்புள்ள கட்சி/கூட்டணி எது என நீங்கள் கருதுகிறீர்கள்?/ Which party/alliance do you think will win in your constituency? | Y1: Rev Party | Z1: நீங்கள் விரும்பும் கட்சி (வினா 13 இல் தெரிவுசெய்தது) தமிழக வெற்றி கழகத்துடன் கூட்டணி அமைத்தால், நீங்கள் அந்த கூட்டணிக்கு வாக்களிக்கிறீர்களா? (இந்த வினா AIADMK, NTK, PMK, DMDK, அல்லது INC-ஐ தேர்ந்தெடுத்தவர்களுக்கே लागू) / If your preferred party (in quest | AA1: விஜயின் அரசியல் வருகை 2026 தேர்தலில் குறிப்பிடத்தக்க தாக்கத்தை ஏற்படுத்தும் என நீங்கள் நம்புகிறீர்களா?/ Do you believe Vijay’s political entry will significantly impact the 2026 elections? | AB1: உங்கள் பதில் "ஆமாம்" எனில், விஜயின் அரசியல் வருகையால் அதிகம் பாதிக்கப்படக்கூடிய கட்சி/கூட்டணி எது? / If yes, which party/alliance will be most affected by Vijay’s entry? | AC1: தமிழக வெற்றி கழகம் (TVK) தற்போது எப்படி செயல்படுகிறது என நீங்கள் மதிப்பீடு செய்கிறீர்கள்? / How would you rate Tamilaga Vettri Kazhagam’s (TVK) current performance? | AD1: சமூக பிரச்சனைகளைத் தீர்க்கும் முயற்சிகளில் விஜய் எவ்வளவு பயனுள்ளதாக இருந்துள்ளார்?/ How effective has Vijay been in addressing social issues? | AE1: திமுக அல்லது அதிமுக கூட்டணிகள் 2026க்கு முந்தைய காலத்தில் உடைந்துவிடும் என நீங்கள் கருதுகிறீர்களா? / Do you foresee the DMK or AIADMK alliances breaking apart before 2026? | AF1: எந்தக் கூட்டணியில் விஜயின் கட்சி (TVK) சேரவேண்டும் என நீங்கள் விரும்புகிறீர்கள்?/ Which alliance would you prefer Vijay’s party (TVK) to join, if any? | AG1: தற்போதைய தமிழகத்தில் மிக முக்கியமான பிரச்சனை எது என நீங்கள் கருதுகிறீர்கள்?/ What is the most critical issue facing Tamil Nadu today? | AH1: சாதி வகை/Caste Category | AI1: சாதி/Caste | AJ1: QC Comment | AK1: QC Remark | AL1: QC User Name | AM1: QC Date | AN1: App Version | AO1: Consider | AP1: Time | AQ1: Rev Caste | AR1: Gender Factor | AS1: Age Factor | AT1: Age & Gender Factor | AU1: 2021 Ae Factor | AV1: Caste Factor | AW1: Multi Factor | AX1: Multi Factor 2 | AY1: Long
A2: wCoRngjNmpdXwr8jpUtS | B2: 2025-07-30 11:50:28.774519 | C2: 45868 | D2: (10.4599207, 78.7030535) | E2: 55,,Annavasal,622101,Tamil Nadu,India. | F2: https://firebasestorage.googleapis.com/v0/b/mindbrink-survey-production.appspot.com/o/audioFiles%2FAtznECuQc6klLPsRR6u2%2FnV4IA56gMWWp4NfG0H1PGfyqfM92%2F2025-07-30%2011%3A50%3A15.491639.m4a?alt=media&token=23fd1b60-6ea5-4086-a9e0-12b2896623eb | G2: 474 | H2: false | I2: G.muthukumar | J2: +918940041476 | K2: Subramanian | L2: VIRALIMALAI | M2: ATHIPALLAM | N2: sinnathuri | O2: ஆண்/Male | P2: 9486664057 | Q2: 31-45 | R2: கூலி தொழில்/ Daily Wage | S2: 10,000 - 25,000 | T2: திருப்திகரமானது / Satisfactory | U2: இல்லை/ No | V2: திமுக கூட்டணி / DMK Alliance | W2: மு.க. ஸ்டாலின் (திமுக) / M.K. Stalin (DMK) | X2: திமுக / DMK | Y2: DMK | Z2: - | AA2: இல்லை / No | AB2: - | AC2: திருப்திகரமல்ல / Unsatisfactory | AD2: குறைவான ஈடுபாடு / Inadequate | AE2: • இல்லை: திமுக மற்றும் அதிமுக கூட்டணிகள் இரண்டும் உடையாது/ No: Both DMK & AIADMK alliances will not break up | AF2: தனித்துப் போட்டியிட வேண்டும் / Contest Independently | AG2: மதுபானம் / போதைப்பொருள் பழக்கம்/ Alcohol/Drug abuse | AH2: OBC | AI2: URALI GOUNDER | AJ2: =IFERROR(_xlfn.XLOOKUP(Table1[[#This Row],[Audio Url]],Qc!C:C,Qc!F:F),"") -> speaking among themselves | AK2: =IFERROR(_xlfn.XLOOKUP(Table1[[#This Row],[Audio Url]],Qc!C:C,Qc!E:E),"") -> Fake Audio/Empty Audio | AL2: - | AM2: - | AN2: =VLOOKUP(Table1[[#This Row],[LOCALITY]],Sheet2!$F:$H,3,0) -> Rural | AO2: No | AP2: =IF(Table1[[#This Row],[Audio Duration (in secs)]]>180,"Greater than 3 Minutes","Less than 3 Minutes") -> Greater than 3 Minutes | AQ2: =IFERROR(VLOOKUP(Table1[[#This Row],[சாதி/Caste]],MApping!$E$1:$F$10,2,0),"Others") -> URALI GOUNDER | AR2: =VLOOKUP(Table1[[#This Row],[பாலினம்/Gender]],Factor!$F$26:$I$28,4,0) -> 0.95700935 | AS2: =VLOOKUP(Table1[[#This Row],[பதிலளித்தவரின் வயது/Age Group]],Factor!$F$35:$I$39,4,0) -> 1.0951872 | AT2: =VLOOKUP(Table1[[#This Row],[பதிலளித்தவரின் வயது/Age Group]]&Table1[[#This Row],[பாலினம்/Gender]],Factor!$A$45:$G$53,7,0) -> 1.0835979 | AU2: =VLOOKUP(Table1[[#This Row],[2021 சட்டமன்றத் தேர்தலில் நீங்கள் எந்தக் கட்சிக்கு வாக்களித்தீர்கள்?/ Which party did you vote in 2021 Assembly Elections? ]],Factor!$F$9:$J$14,5,0) -> 0.73680082 | AV2: =VLOOKUP(Table1[[#This Row],[Rev Caste]],Factor!$F$59:$I$68,4,0) -> 1.0593103 | AW2: =Table1[[#This Row],[2021 Ae Factor]]*Table1[[#This Row],[Age & Gender Factor]] -> 0.79839581 | AX2: =Table1[[#This Row],[2021 Ae Factor]]*Table1[[#This Row],[Caste Factor]] -> 0.78050074 | AY2: =VALUE(MID(D2, FIND(",",D2)+2, FIND(")",D2)-FIND(",",D2)-2)) -> 78.703053
A3: DK5RFIfUeSBZOmSRQwlG | B3: 2025-07-30 13:47:12.018718 | C3: 45868 | D3: (10.4596218, 78.7023729) | E3: FP52+XV3,,Annavasal,622101,Tamil Nadu,India. | F3: https://firebasestorage.googleapis.com/v0/b/mindbrink-survey-production.appspot.com/o/audioFiles%2FAtznECuQc6klLPsRR6u2%2Fe5risFoEPidDckOLperfsZqxzae2%2F2025-07-30%2013%3A47%3A06.589839.m4a?alt=media&token=491fc27d-ed7b-4fbf-88ba-a7af8002c801 | G3: 675 | H3: false | I3: Sinthanai selvi | J3: +918508766594 | K3: Subramanian | L3: ILLUPUR | M3: ANNAVASAL | N3: raja | O3: ஆண்/Male | P3: 8675641312 | Q3: 18-30 | R3: மாணவர்/ Student | S3: 10,000 - 25,000 | T3: திருப்திகரமானது / Satisfactory | U3: ஆம் / Yes | V3: திமுக கூட்டணி / DMK Alliance | W3: மு.க. ஸ்டாலின் (திமுக) / M.K. Stalin (DMK) | X3: திமுக / DMK | Y3: Others | Z3: - | AA3: இல்லை / No | AB3: - | AC3: வேகம் குறைபாடுடன் செயல்படுகிறது / Needs more momentum | AD3: பயனில்லை / Not effective | AE3: • ஆமாம்: அதிமுக கூட்டணி உடையும்/ Yes: AIADMK alliance will break up | AF3: நாம் தமிழர் கட்சி / NTK | AG3: மதுபானம் / போதைப்பொருள் பழக்கம்/ Alcohol/Drug abuse | AH3: BC | AI3: MUKKULATHOR | AJ3: =IFERROR(_xlfn.XLOOKUP(Table1[[#This Row],[Audio Url]],Qc!C:C,Qc!F:F),"") -> they only speaking amkn6them but questions are only read | AK3: =IFERROR(_xlfn.XLOOKUP(Table1[[#This Row],[Audio Url]],Qc!C:C,Qc!E:E),"") -> Not Doing It Properly | AL3: - | AM3: - | AN3: =VLOOKUP(Table1[[#This Row],[LOCALITY]],Sheet2!$F:$H,3,0) -> Urban | AO3: Yes | AP3: =IF(Table1[[#This Row],[Audio Duration (in secs)]]>180,"Greater than 3 Minutes","Less than 3 Minutes") -> Greater than 3 Minutes | AQ3: =IFERROR(VLOOKUP(Table1[[#This Row],[சாதி/Caste]],MApping!$E$1:$F$10,2,0),"Others") -> MUKKULATHOR | AR3: =VLOOKUP(Table1[[#This Row],[பாலினம்/Gender]],Factor!$F$26:$I$28,4,0) -> 0.95700935 | AS3: =VLOOKUP(Table1[[#This Row],[பதிலளித்தவரின் வயது/Age Group]],Factor!$F$35:$I$39,4,0) -> 0.9752381 | AT3: =VLOOKUP(Table1[[#This Row],[பதிலளித்தவரின் வயது/Age Group]]&Table1[[#This Row],[பாலினம்/Gender]],Factor!$A$45:$G$53,7,0) -> 1.0666667 | AU3: =VLOOKUP(Table1[[#This Row],[2021 சட்டமன்றத் தேர்தலில் நீங்கள் எந்தக் கட்சிக்கு வாக்களித்தீர்கள்?/ Which party did you vote in 2021 Assembly Elections? ]],Factor!$F$9:$J$14,5,0) -> 0.73680082 | AV3: =VLOOKUP(Table1[[#This Row],[Rev Caste]],Factor!$F$59:$I$68,4,0) -> 1.3479184 | AW3: =Table1[[#This Row],[2021 Ae Factor]]*Table1[[#This Row],[Age & Gender Factor]] -> 0.78592088 | AX3: =Table1[[#This Row],[2021 Ae Factor]]*Table1[[#This Row],[Caste Factor]] -> 0.99314736 | AY3: =VALUE(MID(D3, FIND(",",D3)+2, FIND(")",D3)-FIND(",",D3)-2)) -> 78.702373
A4: RdafTkFtqCYc1Xw504xM | B4: 2025-07-30 14:00:49.781847 | C4: 45868 | D4: (10.4595158, 78.7023314) | E4: FP53+P33,,Purakarai Natham Pannai,622005,Tamil Nadu,India. | F4: https://firebasestorage.googleapis.com/v0/b/mindbrink-survey-production.appspot.com/o/audioFiles%2FAtznECuQc6klLPsRR6u2%2Fe5risFoEPidDckOLperfsZqxzae2%2F2025-07-30%2014%3A00%3A45.291038.m4a?alt=media&token=cecc8db3-cd5a-48ee-a3e6-d691de1219b0 | G4: 427 | H4: false | I4: Sinthanai selvi | J4: +918508766594 | K4: Subramanian | L4: ILLUPUR | M4: ANNAVASAL | N4: முருகேசன் | O4: ஆண்/Male | P4: 8012825692 | Q4: 46-60 | R4: சொந்த தொழில் / சுயதொழில் செய்பவர்/ Self Employed/Business | S4: 50,000 - 1,00,000 | T4: திருப்திகரமல்ல/ Unsatisfactory | U4: ஆம் / Yes | V4: அதிமுக கூட்டணி / AIADMK Alliance | W4: எடப்பாடி பழனிசாமி (அதிமுக) / Edappadi K. Palaniswami (AIADMK) | X4: அதிமுக / AIADMK | Y4: AIADMK | Z4: ஆம், TVK கூட்டணிக்கு வாக்களிப்பேன் / Yes, I will shift my vote to the TVK alliance | AA4: இல்லை / No | AB4: - | AC4: திருப்திகரமல்ல / Unsatisfactory | AD4: பயனில்லை / Not effective | AE4: • ஆமாம்: திமுக கூட்டணி உடையும் / Yes: DMK Alliance will break up | AF4: அதிமுக / AIADMK | AG4: விவசாய நெருக்கடி / Agricultural crisis | AH4: BC | AI4: - | AJ4: =IFERROR(_xlfn.XLOOKUP(Table1[[#This Row],[Audio Url]],Qc!C:C,Qc!F:F),"") -> same voice | AK4: =IFERROR(_xlfn.XLOOKUP(Table1[[#This Row],[Audio Url]],Qc!C:C,Qc!E:E),"") -> Taking From Friends And Family | AL4: - | AM4: - | AN4: =VLOOKUP(Table1[[#This Row],[LOCALITY]],Sheet2!$F:$H,3,0) -> Urban | AO4: No | AP4: =IF(Table1[[#This Row],[Audio Duration (in secs)]]>180,"Greater than 3 Minutes","Less than 3 Minutes") -> Greater than 3 Minutes | AQ4: =IFERROR(VLOOKUP(Table1[[#This Row],[சாதி/Caste]],MApping!$E$1:$F$10,2,0),"Others") -> Others | AR4: =VLOOKUP(Table1[[#This Row],[பாலினம்/Gender]],Factor!$F$26:$I$28,4,0) -> 0.95700935 | AS4: =VLOOKUP(Table1[[#This Row],[பதிலளித்தவரின் வயது/Age Group]],Factor!$F$35:$I$39,4,0) -> 0.87972509 | AT4: =VLOOKUP(Table1[[#This Row],[பதிலளித்தவரின் வயது/Age Group]]&Table1[[#This Row],[பாலினம்/Gender]],Factor!$A$45:$G$53,7,0) -> 0.79503106 | AU4: =VLOOKUP(Table1[[#This Row],[2021 சட்டமன்றத் தேர்தலில் நீங்கள் எந்தக் கட்சிக்கு வாக்களித்தீர்கள்?/ Which party did you vote in 2021 Assembly Elections? ]],Factor!$F$9:$J$14,5,0) -> 1.3119425 | AV4: =VLOOKUP(Table1[[#This Row],[Rev Caste]],Factor!$F$59:$I$68,4,0) -> 0.14422535 | AW4: =Table1[[#This Row],[2021 Ae Factor]]*Table1[[#This Row],[Age & Gender Factor]] -> 1.0430351 | AX4: =Table1[[#This Row],[2021 Ae Factor]]*Table1[[#This Row],[Caste Factor]] -> 0.18921537 | AY4: =VALUE(MID(D4, FIND(",",D4)+2, FIND(")",D4)-FIND(",",D4)-2)) -> 78.702331
A5: jXAWjqyIxq87qPMieuPS | B5: 2025-07-30 14:19:29.593894 | C5: 45868 | D5: (10.4623883, 78.6815105) | E5: FM6J+JHW,,Pudukkottai,622103,Tamil Nadu,India. | F5: https://firebasestorage.googleapis.com/v0/b/mindbrink-survey-production.appspot.com/o/audioFiles%2FAtznECuQc6klLPsRR6u2%2F2ukCmICpvKWhqTT6dgmjG6nFGjc2%2F2025-07-30%2014%3A19%3A23.528277.m4a?alt=media&token=2a8a1c48-d5a0-40e2-b2c9-f58e1c5cbbb7 | G5: 347 | H5: false | I5: U.Amir nisha | J5: +919698565662 | K5: Subramanian | L5: ILLUPUR | M5: MUKKANNAMALAIPATTI | N5: Rathinam | O5: ஆண்/Male | P5: 8012352247 | Q5: 31-45 | R5: கூலி தொழில்/ Daily Wage | S5: 10,000க்கும் குறைவானது/Less than 10,000 | T5: திருப்திகரமல்ல/ Unsatisfactory | U5: ஆம் / Yes | V5: திமுக கூட்டணி / DMK Alliance | W5: விஜய் (தமிழக வெற்றி கழகம்) / Vijay (TVK) | X5: தமிழக வெற்றி கழகம் / TVK | Y5: TVK | Z5: - | AA5: இல்லை / No | AB5: - | AC5: வேகம் குறைபாடுடன் செயல்படுகிறது / Needs more momentum | AD5: குறைவான ஈடுபாடு / Inadequate | AE5: • ஆமாம்: திமுக மற்றும் அதிமுக கூட்டணிகள் இரண்டும் உடையும்/ Yes: Both DMK & AIADMK alliances will break up | AF5: தனித்துப் போட்டியிட வேண்டும் / Contest Independently | AG5: வேலைவாய்ப்பு குறைபாடு / Unemployment | AH5: SC | AI5: PALLAR SC | AJ5: =IFERROR(_xlfn.XLOOKUP(Table1[[#This Row],[Audio Url]],Qc!C:C,Qc!F:F),"") -> same voice | AK5: =IFERROR(_xlfn.XLOOKUP(Table1[[#This Row],[Audio Url]],Qc!C:C,Qc!E:E),"") -> Taking From Friends And Family | AL5: - | AM5: - | AN5: =VLOOKUP(Table1[[#This Row],[LOCALITY]],Sheet2!$F:$H,3,0) -> Rural | AO5: No | AP5: =IF(Table1[[#This Row],[Audio Duration (in secs)]]>180,"Greater than 3 Minutes","Less than 3 Minutes") -> Greater than 3 Minutes | AQ5: =IFERROR(VLOOKUP(Table1[[#This Row],[சாதி/Caste]],MApping!$E$1:$F$10,2,0),"Others") -> PALLAR SC | AR5: =VLOOKUP(Table1[[#This Row],[பாலினம்/Gender]],Factor!$F$26:$I$28,4,0) -> 0.95700935 | AS5: =VLOOKUP(Table1[[#This Row],[பதிலளித்தவரின் வயது/Age Group]],Factor!$F$35:$I$39,4,0) -> 1.0951872 | AT5: =VLOOKUP(Table1[[#This Row],[பதிலளித்தவரின் வயது/Age Group]]&Table1[[#This Row],[பாலினம்/Gender]],Factor!$A$45:$G$53,7,0) -> 1.0835979 | AU5: =VLOOKUP(Table1[[#This Row],[2021 சட்டமன்றத் தேர்தலில் நீங்கள் எந்தக் கட்சிக்கு வாக்களித்தீர்கள்?/ Which party did you vote in 2021 Assembly Elections? ]],Factor!$F$9:$J$14,5,0) -> 0.73680082 | AV5: =VLOOKUP(Table1[[#This Row],[Rev Caste]],Factor!$F$59:$I$68,4,0) -> 1.28 | AW5: =Table1[[#This Row],[2021 Ae Factor]]*Table1[[#This Row],[Age & Gender Factor]] -> 0.79839581 | AX5: =Table1[[#This Row],[2021 Ae Factor]]*Table1[[#This Row],[Caste Factor]] -> 0.94310506 | AY5: =VALUE(MID(D5, FIND(",",D5)+2, FIND(")",D5)-FIND(",",D5)-2)) -> 78.681511
A6: inwjrr2qGauklkuB5CLS | B6: 2025-07-30 14:26:30.602916 | C6: 45868 | D6: (10.4623704, 78.681544) | E6: FM6J+JHW,,Pudukkottai,622103,Tamil Nadu,India. | F6: https://firebasestorage.googleapis.com/v0/b/mindbrink-survey-production.appspot.com/o/audioFiles%2FAtznECuQc6klLPsRR6u2%2F2ukCmICpvKWhqTT6dgmjG6nFGjc2%2F2025-07-30%2014%3A26%3A24.415606.m4a?alt=media&token=94a2343f-ce0d-4c6c-812f-f12d4d988ffa | G6: 301 | H6: false | I6: U.Amir nisha | J6: +919698565662 | K6: Subramanian | L6: ILLUPUR | M6: MUKKANNAMALAIPATTI | N6: Albert Xavier | O6: ஆண்/Male | P6: 7708200630 | Q6: 31-45 | R6: விவசாயி/ Farmer | S6: 10,000க்கும் குறைவானது/Less than 10,000 | T6: திருப்திகரமல்ல/ Unsatisfactory | U6: ஆம் / Yes | V6: திமுக கூட்டணி / DMK Alliance | W6: விஜய் (தமிழக வெற்றி கழகம்) / Vijay (TVK) | X6: அதிமுக / AIADMK | Y6: TVK | Z6: ஆம், TVK கூட்டணிக்கு வாக்களிப்பேன் / Yes, I will shift my vote to the TVK alliance | AA6: ஆமாம் / Yes | AB6: திமுக கூட்டணி / DMK Alliance | AC6: வேகம் குறைபாடுடன் செயல்படுகிறது / Needs more momentum | AD6: போதுமான ஈடுபாடு / Adequate | AE6: • ஆமாம்: திமுக மற்றும் அதிமுக கூட்டணிகள் இரண்டும் உடையும்/ Yes: Both DMK & AIADMK alliances will break up | AF6: தே.மு.தி.க / DMDK | AG6: விவசாய நெருக்கடி / Agricultural crisis | AH6: BC | AI6: CHRISTIAN | AJ6: =IFERROR(_xlfn.XLOOKUP(Table1[[#This Row],[Audio Url]],Qc!C:C,Qc!F:F),"") -> same voice | AK6: =IFERROR(_xlfn.XLOOKUP(Table1[[#This Row],[Audio Url]],Qc!C:C,Qc!E:E),"") -> Taking From Friends And Family | AL6: - | AM6: - | AN6: =VLOOKUP(Table1[[#This Row],[LOCALITY]],Sheet2!$F:$H,3,0) -> Rural | AO6: No | AP6: =IF(Table1[[#This Row],[Audio Duration (in secs)]]>180,"Greater than 3 Minutes","Less than 3 Minutes") -> Greater than 3 Minutes | AQ6: =IFERROR(VLOOKUP(Table1[[#This Row],[சாதி/Caste]],MApping!$E$1:$F$10,2,0),"Others") -> CHRISTIAN | AR6: =VLOOKUP(Table1[[#This Row],[பாலினம்/Gender]],Factor!$F$26:$I$28,4,0) -> 0.95700935 | AS6: =VLOOKUP(Table1[[#This Row],[பதிலளித்தவரின் வயது/Age Group]],Factor!$F$35:$I$39,4,0) -> 1.0951872 | AT6: =VLOOKUP(Table1[[#This Row],[பதிலளித்தவரின் வயது/Age Group]]&Table1[[#This Row],[பாலினம்/Gender]],Factor!$A$45:$G$53,7,0) -> 1.0835979 | AU6: =VLOOKUP(Table1[[#This Row],[2021 சட்டமன்றத் தேர்தலில் நீங்கள் எந்தக் கட்சிக்கு வாக்களித்தீர்கள்?/ Which party did you vote in 2021 Assembly Elections? ]],Factor!$F$9:$J$14,5,0) -> 0.73680082 | AV6: =VLOOKUP(Table1[[#This Row],[Rev Caste]],Factor!$F$59:$I$68,4,0) -> 0.93090909 | AW6: =Table1[[#This Row],[2021 Ae Factor]]*Table1[[#This Row],[Age & Gender Factor]] -> 0.79839581 | AX6: =Table1[[#This Row],[2021 Ae Factor]]*Table1[[#This Row],[Caste Factor]] -> 0.68589459 | AY6: =VALUE(MID(D6, FIND(",",D6)+2, FIND(")",D6)-FIND(",",D6)-2)) -> 78.681544
A7: oYxHjk6VwK6zG0z9HzLl | B7: 2025-07-30 14:35:10.789469 | C7: 45868 | D7: (10.4623843, 78.6815277) | E7: FM6J+JHW,,Pudukkottai,622103,Tamil Nadu,India. | F7: https://firebasestorage.googleapis.com/v0/b/mindbrink-survey-production.appspot.com/o/audioFiles%2FAtznECuQc6klLPsRR6u2%2F2ukCmICpvKWhqTT6dgmjG6nFGjc2%2F2025-07-30%2014%3A35%3A02.869454.m4a?alt=media&token=66fec1a3-fae7-4769-b641-1ce8faff9d0d | G7: 269 | H7: false | I7: U.Amir nisha | J7: +919698565662 | K7: Subramanian | L7: ILLUPUR | M7: MUKKANNAMALAIPATTI | N7: Jaya | O7: பெண்/Female | P7: 8807414653 | Q7: 31-45 | R7: இல்லத்தரசி/ Housewife | S7: 10,000க்கும் குறைவானது/Less than 10,000 | T7: மேம்பாடு தேவை / Needs improvement | U7: ஆம் / Yes | V7: அதிமுக கூட்டணி / AIADMK Alliance | W7: மு.க. ஸ்டாலின் (திமுக) / M.K. Stalin (DMK) | X7: திமுக / DMK | Y7: DMK | Z7: - | AA7: ஆமாம் / Yes | AB7: பிறவை / Others | AC7: திருப்திகரமானது / Satisfactory | AD7: போதுமான ஈடுபாடு / Adequate | AE7: • ஆமாம்: திமுக கூட்டணி உடையும் / Yes: DMK Alliance will break up | AF7: தனித்துப் போட்டியிட வேண்டும் / Contest Independently | AG7: மதுபானம் / போதைப்பொருள் பழக்கம்/ Alcohol/Drug abuse | AH7: BC | AI7: CHRISTIAN | AJ7: =IFERROR(_xlfn.XLOOKUP(Table1[[#This Row],[Audio Url]],Qc!C:C,Qc!F:F),"") -> 0 | AK7: =IFERROR(_xlfn.XLOOKUP(Table1[[#This Row],[Audio Url]],Qc!C:C,Qc!E:E),"") -> Correctly Done | AL7: - | AM7: - | AN7: =VLOOKUP(Table1[[#This Row],[LOCALITY]],Sheet2!$F:$H,3,0) -> Rural | AO7: Yes | AP7: =IF(Table1[[#This Row],[Audio Duration (in secs)]]>180,"Greater than 3 Minutes","Less than 3 Minutes") -> Greater than 3 Minutes | AQ7: =IFERROR(VLOOKUP(Table1[[#This Row],[சாதி/Caste]],MApping!$E$1:$F$10,2,0),"Others") -> CHRISTIAN | AR7: =VLOOKUP(Table1[[#This Row],[பாலினம்/Gender]],Factor!$F$26:$I$28,4,0) -> 1.0470348 | AS7: =VLOOKUP(Table1[[#This Row],[பதிலளித்தவரின் வயது/Age Group]],Factor!$F$35:$I$39,4,0) -> 1.0951872 | AT7: =VLOOKUP(Table1[[#This Row],[பதிலளித்தவரின் வயது/Age Group]]&Table1[[#This Row],[பாலினம்/Gender]],Factor!$A$45:$G$53,7,0) -> 1.107027 | AU7: =VLOOKUP(Table1[[#This Row],[2021 சட்டமன்றத் தேர்தலில் நீங்கள் எந்தக் கட்சிக்கு வாக்களித்தீர்கள்?/ Which party did you vote in 2021 Assembly Elections? ]],Factor!$F$9:$J$14,5,0) -> 1.3119425 | AV7: =VLOOKUP(Table1[[#This Row],[Rev Caste]],Factor!$F$59:$I$68,4,0) -> 0.93090909 | AW7: =Table1[[#This Row],[2021 Ae Factor]]*Table1[[#This Row],[Age & Gender Factor]] -> 1.4523558 | AX7: =Table1[[#This Row],[2021 Ae Factor]]*Table1[[#This Row],[Caste Factor]] -> 1.2212992 | AY7: =VALUE(MID(D7, FIND(",",D7)+2, FIND(")",D7)-FIND(",",D7)-2)) -> 78.681528
A8: wEykrB7PWmMFbpcLSh29 | B8: 2025-07-30 14:42:51.078465 | C8: 45868 | D8: (10.462279, 78.6809876) | E8: FM6J+JHW,,Pudukkottai,622103,Tamil Nadu,India. | F8: https://firebasestorage.googleapis.com/v0/b/mindbrink-survey-production.appspot.com/o/audioFiles%2FAtznECuQc6klLPsRR6u2%2F2ukCmICpvKWhqTT6dgmjG6nFGjc2%2F2025-07-30%2014%3A42%3A42.625814.m4a?alt=media&token=aa21e8ba-da98-4d18-8f39-886502c10bef | G8: 331 | H8: false | I8: U.Amir nisha | J8: +919698565662 | K8: Subramanian | L8: ILLUPUR | M8: MUKKANNAMALAIPATTI | N8: Jesuthas | O8: ஆண்/Male | P8: 8973759103 | Q8: 46-60 | R8: கூலி தொழில்/ Daily Wage | S8: 10,000க்கும் குறைவானது/Less than 10,000 | T8: திருப்திகரமல்ல/ Unsatisfactory | U8: ஆம் / Yes | V8: திமுக கூட்டணி / DMK Alliance | W8: எடப்பாடி பழனிசாமி (அதிமுக) / Edappadi K. Palaniswami (AIADMK) | X8: திமுக / DMK | Y8: DMK | Z8: - | AA8: ஆமாம் / Yes | AB8: அதிமுக கூட்டணி / AIADMK Alliance | AC8: திருப்திகரமல்ல / Unsatisfactory | AD8: குறைவான ஈடுபாடு / Inadequate | AE8: • ஆமாம்: திமுக மற்றும் அதிமுக கூட்டணிகள் இரண்டும் உடையும்/ Yes: Both DMK & AIADMK alliances will break up | AF8: அதிமுக / AIADMK | AG8: விவசாய நெருக்கடி / Agricultural crisis | AH8: SC | AI8: CHRISTIAN | AJ8: =IFERROR(_xlfn.XLOOKUP(Table1[[#This Row],[Audio Url]],Qc!C:C,Qc!F:F),"") -> 0 | AK8: =IFERROR(_xlfn.XLOOKUP(Table1[[#This Row],[Audio Url]],Qc!C:C,Qc!E:E),"") -> Correctly Done | AL8: - | AM8: - | AN8: =VLOOKUP(Table1[[#This Row],[LOCALITY]],Sheet2!$F:$H,3,0) -> Rural | AO8: Yes | AP8: =IF(Table1[[#This Row],[Audio Duration (in secs)]]>180,"Greater than 3 Minutes","Less than 3 Minutes") -> Greater than 3 Minutes | AQ8: =IFERROR(VLOOKUP(Table1[[#This Row],[சாதி/Caste]],MApping!$E$1:$F$10,2,0),"Others") -> CHRISTIAN | AR8: =VLOOKUP(Table1[[#This Row],[பாலினம்/Gender]],Factor!$F$26:$I$28,4,0) -> 0.95700935 | AS8: =VLOOKUP(Table1[[#This Row],[பதிலளித்தவரின் வயது/Age Group]],Factor!$F$35:$I$39,4,0) -> 0.87972509 | AT8: =VLOOKUP(Table1[[#This Row],[பதிலளித்தவரின் வயது/Age Group]]&Table1[[#This Row],[பாலினம்/Gender]],Factor!$A$45:$G$53,7,0) -> 0.79503106 | AU8: =VLOOKUP(Table1[[#This Row],[2021 சட்டமன்றத் தேர்தலில் நீங்கள் எந்தக் கட்சிக்கு வாக்களித்தீர்கள்?/ Which party did you vote in 2021 Assembly Elections? ]],Factor!$F$9:$J$14,5,0) -> 0.73680082 | AV8: =VLOOKUP(Table1[[#This Row],[Rev Caste]],Factor!$F$59:$I$68,4,0) -> 0.93090909 | AW8: =Table1[[#This Row],[2021 Ae Factor]]*Table1[[#This Row],[Age & Gender Factor]] -> 0.58577954 | AX8: =Table1[[#This Row],[2021 Ae Factor]]*Table1[[#This Row],[Caste Factor]] -> 0.68589459 | AY8: =VALUE(MID(D8, FIND(",",D8)+2, FIND(")",D8)-FIND(",",D8)-2)) -> 78.680988
A9: u9XGRvPU08lptw83iYlu | B9: 2025-07-30 14:51:49.473078 | C9: 45868 | D9: (10.4623531, 78.6809325) | E9: FM6J+JHW,,Pudukkottai,622103,Tamil Nadu,India. | F9: https://firebasestorage.googleapis.com/v0/b/mindbrink-survey-production.appspot.com/o/audioFiles%2FAtznECuQc6klLPsRR6u2%2F2ukCmICpvKWhqTT6dgmjG6nFGjc2%2F2025-07-30%2014%3A51%3A43.908029.m4a?alt=media&token=483045d4-e721-4bd9-870a-817b0e8046be | G9: 274 | H9: false | I9: U.Amir nisha | J9: +919698565662 | K9: Subramanian | L9: ILLUPUR | M9: MUKKANNAMALAIPATTI | N9: Jayamary | O9: பெண்/Female | P9: 9578493153 | Q9: 31-45 | R9: கூலி தொழில்/ Daily Wage | S9: 10,000க்கும் குறைவானது/Less than 10,000 | T9: திருப்திகரமானது / Satisfactory | U9: ஆம் / Yes | V9: அதிமுக கூட்டணி / AIADMK Alliance | W9: மு.க. ஸ்டாலின் (திமுக) / M.K. Stalin (DMK) | X9: அதிமுக / AIADMK | Y9: AIADMK | Z9: ஆம், TVK கூட்டணிக்கு வாக்களிப்பேன் / Yes, I will shift my vote to the TVK alliance | AA9: இல்லை / No | AB9: - | AC9: வேகம் குறைபாடுடன் செயல்படுகிறது / Needs more momentum | AD9: போதுமான ஈடுபாடு / Adequate | AE9: • ஆமாம்: திமுக மற்றும் அதிமுக கூட்டணிகள் இரண்டும் உடையும்/ Yes: Both DMK & AIADMK alliances will break up | AF9: அதிமுக / AIADMK | AG9: விவசாய நெருக்கடி / Agricultural crisis | AH9: SC | AI9: CHRISTIAN | AJ9: =IFERROR(_xlfn.XLOOKUP(Table1[[#This Row],[Audio Url]],Qc!C:C,Qc!F:F),"") -> 0 | AK9: =IFERROR(_xlfn.XLOOKUP(Table1[[#This Row],[Audio Url]],Qc!C:C,Qc!E:E),"") -> Correctly Done | AL9: - | AM9: - | AN9: =VLOOKUP(Table1[[#This Row],[LOCALITY]],Sheet2!$F:$H,3,0) -> Rural | AO9: Yes | AP9: =IF(Table1[[#This Row],[Audio Duration (in secs)]]>180,"Greater than 3 Minutes","Less than 3 Minutes") -> Greater than 3 Minutes | AQ9: =IFERROR(VLOOKUP(Table1[[#This Row],[சாதி/Caste]],MApping!$E$1:$F$10,2,0),"Others") -> CHRISTIAN | AR9: =VLOOKUP(Table1[[#This Row],[பாலினம்/Gender]],Factor!$F$26:$I$28,4,0) -> 1.0470348 | AS9: =VLOOKUP(Table1[[#This Row],[பதிலளித்தவரின் வயது/Age Group]],Factor!$F$35:$I$39,4,0) -> 1.0951872 | AT9: =VLOOKUP(Table1[[#This Row],[பதிலளித்தவரின் வயது/Age Group]]&Table1[[#This Row],[பாலினம்/Gender]],Factor!$A$45:$G$53,7,0) -> 1.107027 | AU9: =VLOOKUP(Table1[[#This Row],[2021 சட்டமன்றத் தேர்தலில் நீங்கள் எந்தக் கட்சிக்கு வாக்களித்தீர்கள்?/ Which party did you vote in 2021 Assembly Elections? ]],Factor!$F$9:$J$14,5,0) -> 1.3119425 | AV9: =VLOOKUP(Table1[[#This Row],[Rev Caste]],Factor!$F$59:$I$68,4,0) -> 0.93090909 | AW9: =Table1[[#This Row],[2021 Ae Factor]]*Table1[[#This Row],[Age & Gender Factor]] -> 1.4523558 | AX9: =Table1[[#This Row],[2021 Ae Factor]]*Table1[[#This Row],[Caste Factor]] -> 1.2212992 | AY9: =VALUE(MID(D9, FIND(",",D9)+2, FIND(")",D9)-FIND(",",D9)-2)) -> 78.680932
A10: e6ac5EItzYfOFpBKRvtE | B10: 2025-07-30 14:56:26.558863 | C10: 45868 | D10: (10.4621783, 78.6809415) | E10: FM6J+JHW,,Pudukkottai,622103,Tamil Nadu,India. | F10: https://firebasestorage.googleapis.com/v0/b/mindbrink-survey-production.appspot.com/o/audioFiles%2FAtznECuQc6klLPsRR6u2%2F2ukCmICpvKWhqTT6dgmjG6nFGjc2%2F2025-07-30%2014%3A56%3A20.571686.m4a?alt=media&token=09e17480-5dfc-4cff-9135-47f53823b27a | G10: 233 | H10: false | I10: U.Amir nisha | J10: +919698565662 | K10: Subramanian | L10: ILLUPUR | M10: MUKKANNAMALAIPATTI | N10: Arokiya shalini | O10: பெண்/Female | P10: 6384537452 | Q10: 18-30 | R10: இல்லத்தரசி/ Housewife | S10: 10,000க்கும் குறைவானது/Less than 10,000 | T10: மேம்பாடு தேவை / Needs improvement | U10: ஆம் / Yes | V10: திமுக கூட்டணி / DMK Alliance | W10: விஜய் (தமிழக வெற்றி கழகம்) / Vijay (TVK) | X10: திமுக / DMK | Y10: DMK | Z10: - | AA10: ஆமாம் / Yes | AB10: திமுக கூட்டணி / DMK Alliance | AC10: வேகம் குறைபாடுடன் செயல்படுகிறது / Needs more momentum | AD10: போதுமான ஈடுபாடு / Adequate | AE10: • ஆமாம்: திமுக மற்றும் அதிமுக கூட்டணிகள் இரண்டும் உடையும்/ Yes: Both DMK & AIADMK alliances will break up | AF10: தனித்துப் போட்டியிட வேண்டும் / Contest Independently | AG10: விவசாய நெருக்கடி / Agricultural crisis | AH10: SC | AI10: CHRISTIAN | AJ10: =IFERROR(_xlfn.XLOOKUP(Table1[[#This Row],[Audio Url]],Qc!C:C,Qc!F:F),"") | AK10: =IFERROR(_xlfn.XLOOKUP(Table1[[#This Row],[Audio Url]],Qc!C:C,Qc!E:E),"") | AL10: - | AM10: - | AN10: =VLOOKUP(Table1[[#This Row],[LOCALITY]],Sheet2!$F:$H,3,0) -> Rural | AO10: Yes | AP10: =IF(Table1[[#This Row],[Audio Duration (in secs)]]>180,"Greater than 3 Minutes","Less than 3 Minutes") -> Greater than 3 Minutes | AQ10: =IFERROR(VLOOKUP(Table1[[#This Row],[சாதி/Caste]],MApping!$E$1:$F$10,2,0),"Others") -> CHRISTIAN | AR10: =VLOOKUP(Table1[[#This Row],[பாலினம்/Gender]],Factor!$F$26:$I$28,4,0) -> 1.0470348 | AS10: =VLOOKUP(Table1[[#This Row],[பதிலளித்தவரின் வயது/Age Group]],Factor!$F$35:$I$39,4,0) -> 0.9752381 | AT10: =VLOOKUP(Table1[[#This Row],[பதிலளித்தவரின் வயது/Age Group]]&Table1[[#This Row],[பாலினம்/Gender]],Factor!$A$45:$G$53,7,0) -> 0.89824561 | AU10: =VLOOKUP(Table1[[#This Row],[2021 சட்டமன்றத் தேர்தலில் நீங்கள் எந்தக் கட்சிக்கு வாக்களித்தீர்கள்?/ Which party did you vote in 2021 Assembly Elections? ]],Factor!$F$9:$J$14,5,0) -> 0.73680082 | AV10: =VLOOKUP(Table1[[#This Row],[Rev Caste]],Factor!$F$59:$I$68,4,0) -> 0.93090909 | AW10: =Table1[[#This Row],[2021 Ae Factor]]*Table1[[#This Row],[Age & Gender Factor]] -> 0.66182811 | AX10: =Table1[[#This Row],[2021 Ae Factor]]*Table1[[#This Row],[Caste Factor]] -> 0.68589459 | AY10: =VALUE(MID(D10, FIND(",",D10)+2, FIND(")",D10)-FIND(",",D10)-2)) -> 78.680942
A11: E0uszhEvnSbx6OhSMH4r | B11: 2025-07-30 15:02:09.334115 | C11: 45868 | D11: (10.462594, 78.6806822) | E11: FM7J+89V,,Madakoil,622103,Tamil Nadu,India. | F11: https://firebasestorage.googleapis.com/v0/b/mindbrink-survey-production.appspot.com/o/audioFiles%2FAtznECuQc6klLPsRR6u2%2F2ukCmICpvKWhqTT6dgmjG6nFGjc2%2F2025-07-30%2015%3A02%3A02.380467.m4a?alt=media&token=81f317a8-fb8d-43d3-859d-4d0a1d121306 | G11: 187 | H11: false | I11: U.Amir nisha | J11: +919698565662 | K11: Subramanian | L11: ILLUPUR | M11: MUKKANNAMALAIPATTI | N11: sivanthai | O11: பெண்/Female | P11: 9715185244 | Q11: 46-60 | R11: இல்லத்தரசி/ Housewife | S11: 10,000க்கும் குறைவானது/Less than 10,000 | T11: மேம்பாடு தேவை / Needs improvement | U11: ஆம் / Yes | V11: திமுக கூட்டணி / DMK Alliance | W11: விஜய் (தமிழக வெற்றி கழகம்) / Vijay (TVK) | X11: திமுக / DMK | Y11: DMK | Z11: - | AA11: ஆமாம் / Yes | AB11: திமுக கூட்டணி / DMK Alliance | AC11: வேகம் குறைபாடுடன் செயல்படுகிறது / Needs more momentum | AD11: குறைவான ஈடுபாடு / Inadequate | AE11: • ஆமாம்: திமுக மற்றும் அதிமுக கூட்டணிகள் இரண்டும் உடையும்/ Yes: Both DMK & AIADMK alliances will break up | AF11: தனித்துப் போட்டியிட வேண்டும் / Contest Independently | AG11: வேலைவாய்ப்பு குறைபாடு / Unemployment | AH11: SC | AI11: CHRISTIAN | AJ11: =IFERROR(_xlfn.XLOOKUP(Table1[[#This Row],[Audio Url]],Qc!C:C,Qc!F:F),"") | AK11: =IFERROR(_xlfn.XLOOKUP(Table1[[#This Row],[Audio Url]],Qc!C:C,Qc!E:E),"") | AL11: - | AM11: - | AN11: =VLOOKUP(Table1[[#This Row],[LOCALITY]],Sheet2!$F:$H,3,0) -> Rural | AO11: Yes | AP11: =IF(Table1[[#This Row],[Audio Duration (in secs)]]>180,"Greater than 3 Minutes","Less than 3 Minutes") -> Greater than 3 Minutes | AQ11: =IFERROR(VLOOKUP(Table1[[#This Row],[சாதி/Caste]],MApping!$E$1:$F$10,2,0),"Others") -> CHRISTIAN | AR11: =VLOOKUP(Table1[[#This Row],[பாலினம்/Gender]],Factor!$F$26:$I$28,4,0) -> 1.0470348 | AS11: =VLOOKUP(Table1[[#This Row],[பதிலளித்தவரின் வயது/Age Group]],Factor!$F$35:$I$39,4,0) -> 0.87972509 | AT11: =VLOOKUP(Table1[[#This Row],[பதிலளித்தவரின் வயது/Age Group]]&Table1[[#This Row],[பாலினம்/Gender]],Factor!$A$45:$G$53,7,0) -> 0.98461538 | AU11: =VLOOKUP(Table1[[#This Row],[2021 சட்டமன்றத் தேர்தலில் நீங்கள் எந்தக் கட்சிக்கு வாக்களித்தீர்கள்?/ Which party did you vote in 2021 Assembly Elections? ]],Factor!$F$9:$J$14,5,0) -> 0.73680082 | AV11: =VLOOKUP(Table1[[#This Row],[Rev Caste]],Factor!$F$59:$I$68,4,0) -> 0.93090909 | AW11: =Table1[[#This Row],[2021 Ae Factor]]*Table1[[#This Row],[Age & Gender Factor]] -> 0.72546543 | AX11: =Table1[[#This Row],[2021 Ae Factor]]*Table1[[#This Row],[Caste Factor]] -> 0.68589459 | AY11: =VALUE(MID(D11, FIND(",",D11)+2, FIND(")",D11)-FIND(",",D11)-2)) -> 78.680682
A12: BhxdqOskEmCZ304Pnoub | B12: 2025-07-30 15:10:51.958258 | C12: 45868 | D12: (10.4629467, 78.6810732) | E12: FM7J+89V,,Madakoil,622103,Tamil Nadu,India. | F12: https://firebasestorage.googleapis.com/v0/b/mindbrink-survey-production.appspot.com/o/audioFiles%2FAtznECuQc6klLPsRR6u2%2F2ukCmICpvKWhqTT6dgmjG6nFGjc2%2F2025-07-30%2015%3A10%3A39.624126.m4a?alt=media&token=d885f812-189d-4fd3-8103-6594736f083c | G12: 437 | H12: false | I12: U.Amir nisha | J12: +919698565662 | K12: Subramanian | L12: ILLUPUR | M12: MUKKANNAMALAIPATTI | N12: jansi rani | O12: பெண்/Female | P12: 8012952924 | Q12: 18-30 | R12: இல்லத்தரசி/ Housewife | S12: 10,000க்கும் குறைவானது/Less than 10,000 | T12: மேம்பாடு தேவை / Needs improvement | U12: ஆம் / Yes | V12: நினைவில் இல்லை / Don’t Remember | W12: விஜய் (தமிழக வெற்றி கழகம்) / Vijay (TVK) | X12: திமுக / DMK | Y12: DMK | Z12: - | AA12: ஆமாம் / Yes | AB12: திமுக கூட்டணி / DMK Alliance | AC12: வேகம் குறைபாடுடன் செயல்படுகிறது / Needs more momentum | AD12: குறைவான ஈடுபாடு / Inadequate | AE12: • ஆமாம்: திமுக மற்றும் அதிமுக கூட்டணிகள் இரண்டும் உடையும்/ Yes: Both DMK & AIADMK alliances will break up | AF12: தனித்துப் போட்டியிட வேண்டும் / Contest Independently | AG12: மதுபானம் / போதைப்பொருள் பழக்கம்/ Alcohol/Drug abuse | AH12: SC | AI12: CHRISTIAN | AJ12: =IFERROR(_xlfn.XLOOKUP(Table1[[#This Row],[Audio Url]],Qc!C:C,Qc!F:F),"") -> 0 | AK12: =IFERROR(_xlfn.XLOOKUP(Table1[[#This Row],[Audio Url]],Qc!C:C,Qc!E:E),"") -> Correctly Done | AL12: - | AM12: - | AN12: =VLOOKUP(Table1[[#This Row],[LOCALITY]],Sheet2!$F:$H,3,0) -> Rural | AO12: Yes | AP12: =IF(Table1[[#This Row],[Audio Duration (in secs)]]>180,"Greater than 3 Minutes","Less than 3 Minutes") -> Greater than 3 Minutes | AQ12: =IFERROR(VLOOKUP(Table1[[#This Row],[சாதி/Caste]],MApping!$E$1:$F$10,2,0),"Others") -> CHRISTIAN | AR12: =VLOOKUP(Table1[[#This Row],[பாலினம்/Gender]],Factor!$F$26:$I$28,4,0) -> 1.0470348 | AS12: =VLOOKUP(Table1[[#This Row],[பதிலளித்தவரின் வயது/Age Group]],Factor!$F$35:$I$39,4,0) -> 0.9752381 | AT12: =VLOOKUP(Table1[[#This Row],[பதிலளித்தவரின் வயது/Age Group]]&Table1[[#This Row],[பாலினம்/Gender]],Factor!$A$45:$G$53,7,0) -> 0.89824561 | AU12: =VLOOKUP(Table1[[#This Row],[2021 சட்டமன்றத் தேர்தலில் நீங்கள் எந்தக் கட்சிக்கு வாக்களித்தீர்கள்?/ Which party did you vote in 2021 Assembly Elections? ]],Factor!$F$9:$J$14,5,0) -> 1 | AV12: =VLOOKUP(Table1[[#This Row],[Rev Caste]],Factor!$F$59:$I$68,4,0) -> 0.93090909 | AW12: =Table1[[#This Row],[2021 Ae Factor]]*Table1[[#This Row],[Age & Gender Factor]] -> 0.89824561 | AX12: =Table1[[#This Row],[2021 Ae Factor]]*Table1[[#This Row],[Caste Factor]] -> 0.93090909 | AY12: =VALUE(MID(D12, FIND(",",D12)+2, FIND(")",D12)-FIND(",",D12)-2)) -> 78.681073
A13: LtwsC8GYqQizC0FxeuxW | B13: 2025-07-30 15:14:56.602348 | C13: 45868 | D13: (10.4628599, 78.6808137) | E13: FM7J+89V,,Madakoil,622103,Tamil Nadu,India. | F13: https://firebasestorage.googleapis.com/v0/b/mindbrink-survey-production.appspot.com/o/audioFiles%2FAtznECuQc6klLPsRR6u2%2F2ukCmICpvKWhqTT6dgmjG6nFGjc2%2F2025-07-30%2015%3A14%3A48.563168.m4a?alt=media&token=e6b48caf-67ad-4c1d-aadf-d84204f505a0 | G13: 203 | H13: false | I13: U.Amir nisha | J13: +919698565662 | K13: Subramanian | L13: ILLUPUR | M13: MUKKANNAMALAIPATTI | N13: Arulselvi | O13: பெண்/Female | P13: 9843601161 | Q13: 18-30 | R13: இல்லத்தரசி/ Housewife | S13: 10,000க்கும் குறைவானது/Less than 10,000 | T13: திருப்திகரமானது / Satisfactory | U13: ஆம் / Yes | V13: திமுக கூட்டணி / DMK Alliance | W13: மு.க. ஸ்டாலின் (திமுக) / M.K. Stalin (DMK) | X13: திமுக / DMK | Y13: DMK | Z13: - | AA13: ஆமாம் / Yes | AB13: அதிமுக கூட்டணி / AIADMK Alliance | AC13: திருப்திகரமல்ல / Unsatisfactory | AD13: குறைவான ஈடுபாடு / Inadequate | AE13: • ஆமாம்: அதிமுக கூட்டணி உடையும்/ Yes: AIADMK alliance will break up | AF13: தனித்துப் போட்டியிட வேண்டும் / Contest Independently | AG13: விவசாய நெருக்கடி / Agricultural crisis | AH13: SC | AI13: CHRISTIAN | AJ13: =IFERROR(_xlfn.XLOOKUP(Table1[[#This Row],[Audio Url]],Qc!C:C,Qc!F:F),"") -> same voice | AK13: =IFERROR(_xlfn.XLOOKUP(Table1[[#This Row],[Audio Url]],Qc!C:C,Qc!E:E),"") -> Taking From Friends And Family | AL13: - | AM13: - | AN13: =VLOOKUP(Table1[[#This Row],[LOCALITY]],Sheet2!$F:$H,3,0) -> Rural | AO13: No | AP13: =IF(Table1[[#This Row],[Audio Duration (in secs)]]>180,"Greater than 3 Minutes","Less than 3 Minutes") -> Greater than 3 Minutes | AQ13: =IFERROR(VLOOKUP(Table1[[#This Row],[சாதி/Caste]],MApping!$E$1:$F$10,2,0),"Others") -> CHRISTIAN | AR13: =VLOOKUP(Table1[[#This Row],[பாலினம்/Gender]],Factor!$F$26:$I$28,4,0) -> 1.0470348 | AS13: =VLOOKUP(Table1[[#This Row],[பதிலளித்தவரின் வயது/Age Group]],Factor!$F$35:$I$39,4,0) -> 0.9752381 | AT13: =VLOOKUP(Table1[[#This Row],[பதிலளித்தவரின் வயது/Age Group]]&Table1[[#This Row],[பாலினம்/Gender]],Factor!$A$45:$G$53,7,0) -> 0.89824561 | AU13: =VLOOKUP(Table1[[#This Row],[2021 சட்டமன்றத் தேர்தலில் நீங்கள் எந்தக் கட்சிக்கு வாக்களித்தீர்கள்?/ Which party did you vote in 2021 Assembly Elections? ]],Factor!$F$9:$J$14,5,0) -> 0.73680082 | AV13: =VLOOKUP(Table1[[#This Row],[Rev Caste]],Factor!$F$59:$I$68,4,0) -> 0.93090909 | AW13: =Table1[[#This Row],[2021 Ae Factor]]*Table1[[#This Row],[Age & Gender Factor]] -> 0.66182811 | AX13: =Table1[[#This Row],[2021 Ae Factor]]*Table1[[#This Row],[Caste Factor]] -> 0.68589459 | AY13: =VALUE(MID(D13, FIND(",",D13)+2, FIND(")",D13)-FIND(",",D13)-2)) -> 78.680814
... A41: kTVsPMA8T7faxSj38lEY | B41: 2025-07-30 17:34:59.329295 | C41: 45868 | D41: (10.4598067, 78.6825817) | E41: 1/38a,,Vilampatti,622103,Tamil Nadu,India. | F41: https://firebasestorage.googleapis.com/v0/b/mindbrink-survey-production.appspot.com/o/audioFiles%2FAtznECuQc6klLPsRR6u2%2FfYiv0HvGk4VbFlXYwsKbSZ6fwXI2%2F2025-07-30%2017%3A34%3A53.880757.m4a?alt=media&token=d8a52737-f4fc-42e4-91b9-7b5b541457a6 | G41: 190 | H41: false | I41: A.Banu | J41: +919443892814 | K41: Subramanian | L41: ILLUPUR | M41: MUKKANNAMALAIPATTI | N41: Prathiba | O41: பெண்/Female | P41: 8072379197 | Q41: 31-45 | R41: இல்லத்தரசி/ Housewife | S41: 10,000க்கும் குறைவானது/Less than 10,000 | T41: திருப்திகரமானது / Satisfactory | U41: உறுதியாக தெரியவில்லை / Not Sure | V41: திமுக கூட்டணி / DMK Alliance | W41: விஜய் (தமிழக வெற்றி கழகம்) / Vijay (TVK) | X41: அதிமுக / AIADMK | Y41: TVK | Z41: ஆம், TVK கூட்டணிக்கு வாக்களிப்பேன் / Yes, I will shift my vote to the TVK alliance | AA41: ஆமாம் / Yes | AB41: அதிமுக கூட்டணி / AIADMK Alliance | AC41: திருப்திகரமானது / Satisfactory | AD41: போதுமான ஈடுபாடு / Adequate | AE41: • ஆமாம்: அதிமுக கூட்டணி உடையும்/ Yes: AIADMK alliance will break up | AF41: தனித்துப் போட்டியிட வேண்டும் / Contest Independently | AG41: உட்கட்டமைப்பு மேம்பாடு / Infrastructure development | AH41: BC | AI41: MUTTARAIYAR | AJ41: =IFERROR(_xlfn.XLOOKUP(Table1[[#This Row],[Audio Url]],Qc!C:C,Qc!F:F),"") -> correctly done | AK41: =IFERROR(_xlfn.XLOOKUP(Table1[[#This Row],[Audio Url]],Qc!C:C,Qc!E:E),"") -> Correctly Done | AL41: - | AM41: - | AN41: =VLOOKUP(Table1[[#This Row],[LOCALITY]],Sheet2!$F:$H,3,0) -> Rural | AO41: Yes | AP41: =IF(Table1[[#This Row],[Audio Duration (in secs)]]>180,"Greater than 3 Minutes","Less than 3 Minutes") -> Greater than 3 Minutes | AQ41: =IFERROR(VLOOKUP(Table1[[#This Row],[சாதி/Caste]],MApping!$E$1:$F$10,2,0),"Others") -> MUTTARAIYAR | AR41: =VLOOKUP(Table1[[#This Row],[பாலினம்/Gender]],Factor!$F$26:$I$28,4,0) -> 1.0470348 | AS41: =VLOOKUP(Table1[[#This Row],[பதிலளித்தவரின் வயது/Age Group]],Factor!$F$35:$I$39,4,0) -> 1.0951872 | AT41: =VLOOKUP(Table1[[#This Row],[பதிலளித்தவரின் வயது/Age Group]]&Table1[[#This Row],[பாலினம்/Gender]],Factor!$A$45:$G$53,7,0) -> 1.107027 | AU41: =VLOOKUP(Table1[[#This Row],[2021 சட்டமன்றத் தேர்தலில் நீங்கள் எந்தக் கட்சிக்கு வாக்களித்தீர்கள்?/ Which party did you vote in 2021 Assembly Elections? ]],Factor!$F$9:$J$14,5,0) -> 0.73680082 | AV41: =VLOOKUP(Table1[[#This Row],[Rev Caste]],Factor!$F$59:$I$68,4,0) -> 1.2358621 | AW41: =Table1[[#This Row],[2021 Ae Factor]]*Table1[[#This Row],[Age & Gender Factor]] -> 0.81565843 | AX41: =Table1[[#This Row],[2021 Ae Factor]]*Table1[[#This Row],[Caste Factor]] -> 0.91058419 | AY41: =VALUE(MID(D41, FIND(",",D41)+2, FIND(")",D41)-FIND(",",D41)-2)) -> 78.682582
A42: 6zjcBt5iUEZaCB6mu2Ig | B42: 2025-07-30 17:40:57.453093 | C42: 45868 | D42: (10.456378, 78.7003456) | E42: 42/43,,Annavasal,622101,Tamil Nadu,India. | F42: https://firebasestorage.googleapis.com/v0/b/mindbrink-survey-production.appspot.com/o/audioFiles%2FAtznECuQc6klLPsRR6u2%2Fe5risFoEPidDckOLperfsZqxzae2%2F2025-07-30%2017%3A40%3A51.803052.m4a?alt=media&token=aa8b4929-57c7-4954-924b-4701a39da350 | G42: 338 | H42: false | I42: Sinthanai selvi | J42: +918508766594 | K42: Subramanian | L42: ILLUPUR | M42: ANNAVASAL | N42: முருகேசன் | O42: ஆண்/Male | P42: No Number | Q42: 31-45 | R42: சொந்த தொழில் / சுயதொழில் செய்பவர்/ Self Employed/Business | S42: 10,000 - 25,000 | T42: திருப்திகரமல்ல/ Unsatisfactory | U42: ஆம் / Yes | V42: நினைவில் இல்லை / Don’t Remember | W42: பிரேமலதா விஜயகாந்த் (தே.மு.தி.க) / Premalatha Vijayakanth (DMDK) | X42: தே.மு.தி.க / DMDK | Y42: DMDK | Z42: ஆம், TVK கூட்டணிக்கு வாக்களிப்பேன் / Yes, I will shift my vote to the TVK alliance | AA42: இல்லை / No | AB42: - | AC42: திருப்திகரமானது / Satisfactory | AD42: போதுமான ஈடுபாடு / Adequate | AE42: • ஆமாம்: திமுக கூட்டணி உடையும் / Yes: DMK Alliance will break up | AF42: தே.மு.தி.க / DMDK | AG42: மதுபானம் / போதைப்பொருள் பழக்கம்/ Alcohol/Drug abuse | AH42: SC | AI42: DEVENDRA KULA VELLALAR | AJ42: =IFERROR(_xlfn.XLOOKUP(Table1[[#This Row],[Audio Url]],Qc!C:C,Qc!F:F),"") -> 0 | AK42: =IFERROR(_xlfn.XLOOKUP(Table1[[#This Row],[Audio Url]],Qc!C:C,Qc!E:E),"") -> Correctly Done | AL42: - | AM42: - | AN42: =VLOOKUP(Table1[[#This Row],[LOCALITY]],Sheet2!$F:$H,3,0) -> Urban | AO42: Yes | AP42: =IF(Table1[[#This Row],[Audio Duration (in secs)]]>180,"Greater than 3 Minutes","Less than 3 Minutes") -> Greater than 3 Minutes | AQ42: =IFERROR(VLOOKUP(Table1[[#This Row],[சாதி/Caste]],MApping!$E$1:$F$10,2,0),"Others") -> DEVENDRA KULA VELLALAR | AR42: =VLOOKUP(Table1[[#This Row],[பாலினம்/Gender]],Factor!$F$26:$I$28,4,0) -> 0.95700935 | AS42: =VLOOKUP(Table1[[#This Row],[பதிலளித்தவரின் வயது/Age Group]],Factor!$F$35:$I$39,4,0) -> 1.0951872 | AT42: =VLOOKUP(Table1[[#This Row],[பதிலளித்தவரின் வயது/Age Group]]&Table1[[#This Row],[பாலினம்/Gender]],Factor!$A$45:$G$53,7,0) -> 1.0835979 | AU42: =VLOOKUP(Table1[[#This Row],[2021 சட்டமன்றத் தேர்தலில் நீங்கள் எந்தக் கட்சிக்கு வாக்களித்தீர்கள்?/ Which party did you vote in 2021 Assembly Elections? ]],Factor!$F$9:$J$14,5,0) -> 1 | AV42: =VLOOKUP(Table1[[#This Row],[Rev Caste]],Factor!$F$59:$I$68,4,0) -> 0.99902439 | AW42: =Table1[[#This Row],[2021 Ae Factor]]*Table1[[#This Row],[Age & Gender Factor]] -> 1.0835979 | AX42: =Table1[[#This Row],[2021 Ae Factor]]*Table1[[#This Row],[Caste Factor]] -> 0.99902439 | AY42: =VALUE(MID(D42, FIND(",",D42)+2, FIND(")",D42)-FIND(",",D42)-2)) -> 78.700346
A43: R46ctjO5cVyXhDWpsccI | B43: 2025-07-30 17:50:56.350415 | C43: 45868 | D43: (10.4580902, 78.6994924) | E43: 22/A,,Annavasal,622101,Tamil Nadu,India. | F43: https://firebasestorage.googleapis.com/v0/b/mindbrink-survey-production.appspot.com/o/audioFiles%2FAtznECuQc6klLPsRR6u2%2Fe5risFoEPidDckOLperfsZqxzae2%2F2025-07-30%2017%3A50%3A50.759521.m4a?alt=media&token=03f03cc0-1f39-492f-8dde-e629ae9bef21 | G43: 319 | H43: false | I43: Sinthanai selvi | J43: +918508766594 | K43: Subramanian | L43: ILLUPUR | M43: ANNAVASAL | N43: இளஞ்சியம் | O43: பெண்/Female | P43: 9750255938 | Q43: 31-45 | R43: கூலி தொழில்/ Daily Wage | S43: 10,000 - 25,000 | T43: திருப்திகரமானது / Satisfactory | U43: ஆம் / Yes | V43: அதிமுக கூட்டணி / AIADMK Alliance | W43: மு.க. ஸ்டாலின் (திமுக) / M.K. Stalin (DMK) | X43: திமுக / DMK | Y43: DMK | Z43: - | AA43: ஆமாம் / Yes | AB43: திமுக கூட்டணி / DMK Alliance | AC43: திருப்திகரமானது / Satisfactory | AD43: போதுமான ஈடுபாடு / Adequate | AE43: • ஆமாம்: திமுக கூட்டணி உடையும் / Yes: DMK Alliance will break up | AF43: அதிமுக / AIADMK | AG43: மதுபானம் / போதைப்பொருள் பழக்கம்/ Alcohol/Drug abuse | AH43: SC | AI43: DEVENDRA KULA VELLALAR | AJ43: =IFERROR(_xlfn.XLOOKUP(Table1[[#This Row],[Audio Url]],Qc!C:C,Qc!F:F),"") -> same voice | AK43: =IFERROR(_xlfn.XLOOKUP(Table1[[#This Row],[Audio Url]],Qc!C:C,Qc!E:E),"") -> Taking From Friends And Family | AL43: - | AM43: - | AN43: =VLOOKUP(Table1[[#This Row],[LOCALITY]],Sheet2!$F:$H,3,0) -> Urban | AO43: No | AP43: =IF(Table1[[#This Row],[Audio Duration (in secs)]]>180,"Greater than 3 Minutes","Less than 3 Minutes") -> Greater than 3 Minutes | AQ43: =IFERROR(VLOOKUP(Table1[[#This Row],[சாதி/Caste]],MApping!$E$1:$F$10,2,0),"Others") -> DEVENDRA KULA VELLALAR | AR43: =VLOOKUP(Table1[[#This Row],[பாலினம்/Gender]],Factor!$F$26:$I$28,4,0) -> 1.0470348 | AS43: =VLOOKUP(Table1[[#This Row],[பதிலளித்தவரின் வயது/Age Group]],Factor!$F$35:$I$39,4,0) -> 1.0951872 | AT43: =VLOOKUP(Table1[[#This Row],[பதிலளித்தவரின் வயது/Age Group]]&Table1[[#This Row],[பாலினம்/Gender]],Factor!$A$45:$G$53,7,0) -> 1.107027 | AU43: =VLOOKUP(Table1[[#This Row],[2021 சட்டமன்றத் தேர்தலில் நீங்கள் எந்தக் கட்சிக்கு வாக்களித்தீர்கள்?/ Which party did you vote in 2021 Assembly Elections? ]],Factor!$F$9:$J$14,5,0) -> 1.3119425 | AV43: =VLOOKUP(Table1[[#This Row],[Rev Caste]],Factor!$F$59:$I$68,4,0) -> 0.99902439 | AW43: =Table1[[#This Row],[2021 Ae Factor]]*Table1[[#This Row],[Age & Gender Factor]] -> 1.4523558 | AX43: =Table1[[#This Row],[2021 Ae Factor]]*Table1[[#This Row],[Caste Factor]] -> 1.3106626 | AY43: =VALUE(MID(D43, FIND(",",D43)+2, FIND(")",D43)-FIND(",",D43)-2)) -> 78.699492
A44: TCWp5Rp0ntwIwFL3ZcxZ | B44: 2025-07-30 18:18:35.517883 | C44: 45868 | D44: (10.4567399, 78.6767951) | E44: FM4G+JVJ,,Mukknamalpatti,622103,Tamil Nadu,India. | F44: https://firebasestorage.googleapis.com/v0/b/mindbrink-survey-production.appspot.com/o/audioFiles%2FAtznECuQc6klLPsRR6u2%2FfYiv0HvGk4VbFlXYwsKbSZ6fwXI2%2F2025-07-30%2018%3A18%3A29.612461.m4a?alt=media&token=bb5a98ef-fe0b-462b-9908-fe9f8bbf5709 | G44: 132 | H44: false | I44: A.Banu | J44: +919443892814 | K44: Subramanian | L44: ILLUPUR | M44: MUKKANNAMALAIPATTI | N44: Bugari | O44: ஆண்/Male | P44: 9786820387 | Q44: 46-60 | R44: கூலி தொழில்/ Daily Wage | S44: 10,000 - 25,000 | T44: திருப்திகரமானது / Satisfactory | U44: உறுதியாக தெரியவில்லை / Not Sure | V44: நினைவில் இல்லை / Don’t Remember | W44: எடப்பாடி பழனிசாமி (அதிமுக) / Edappadi K. Palaniswami (AIADMK) | X44: அதிமுக / AIADMK | Y44: AIADMK | Z44: இல்லை, நான் அந்த கூட்டணிக்கு வாக்களிக்க மாட்டேன். / No, I will not vote for the alliance | AA44: ஆமாம் / Yes | AB44: அதிமுக கூட்டணி / AIADMK Alliance | AC44: வேகம் குறைபாடுடன் செயல்படுகிறது / Needs more momentum | AD44: குறைவான ஈடுபாடு / Inadequate | AE44: • ஆமாம்: திமுக மற்றும் அதிமுக கூட்டணிகள் இரண்டும் உடையும்/ Yes: Both DMK & AIADMK alliances will break up | AF44: தனித்துப் போட்டியிட வேண்டும் / Contest Independently | AG44: வேலைவாய்ப்பு குறைபாடு / Unemployment | AH44: Muslim | AI44: MUSLIM | AJ44: =IFERROR(_xlfn.XLOOKUP(Table1[[#This Row],[Audio Url]],Qc!C:C,Qc!F:F),"") -> 0 | AK44: =IFERROR(_xlfn.XLOOKUP(Table1[[#This Row],[Audio Url]],Qc!C:C,Qc!E:E),"") -> Fake Audio/Empty Audio | AL44: - | AM44: - | AN44: =VLOOKUP(Table1[[#This Row],[LOCALITY]],Sheet2!$F:$H,3,0) -> Rural | AO44: No | AP44: =IF(Table1[[#This Row],[Audio Duration (in secs)]]>180,"Greater than 3 Minutes","Less than 3 Minutes") -> Less than 3 Minutes | AQ44: =IFERROR(VLOOKUP(Table1[[#This Row],[சாதி/Caste]],MApping!$E$1:$F$10,2,0),"Others") -> MUSLIM | AR44: =VLOOKUP(Table1[[#This Row],[பாலினம்/Gender]],Factor!$F$26:$I$28,4,0) -> 0.95700935 | AS44: =VLOOKUP(Table1[[#This Row],[பதிலளித்தவரின் வயது/Age Group]],Factor!$F$35:$I$39,4,0) -> 0.87972509 | AT44: =VLOOKUP(Table1[[#This Row],[பதிலளித்தவரின் வயது/Age Group]]&Table1[[#This Row],[பாலினம்/Gender]],Factor!$A$45:$G$53,7,0) -> 0.79503106 | AU44: =VLOOKUP(Table1[[#This Row],[2021 சட்டமன்றத் தேர்தலில் நீங்கள் எந்தக் கட்சிக்கு வாக்களித்தீர்கள்?/ Which party did you vote in 2021 Assembly Elections? ]],Factor!$F$9:$J$14,5,0) -> 1 | AV44: =VLOOKUP(Table1[[#This Row],[Rev Caste]],Factor!$F$59:$I$68,4,0) -> 1.024 | AW44: =Table1[[#This Row],[2021 Ae Factor]]*Table1[[#This Row],[Age & Gender Factor]] -> 0.79503106 | AX44: =Table1[[#This Row],[2021 Ae Factor]]*Table1[[#This Row],[Caste Factor]] -> 1.024 | AY44: =VALUE(MID(D44, FIND(",",D44)+2, FIND(")",D44)-FIND(",",D44)-2)) -> 78.676795
A45: oFlcpEKZJTCq20kYeXAt | B45: 2025-07-30 18:22:33.937283 | C45: 45868 | D45: (10.4555801, 78.7051901) | E45: FP44+836,,Annavasal,622101,Tamil Nadu,India. | F45: https://firebasestorage.googleapis.com/v0/b/mindbrink-survey-production.appspot.com/o/audioFiles%2FAtznECuQc6klLPsRR6u2%2Fe5risFoEPidDckOLperfsZqxzae2%2F2025-07-30%2018%3A22%3A20.767213.m4a?alt=media&token=80b75b8f-a091-40d6-af25-5872fe7f59a5 | G45: 221 | H45: false | I45: Sinthanai selvi | J45: +918508766594 | K45: Subramanian | L45: ILLUPUR | M45: ANNAVASAL | N45: பழனியம்மாள் | O45: பெண்/Female | P45: 9976234034 | Q45: 60+ | R45: இல்லத்தரசி/ Housewife | S45: 10,000 - 25,000 | T45: திருப்திகரமல்ல/ Unsatisfactory | U45: ஆம் / Yes | V45: அதிமுக கூட்டணி / AIADMK Alliance | W45: எடப்பாடி பழனிசாமி (அதிமுக) / Edappadi K. Palaniswami (AIADMK) | X45: அதிமுக / AIADMK | Y45: AIADMK | Z45: ஆம், TVK கூட்டணிக்கு வாக்களிப்பேன் / Yes, I will shift my vote to the TVK alliance | AA45: ஆமாம் / Yes | AB45: திமுக கூட்டணி / DMK Alliance | AC45: திருப்திகரமானது / Satisfactory | AD45: போதுமான ஈடுபாடு / Adequate | AE45: • ஆமாம்: திமுக கூட்டணி உடையும் / Yes: DMK Alliance will break up | AF45: தே.மு.தி.க / DMDK | AG45: மதுபானம் / போதைப்பொருள் பழக்கம்/ Alcohol/Drug abuse | AH45: SC | AI45: DEVENDRA KULA VELLALAR | AJ45: =IFERROR(_xlfn.XLOOKUP(Table1[[#This Row],[Audio Url]],Qc!C:C,Qc!F:F),"") -> Sam voice | AK45: =IFERROR(_xlfn.XLOOKUP(Table1[[#This Row],[Audio Url]],Qc!C:C,Qc!E:E),"") -> Taking From Friends And Family | AL45: - | AM45: - | AN45: =VLOOKUP(Table1[[#This Row],[LOCALITY]],Sheet2!$F:$H,3,0) -> Urban | AO45: No | AP45: =IF(Table1[[#This Row],[Audio Duration (in secs)]]>180,"Greater than 3 Minutes","Less than 3 Minutes") -> Greater than 3 Minutes | AQ45: =IFERROR(VLOOKUP(Table1[[#This Row],[சாதி/Caste]],MApping!$E$1:$F$10,2,0),"Others") -> DEVENDRA KULA VELLALAR | AR45: =VLOOKUP(Table1[[#This Row],[பாலினம்/Gender]],Factor!$F$26:$I$28,4,0) -> 1.0470348 | AS45: =VLOOKUP(Table1[[#This Row],[பதிலளித்தவரின் வயது/Age Group]],Factor!$F$35:$I$39,4,0) -> 1.0308725 | AT45: =VLOOKUP(Table1[[#This Row],[பதிலளித்தவரின் வயது/Age Group]]&Table1[[#This Row],[பாலினம்/Gender]],Factor!$A$45:$G$53,7,0) -> 1.28 | AU45: =VLOOKUP(Table1[[#This Row],[2021 சட்டமன்றத் தேர்தலில் நீங்கள் எந்தக் கட்சிக்கு வாக்களித்தீர்கள்?/ Which party did you vote in 2021 Assembly Elections? ]],Factor!$F$9:$J$14,5,0) -> 1.3119425 | AV45: =VLOOKUP(Table1[[#This Row],[Rev Caste]],Factor!$F$59:$I$68,4,0) -> 0.99902439 | AW45: =Table1[[#This Row],[2021 Ae Factor]]*Table1[[#This Row],[Age & Gender Factor]] -> 1.6792864 | AX45: =Table1[[#This Row],[2021 Ae Factor]]*Table1[[#This Row],[Caste Factor]] -> 1.3106626 | AY45: =VALUE(MID(D45, FIND(",",D45)+2, FIND(")",D45)-FIND(",",D45)-2)) -> 78.70519
A46: BaBgSpdHExXyHT8ts1KV | B46: 2025-07-30 18:27:47.906472 | C46: 45868 | D46: (10.4566937, 78.6764513) | E46: FM4G+MGJ,,Mukknamalpatti,622103,Tamil Nadu,India. | F46: https://firebasestorage.googleapis.com/v0/b/mindbrink-survey-production.appspot.com/o/audioFiles%2FAtznECuQc6klLPsRR6u2%2FfYiv0HvGk4VbFlXYwsKbSZ6fwXI2%2F2025-07-30%2018%3A27%3A42.123347.m4a?alt=media&token=f8dae3ef-36f3-4753-babc-dccd78901929 | G46: 107 | H46: false | I46: A.Banu | J46: +919443892814 | K46: Subramanian | L46: ILLUPUR | M46: MUKKANNAMALAIPATTI | N46: umsalima | O46: பெண்/Female | P46: 9047843014 | Q46: 46-60 | R46: இல்லத்தரசி/ Housewife | S46: 10,000க்கும் குறைவானது/Less than 10,000 | T46: மேம்பாடு தேவை / Needs improvement | U46: இல்லை/ No | V46: திமுக கூட்டணி / DMK Alliance | W46: எடப்பாடி பழனிசாமி (அதிமுக) / Edappadi K. Palaniswami (AIADMK) | X46: திமுக / DMK | Y46: DMK | Z46: - | AA46: ஆமாம் / Yes | AB46: அதிமுக கூட்டணி / AIADMK Alliance | AC46: வேகம் குறைபாடுடன் செயல்படுகிறது / Needs more momentum | AD46: குறைவான ஈடுபாடு / Inadequate | AE46: • ஆமாம்: அதிமுக கூட்டணி உடையும்/ Yes: AIADMK alliance will break up | AF46: தனித்துப் போட்டியிட வேண்டும் / Contest Independently | AG46: மதுபானம் / போதைப்பொருள் பழக்கம்/ Alcohol/Drug abuse | AH46: Muslim | AI46: MUSLIM | AJ46: =IFERROR(_xlfn.XLOOKUP(Table1[[#This Row],[Audio Url]],Qc!C:C,Qc!F:F),"") -> 0 | AK46: =IFERROR(_xlfn.XLOOKUP(Table1[[#This Row],[Audio Url]],Qc!C:C,Qc!E:E),"") -> Fake Audio/Empty Audio | AL46: - | AM46: - | AN46: =VLOOKUP(Table1[[#This Row],[LOCALITY]],Sheet2!$F:$H,3,0) -> Rural | AO46: No | AP46: =IF(Table1[[#This Row],[Audio Duration (in secs)]]>180,"Greater than 3 Minutes","Less than 3 Minutes") -> Less than 3 Minutes | AQ46: =IFERROR(VLOOKUP(Table1[[#This Row],[சாதி/Caste]],MApping!$E$1:$F$10,2,0),"Others") -> MUSLIM | AR46: =VLOOKUP(Table1[[#This Row],[பாலினம்/Gender]],Factor!$F$26:$I$28,4,0) -> 1.0470348 | AS46: =VLOOKUP(Table1[[#This Row],[பதிலளித்தவரின் வயது/Age Group]],Factor!$F$35:$I$39,4,0) -> 0.87972509 | AT46: =VLOOKUP(Table1[[#This Row],[பதிலளித்தவரின் வயது/Age Group]]&Table1[[#This Row],[பாலினம்/Gender]],Factor!$A$45:$G$53,7,0) -> 0.98461538 | AU46: =VLOOKUP(Table1[[#This Row],[2021 சட்டமன்றத் தேர்தலில் நீங்கள் எந்தக் கட்சிக்கு வாக்களித்தீர்கள்?/ Which party did you vote in 2021 Assembly Elections? ]],Factor!$F$9:$J$14,5,0) -> 0.73680082 | AV46: =VLOOKUP(Table1[[#This Row],[Rev Caste]],Factor!$F$59:$I$68,4,0) -> 1.024 | AW46: =Table1[[#This Row],[2021 Ae Factor]]*Table1[[#This Row],[Age & Gender Factor]] -> 0.72546543 | AX46: =Table1[[#This Row],[2021 Ae Factor]]*Table1[[#This Row],[Caste Factor]] -> 0.75448404 | AY46: =VALUE(MID(D46, FIND(",",D46)+2, FIND(")",D46)-FIND(",",D46)-2)) -> 78.676451
A47: EDtyMJ27WdXsevCdjc9q | B47: 2025-07-30 18:31:22.493369 | C47: 45868 | D47: (10.456693, 78.6764446) | E47: FM4G+MGJ,,Mukknamalpatti,622103,Tamil Nadu,India. | F47: https://firebasestorage.googleapis.com/v0/b/mindbrink-survey-production.appspot.com/o/audioFiles%2FAtznECuQc6klLPsRR6u2%2FfYiv0HvGk4VbFlXYwsKbSZ6fwXI2%2F2025-07-30%2018%3A31%3A14.823960.m4a?alt=media&token=51373197-6438-4eca-bbea-36e27d8cd94f | G47: 156 | H47: false | I47: A.Banu | J47: +919443892814 | K47: Subramanian | L47: ILLUPUR | M47: MUKKANNAMALAIPATTI | N47: fyrose | O47: பெண்/Female | P47: 8675359062 | Q47: 60+ | R47: இல்லத்தரசி/ Housewife | S47: 10,000க்கும் குறைவானது/Less than 10,000 | T47: திருப்திகரமானது / Satisfactory | U47: இல்லை/ No | V47: திமுக கூட்டணி / DMK Alliance | W47: மு.க. ஸ்டாலின் (திமுக) / M.K. Stalin (DMK) | X47: திமுக / DMK | Y47: DMK | Z47: - | AA47: ஆமாம் / Yes | AB47: அதிமுக கூட்டணி / AIADMK Alliance | AC47: வேகம் குறைபாடுடன் செயல்படுகிறது / Needs more momentum | AD47: பயனில்லை / Not effective | AE47: • ஆமாம்: அதிமுக கூட்டணி உடையும்/ Yes: AIADMK alliance will break up | AF47: தனித்துப் போட்டியிட வேண்டும் / Contest Independently | AG47: மதுபானம் / போதைப்பொருள் பழக்கம்/ Alcohol/Drug abuse | AH47: Muslim | AI47: MUSLIM | AJ47: =IFERROR(_xlfn.XLOOKUP(Table1[[#This Row],[Audio Url]],Qc!C:C,Qc!F:F),"") -> 0 | AK47: =IFERROR(_xlfn.XLOOKUP(Table1[[#This Row],[Audio Url]],Qc!C:C,Qc!E:E),"") -> Fake Audio/Empty Audio | AL47: - | AM47: - | AN47: =VLOOKUP(Table1[[#This Row],[LOCALITY]],Sheet2!$F:$H,3,0) -> Rural | AO47: No | AP47: =IF(Table1[[#This Row],[Audio Duration (in secs)]]>180,"Greater than 3 Minutes","Less than 3 Minutes") -> Less than 3 Minutes | AQ47: =IFERROR(VLOOKUP(Table1[[#This Row],[சாதி/Caste]],MApping!$E$1:$F$10,2,0),"Others") -> MUSLIM | AR47: =VLOOKUP(Table1[[#This Row],[பாலினம்/Gender]],Factor!$F$26:$I$28,4,0) -> 1.0470348 | AS47: =VLOOKUP(Table1[[#This Row],[பதிலளித்தவரின் வயது/Age Group]],Factor!$F$35:$I$39,4,0) -> 1.0308725 | AT47: =VLOOKUP(Table1[[#This Row],[பதிலளித்தவரின் வயது/Age Group]]&Table1[[#This Row],[பாலினம்/Gender]],Factor!$A$45:$G$53,7,0) -> 1.28 | AU47: =VLOOKUP(Table1[[#This Row],[2021 சட்டமன்றத் தேர்தலில் நீங்கள் எந்தக் கட்சிக்கு வாக்களித்தீர்கள்?/ Which party did you vote in 2021 Assembly Elections? ]],Factor!$F$9:$J$14,5,0) -> 0.73680082 | AV47: =VLOOKUP(Table1[[#This Row],[Rev Caste]],Factor!$F$59:$I$68,4,0) -> 1.024 | AW47: =Table1[[#This Row],[2021 Ae Factor]]*Table1[[#This Row],[Age & Gender Factor]] -> 0.94310506 | AX47: =Table1[[#This Row],[2021 Ae Factor]]*Table1[[#This Row],[Caste Factor]] -> 0.75448404 | AY47: =VALUE(MID(D47, FIND(",",D47)+2, FIND(")",D47)-FIND(",",D47)-2)) -> 78.676445
A48: 74QTlPEi8pFWvnyEhKuj | B48: 2025-07-30 18:37:58.053124 | C48: 45868 | D48: (10.4566917, 78.6764481) | E48: FM4G+MGJ,,Mukknamalpatti,622103,Tamil Nadu,India. | F48: https://firebasestorage.googleapis.com/v0/b/mindbrink-survey-production.appspot.com/o/audioFiles%2FAtznECuQc6klLPsRR6u2%2FfYiv0HvGk4VbFlXYwsKbSZ6fwXI2%2F2025-07-30%2018%3A37%3A27.096214.m4a?alt=media&token=7f40148c-d3aa-4b4e-ad89-83cdd2f64837 | G48: 264 | H48: false | I48: A.Banu | J48: +919443892814 | K48: Subramanian | L48: ILLUPUR | M48: MUKKANNAMALAIPATTI | N48: Jahir usan | O48: ஆண்/Male | P48: 7010675442 | Q48: 46-60 | R48: கூலி தொழில்/ Daily Wage | S48: 10,000 - 25,000 | T48: திருப்திகரமானது / Satisfactory | U48: இல்லை/ No | V48: திமுக கூட்டணி / DMK Alliance | W48: மு.க. ஸ்டாலின் (திமுக) / M.K. Stalin (DMK) | X48: திமுக / DMK | Y48: DMK | Z48: - | AA48: இல்லை / No | AB48: - | AC48: திருப்திகரமல்ல / Unsatisfactory | AD48: பயனில்லை / Not effective | AE48: • ஆமாம்: அதிமுக கூட்டணி உடையும்/ Yes: AIADMK alliance will break up | AF48: தனித்துப் போட்டியிட வேண்டும் / Contest Independently | AG48: வேலைவாய்ப்பு குறைபாடு / Unemployment | AH48: Muslim | AI48: MUSLIM | AJ48: =IFERROR(_xlfn.XLOOKUP(Table1[[#This Row],[Audio Url]],Qc!C:C,Qc!F:F),"") -> didn't ask question in th6middle | AK48: =IFERROR(_xlfn.XLOOKUP(Table1[[#This Row],[Audio Url]],Qc!C:C,Qc!E:E),"") -> Not Doing It Properly | AL48: - | AM48: - | AN48: =VLOOKUP(Table1[[#This Row],[LOCALITY]],Sheet2!$F:$H,3,0) -> Rural | AO48: Yes | AP48: =IF(Table1[[#This Row],[Audio Duration (in secs)]]>180,"Greater than 3 Minutes","Less than 3 Minutes") -> Greater than 3 Minutes | AQ48: =IFERROR(VLOOKUP(Table1[[#This Row],[சாதி/Caste]],MApping!$E$1:$F$10,2,0),"Others") -> MUSLIM | AR48: =VLOOKUP(Table1[[#This Row],[பாலினம்/Gender]],Factor!$F$26:$I$28,4,0) -> 0.95700935 | AS48: =VLOOKUP(Table1[[#This Row],[பதிலளித்தவரின் வயது/Age Group]],Factor!$F$35:$I$39,4,0) -> 0.87972509 | AT48: =VLOOKUP(Table1[[#This Row],[பதிலளித்தவரின் வயது/Age Group]]&Table1[[#This Row],[பாலினம்/Gender]],Factor!$A$45:$G$53,7,0) -> 0.79503106 | AU48: =VLOOKUP(Table1[[#This Row],[2021 சட்டமன்றத் தேர்தலில் நீங்கள் எந்தக் கட்சிக்கு வாக்களித்தீர்கள்?/ Which party did you vote in 2021 Assembly Elections? ]],Factor!$F$9:$J$14,5,0) -> 0.73680082 | AV48: =VLOOKUP(Table1[[#This Row],[Rev Caste]],Factor!$F$59:$I$68,4,0) -> 1.024 | AW48: =Table1[[#This Row],[2021 Ae Factor]]*Table1[[#This Row],[Age & Gender Factor]] -> 0.58577954 | AX48: =Table1[[#This Row],[2021 Ae Factor]]*Table1[[#This Row],[Caste Factor]] -> 0.75448404 | AY48: =VALUE(MID(D48, FIND(",",D48)+2, FIND(")",D48)-FIND(",",D48)-2)) -> 78.676448
A49: v6JccaM3Nbt1N5tpe9eV | B49: 2025-07-30 18:43:13.845797 | C49: 45868 | D49: (10.4566916, 78.6764346) | E49: FM4G+MGJ,,Mukknamalpatti,622103,Tamil Nadu,India. | F49: https://firebasestorage.googleapis.com/v0/b/mindbrink-survey-production.appspot.com/o/audioFiles%2FAtznECuQc6klLPsRR6u2%2FfYiv0HvGk4VbFlXYwsKbSZ6fwXI2%2F2025-07-30%2018%3A43%3A07.077254.m4a?alt=media&token=5a010714-24b3-4c1f-aaff-75fa375b6d4a | G49: 133 | H49: false | I49: A.Banu | J49: +919443892814 | K49: Subramanian | L49: ILLUPUR | M49: MUKKANNAMALAIPATTI | N49: Balaji | O49: ஆண்/Male | P49: 9788101109 | Q49: 31-45 | R49: சொந்த தொழில் / சுயதொழில் செய்பவர்/ Self Employed/Business | S49: 10,000 - 25,000 | T49: திருப்திகரமானது / Satisfactory | U49: இல்லை/ No | V49: திமுக கூட்டணி / DMK Alliance | W49: மு.க. ஸ்டாலின் (திமுக) / M.K. Stalin (DMK) | X49: திமுக / DMK | Y49: DMK | Z49: - | AA49: இல்லை / No | AB49: - | AC49: வேகம் குறைபாடுடன் செயல்படுகிறது / Needs more momentum | AD49: குறைவான ஈடுபாடு / Inadequate | AE49: • ஆமாம்: அதிமுக கூட்டணி உடையும்/ Yes: AIADMK alliance will break up | AF49: தனித்துப் போட்டியிட வேண்டும் / Contest Independently | AG49: சட்டம் மற்றும் ஒழுங்கு/ Law and order | AH49: BC | AI49: MUTTARAIYAR | AJ49: =IFERROR(_xlfn.XLOOKUP(Table1[[#This Row],[Audio Url]],Qc!C:C,Qc!F:F),"") -> 0 | AK49: =IFERROR(_xlfn.XLOOKUP(Table1[[#This Row],[Audio Url]],Qc!C:C,Qc!E:E),"") -> Fake Audio/Empty Audio | AL49: - | AM49: - | AN49: =VLOOKUP(Table1[[#This Row],[LOCALITY]],Sheet2!$F:$H,3,0) -> Rural | AO49: No | AP49: =IF(Table1[[#This Row],[Audio Duration (in secs)]]>180,"Greater than 3 Minutes","Less than 3 Minutes") -> Less than 3 Minutes | AQ49: =IFERROR(VLOOKUP(Table1[[#This Row],[சாதி/Caste]],MApping!$E$1:$F$10,2,0),"Others") -> MUTTARAIYAR | AR49: =VLOOKUP(Table1[[#This Row],[பாலினம்/Gender]],Factor!$F$26:$I$28,4,0) -> 0.95700935 | AS49: =VLOOKUP(Table1[[#This Row],[பதிலளித்தவரின் வயது/Age Group]],Factor!$F$35:$I$39,4,0) -> 1.0951872 | AT49: =VLOOKUP(Table1[[#This Row],[பதிலளித்தவரின் வயது/Age Group]]&Table1[[#This Row],[பாலினம்/Gender]],Factor!$A$45:$G$53,7,0) -> 1.0835979 | AU49: =VLOOKUP(Table1[[#This Row],[2021 சட்டமன்றத் தேர்தலில் நீங்கள் எந்தக் கட்சிக்கு வாக்களித்தீர்கள்?/ Which party did you vote in 2021 Assembly Elections? ]],Factor!$F$9:$J$14,5,0) -> 0.73680082 | AV49: =VLOOKUP(Table1[[#This Row],[Rev Caste]],Factor!$F$59:$I$68,4,0) -> 1.2358621 | AW49: =Table1[[#This Row],[2021 Ae Factor]]*Table1[[#This Row],[Age & Gender Factor]] -> 0.79839581 | AX49: =Table1[[#This Row],[2021 Ae Factor]]*Table1[[#This Row],[Caste Factor]] -> 0.91058419 | AY49: =VALUE(MID(D49, FIND(",",D49)+2, FIND(")",D49)-FIND(",",D49)-2)) -> 78.676435
A50: n53g7hB2xnRNClZCUGDr | B50: 2025-07-30 18:48:27.714148 | C50: 45868 | D50: (10.4565883, 78.6762283) | E50: FM4G+MGJ,,Mukknamalpatti,622103,Tamil Nadu,India. | F50: https://firebasestorage.googleapis.com/v0/b/mindbrink-survey-production.appspot.com/o/audioFiles%2FAtznECuQc6klLPsRR6u2%2FfYiv0HvGk4VbFlXYwsKbSZ6fwXI2%2F2025-07-30%2018%3A48%3A21.731656.m4a?alt=media&token=5717e47e-6dc9-492f-955f-12de4d98ec49 | G50: 137 | H50: false | I50: A.Banu | J50: +919443892814 | K50: Subramanian | L50: ILLUPUR | M50: MUKKANNAMALAIPATTI | N50: Mubarak | O50: ஆண்/Male | P50: 9865714401 | Q50: 46-60 | R50: சொந்த தொழில் / சுயதொழில் செய்பவர்/ Self Employed/Business | S50: 10,000 - 25,000 | T50: திருப்திகரமானது / Satisfactory | U50: இல்லை/ No | V50: திமுக கூட்டணி / DMK Alliance | W50: மு.க. ஸ்டாலின் (திமுக) / M.K. Stalin (DMK) | X50: திமுக / DMK | Y50: DMK | Z50: - | AA50: இல்லை / No | AB50: - | AC50: வேகம் குறைபாடுடன் செயல்படுகிறது / Needs more momentum | AD50: பயனில்லை / Not effective | AE50: • ஆமாம்: அதிமுக கூட்டணி உடையும்/ Yes: AIADMK alliance will break up | AF50: தனித்துப் போட்டியிட வேண்டும் / Contest Independently | AG50: உட்கட்டமைப்பு மேம்பாடு / Infrastructure development | AH50: Muslim | AI50: MUSLIM | AJ50: =IFERROR(_xlfn.XLOOKUP(Table1[[#This Row],[Audio Url]],Qc!C:C,Qc!F:F),"") -> she is randomly posting | AK50: =IFERROR(_xlfn.XLOOKUP(Table1[[#This Row],[Audio Url]],Qc!C:C,Qc!E:E),"") -> Taking From Friends And Family | AL50: - | AM50: - | AN50: =VLOOKUP(Table1[[#This Row],[LOCALITY]],Sheet2!$F:$H,3,0) -> Rural | AO50: No | AP50: =IF(Table1[[#This Row],[Audio Duration (in secs)]]>180,"Greater than 3 Minutes","Less than 3 Minutes") -> Less than 3 Minutes | AQ50: =IFERROR(VLOOKUP(Table1[[#This Row],[சாதி/Caste]],MApping!$E$1:$F$10,2,0),"Others") -> MUSLIM | AR50: =VLOOKUP(Table1[[#This Row],[பாலினம்/Gender]],Factor!$F$26:$I$28,4,0) -> 0.95700935 | AS50: =VLOOKUP(Table1[[#This Row],[பதிலளித்தவரின் வயது/Age Group]],Factor!$F$35:$I$39,4,0) -> 0.87972509 | AT50: =VLOOKUP(Table1[[#This Row],[பதிலளித்தவரின் வயது/Age Group]]&Table1[[#This Row],[பாலினம்/Gender]],Factor!$A$45:$G$53,7,0) -> 0.79503106 | AU50: =VLOOKUP(Table1[[#This Row],[2021 சட்டமன்றத் தேர்தலில் நீங்கள் எந்தக் கட்சிக்கு வாக்களித்தீர்கள்?/ Which party did you vote in 2021 Assembly Elections? ]],Factor!$F$9:$J$14,5,0) -> 0.73680082 | AV50: =VLOOKUP(Table1[[#This Row],[Rev Caste]],Factor!$F$59:$I$68,4,0) -> 1.024 | AW50: =Table1[[#This Row],[2021 Ae Factor]]*Table1[[#This Row],[Age & Gender Factor]] -> 0.58577954 | AX50: =Table1[[#This Row],[2021 Ae Factor]]*Table1[[#This Row],[Caste Factor]] -> 0.75448404 | AY50: =VALUE(MID(D50, FIND(",",D50)+2, FIND(")",D50)-FIND(",",D50)-2)) -> 78.676228
A51: DGmwD5mSpLhsz75LXk7o | B51: 2025-07-30 18:52:28.690623 | C51: 45868 | D51: (10.4572549, 78.6743761) | E51: FM4F+PQC,,Mukknamalpatti,622103,Tamil Nadu,India. | F51: https://firebasestorage.googleapis.com/v0/b/mindbrink-survey-production.appspot.com/o/audioFiles%2FAtznECuQc6klLPsRR6u2%2FfYiv0HvGk4VbFlXYwsKbSZ6fwXI2%2F2025-07-30%2018%3A52%3A24.196625.m4a?alt=media&token=0d2fee61-60f3-43d8-88f0-2e5adcaf95e3 | G51: 130 | H51: false | I51: A.Banu | J51: +919443892814 | K51: Subramanian | L51: ILLUPUR | M51: MUKKANNAMALAIPATTI | N51: Sarmila | O51: பெண்/Female | P51: 9442762322 | Q51: 31-45 | R51: இல்லத்தரசி/ Housewife | S51: 10,000க்கும் குறைவானது/Less than 10,000 | T51: திருப்திகரமானது / Satisfactory | U51: இல்லை/ No | V51: திமுக கூட்டணி / DMK Alliance | W51: மு.க. ஸ்டாலின் (திமுக) / M.K. Stalin (DMK) | X51: திமுக / DMK | Y51: DMK | Z51: - | AA51: இல்லை / No | AB51: - | AC51: வேகம் குறைபாடுடன் செயல்படுகிறது / Needs more momentum | AD51: குறைவான ஈடுபாடு / Inadequate | AE51: • ஆமாம்: அதிமுக கூட்டணி உடையும்/ Yes: AIADMK alliance will break up | AF51: தனித்துப் போட்டியிட வேண்டும் / Contest Independently | AG51: மதுபானம் / போதைப்பொருள் பழக்கம்/ Alcohol/Drug abuse | AH51: Muslim | AI51: MUSLIM | AJ51: =IFERROR(_xlfn.XLOOKUP(Table1[[#This Row],[Audio Url]],Qc!C:C,Qc!F:F),"") -> same voice | AK51: =IFERROR(_xlfn.XLOOKUP(Table1[[#This Row],[Audio Url]],Qc!C:C,Qc!E:E),"") -> Taking From Friends And Family | AL51: - | AM51: - | AN51: =VLOOKUP(Table1[[#This Row],[LOCALITY]],Sheet2!$F:$H,3,0) -> Rural | AO51: No | AP51: =IF(Table1[[#This Row],[Audio Duration (in secs)]]>180,"Greater than 3 Minutes","Less than 3 Minutes") -> Less than 3 Minutes | AQ51: =IFERROR(VLOOKUP(Table1[[#This Row],[சாதி/Caste]],MApping!$E$1:$F$10,2,0),"Others") -> MUSLIM | AR51: =VLOOKUP(Table1[[#This Row],[பாலினம்/Gender]],Factor!$F$26:$I$28,4,0) -> 1.0470348 | AS51: =VLOOKUP(Table1[[#This Row],[பதிலளித்தவரின் வயது/Age Group]],Factor!$F$35:$I$39,4,0) -> 1.0951872 | AT51: =VLOOKUP(Table1[[#This Row],[பதிலளித்தவரின் வயது/Age Group]]&Table1[[#This Row],[பாலினம்/Gender]],Factor!$A$45:$G$53,7,0) -> 1.107027 | AU51: =VLOOKUP(Table1[[#This Row],[2021 சட்டமன்றத் தேர்தலில் நீங்கள் எந்தக் கட்சிக்கு வாக்களித்தீர்கள்?/ Which party did you vote in 2021 Assembly Elections? ]],Factor!$F$9:$J$14,5,0) -> 0.73680082 | AV51: =VLOOKUP(Table1[[#This Row],[Rev Caste]],Factor!$F$59:$I$68,4,0) -> 1.024 | AW51: =Table1[[#This Row],[2021 Ae Factor]]*Table1[[#This Row],[Age & Gender Factor]] -> 0.81565843 | AX51: =Table1[[#This Row],[2021 Ae Factor]]*Table1[[#This Row],[Caste Factor]] -> 0.75448404 | AY51: =VALUE(MID(D51, FIND(",",D51)+2, FIND(")",D51)-FIND(",",D51)-2)) -> 78.674376
A52: jlKfKsDDz5wVTawCjz0K | B52: 2025-07-30 19:00:01.187198 | C52: 45868 | D52: (10.45667, 78.6810667) | E52: FM4J+G76,,Mukknamalpatti,622103,Tamil Nadu,India. | F52: https://firebasestorage.googleapis.com/v0/b/mindbrink-survey-production.appspot.com/o/audioFiles%2FAtznECuQc6klLPsRR6u2%2FfYiv0HvGk4VbFlXYwsKbSZ6fwXI2%2F2025-07-30%2018%3A59%3A54.870199.m4a?alt=media&token=38647072-7a82-48f1-b77c-ca5e040a8ff4 | G52: 88 | H52: false | I52: A.Banu | J52: +919443892814 | K52: Subramanian | L52: ILLUPUR | M52: MUKKANNAMALAIPATTI | N52: Baruk | O52: ஆண்/Male | P52: 9655507498 | Q52: 60+ | R52: சொந்த தொழில் / சுயதொழில் செய்பவர்/ Self Employed/Business | S52: 10,000 - 25,000 | T52: திருப்திகரமானது / Satisfactory | U52: இல்லை/ No | V52: திமுக கூட்டணி / DMK Alliance | W52: மு.க. ஸ்டாலின் (திமுக) / M.K. Stalin (DMK) | X52: திமுக / DMK | Y52: DMK | Z52: - | AA52: இல்லை / No | AB52: - | AC52: வேகம் குறைபாடுடன் செயல்படுகிறது / Needs more momentum | AD52: குறைவான ஈடுபாடு / Inadequate | AE52: • ஆமாம்: அதிமுக கூட்டணி உடையும்/ Yes: AIADMK alliance will break up | AF52: தனித்துப் போட்டியிட வேண்டும் / Contest Independently | AG52: ஊழல்/ Corruption | AH52: Muslim | AI52: MUSLIM | AJ52: =IFERROR(_xlfn.XLOOKUP(Table1[[#This Row],[Audio Url]],Qc!C:C,Qc!F:F),"") -> randomly entering first few questions where asked only | AK52: =IFERROR(_xlfn.XLOOKUP(Table1[[#This Row],[Audio Url]],Qc!C:C,Qc!E:E),"") -> Not Asking All The Questions | AL52: - | AM52: - | AN52: =VLOOKUP(Table1[[#This Row],[LOCALITY]],Sheet2!$F:$H,3,0) -> Rural | AO52: Yes | AP52: =IF(Table1[[#This Row],[Audio Duration (in secs)]]>180,"Greater than 3 Minutes","Less than 3 Minutes") -> Less than 3 Minutes | AQ52: =IFERROR(VLOOKUP(Table1[[#This Row],[சாதி/Caste]],MApping!$E$1:$F$10,2,0),"Others") -> MUSLIM | AR52: =VLOOKUP(Table1[[#This Row],[பாலினம்/Gender]],Factor!$F$26:$I$28,4,0) -> 0.95700935 | AS52: =VLOOKUP(Table1[[#This Row],[பதிலளித்தவரின் வயது/Age Group]],Factor!$F$35:$I$39,4,0) -> 1.0308725 | AT52: =VLOOKUP(Table1[[#This Row],[பதிலளித்தவரின் வயது/Age Group]]&Table1[[#This Row],[பாலினம்/Gender]],Factor!$A$45:$G$53,7,0) -> 0.86292135 | AU52: =VLOOKUP(Table1[[#This Row],[2021 சட்டமன்றத் தேர்தலில் நீங்கள் எந்தக் கட்சிக்கு வாக்களித்தீர்கள்?/ Which party did you vote in 2021 Assembly Elections? ]],Factor!$F$9:$J$14,5,0) -> 0.73680082 | AV52: =VLOOKUP(Table1[[#This Row],[Rev Caste]],Factor!$F$59:$I$68,4,0) -> 1.024 | AW52: =Table1[[#This Row],[2021 Ae Factor]]*Table1[[#This Row],[Age & Gender Factor]] -> 0.63580116 | AX52: =Table1[[#This Row],[2021 Ae Factor]]*Table1[[#This Row],[Caste Factor]] -> 0.75448404 | AY52: =VALUE(MID(D52, FIND(",",D52)+2, FIND(")",D52)-FIND(",",D52)-2)) -> 78.681067
A53: oPFm7HPY2uJvkjG37Awx | B53: 2025-07-30 19:17:07.149590 | C53: 45868 | D53: (10.4528494, 78.6991889) | E53: 6/C,,Annavasal,622101,Tamil Nadu,India. | F53: https://firebasestorage.googleapis.com/v0/b/mindbrink-survey-production.appspot.com/o/audioFiles%2FAtznECuQc6klLPsRR6u2%2Fe5risFoEPidDckOLperfsZqxzae2%2F2025-07-30%2019%3A16%3A57.193446.m4a?alt=media&token=9b09651c-2903-4bd8-bd4c-a146c3003637 | G53: 319 | H53: false | I53: Sinthanai selvi | J53: +918508766594 | K53: Subramanian | L53: ILLUPUR | M53: ANNAVASAL | N53: முத்து | O53: ஆண்/Male | P53: 9750219287 | Q53: 31-45 | R53: கூலி தொழில்/ Daily Wage | S53: 10,000 - 25,000 | T53: திருப்திகரமல்ல/ Unsatisfactory | U53: ஆம் / Yes | V53: திமுக கூட்டணி / DMK Alliance | W53: சீமான் (நாம் தமிழர் கட்சி) / Seeman (NTK) | X53: அதிமுக / AIADMK | Y53: AIADMK | Z53: உறுதி இல்லை / வேட்பாளரைப் பொறுத்தது/ Not sure / Depends on candidate | AA53: இல்லை / No | AB53: - | AC53: திருப்திகரமல்ல / Unsatisfactory | AD53: பயனில்லை / Not effective | AE53: • ஆமாம்: திமுக கூட்டணி உடையும் / Yes: DMK Alliance will break up | AF53: தனித்துப் போட்டியிட வேண்டும் / Contest Independently | AG53: Other Issues | AH53: SC | AI53: DEVENDRA KULA VELLALAR | AJ53: =IFERROR(_xlfn.XLOOKUP(Table1[[#This Row],[Audio Url]],Qc!C:C,Qc!F:F),"") -> 0 | AK53: =IFERROR(_xlfn.XLOOKUP(Table1[[#This Row],[Audio Url]],Qc!C:C,Qc!E:E),"") -> Correctly Done | AL53: - | AM53: - | AN53: =VLOOKUP(Table1[[#This Row],[LOCALITY]],Sheet2!$F:$H,3,0) -> Urban | AO53: Yes | AP53: =IF(Table1[[#This Row],[Audio Duration (in secs)]]>180,"Greater than 3 Minutes","Less than 3 Minutes") -> Greater than 3 Minutes | AQ53: =IFERROR(VLOOKUP(Table1[[#This Row],[சாதி/Caste]],MApping!$E$1:$F$10,2,0),"Others") -> DEVENDRA KULA VELLALAR | AR53: =VLOOKUP(Table1[[#This Row],[பாலினம்/Gender]],Factor!$F$26:$I$28,4,0) -> 0.95700935 | AS53: =VLOOKUP(Table1[[#This Row],[பதிலளித்தவரின் வயது/Age Group]],Factor!$F$35:$I$39,4,0) -> 1.0951872 | AT53: =VLOOKUP(Table1[[#This Row],[பதிலளித்தவரின் வயது/Age Group]]&Table1[[#This Row],[பாலினம்/Gender]],Factor!$A$45:$G$53,7,0) -> 1.0835979 | AU53: =VLOOKUP(Table1[[#This Row],[2021 சட்டமன்றத் தேர்தலில் நீங்கள் எந்தக் கட்சிக்கு வாக்களித்தீர்கள்?/ Which party did you vote in 2021 Assembly Elections? ]],Factor!$F$9:$J$14,5,0) -> 0.73680082 | AV53: =VLOOKUP(Table1[[#This Row],[Rev Caste]],Factor!$F$59:$I$68,4,0) -> 0.99902439 | AW53: =Table1[[#This Row],[2021 Ae Factor]]*Table1[[#This Row],[Age & Gender Factor]] -> 0.79839581 | AX53: =Table1[[#This Row],[2021 Ae Factor]]*Table1[[#This Row],[Caste Factor]] -> 0.73608199 | AY53: =VALUE(MID(D53, FIND(",",D53)+2, FIND(")",D53)-FIND(",",D53)-2)) -> 78.699189
A54: y0zDjI07wvmmieKGpCr1 | B54: 2025-07-30 19:32:33.865735 | C54: 45868 | D54: (10.4565715, 78.6998932) | E54: 46,,Annavasal,622101,Tamil Nadu,India. | F54: https://firebasestorage.googleapis.com/v0/b/mindbrink-survey-production.appspot.com/o/audioFiles%2FAtznECuQc6klLPsRR6u2%2Fe5risFoEPidDckOLperfsZqxzae2%2F2025-07-30%2019%3A32%3A25.489200.m4a?alt=media&token=4a905e86-07c8-40e7-bc1e-dd61f5698d98 | G54: 397 | H54: false | I54: Sinthanai selvi | J54: +918508766594 | K54: Subramanian | L54: ILLUPUR | M54: ANNAVASAL | N54: தனுஷியா | O54: பெண்/Female | P54: 9962921011 | Q54: 18-30 | R54: இல்லத்தரசி/ Housewife | S54: 10,000 - 25,000 | T54: திருப்திகரமல்ல/ Unsatisfactory | U54: ஆம் / Yes | V54: நினைவில் இல்லை / Don’t Remember | W54: விஜய் (தமிழக வெற்றி கழகம்) / Vijay (TVK) | X54: அதிமுக / AIADMK | Y54: TVK | Z54: உறுதி இல்லை / வேட்பாளரைப் பொறுத்தது/ Not sure / Depends on candidate | AA54: ஆமாம் / Yes | AB54: திமுக கூட்டணி / DMK Alliance | AC54: திருப்திகரமல்ல / Unsatisfactory | AD54: குறைவான ஈடுபாடு / Inadequate | AE54: • ஆமாம்: திமுக கூட்டணி உடையும் / Yes: DMK Alliance will break up | AF54: அதிமுக / AIADMK | AG54: மதுபானம் / போதைப்பொருள் பழக்கம்/ Alcohol/Drug abuse | AH54: SC | AI54: PALLAR SC | AJ54: =IFERROR(_xlfn.XLOOKUP(Table1[[#This Row],[Audio Url]],Qc!C:C,Qc!F:F),"") -> same voice | AK54: =IFERROR(_xlfn.XLOOKUP(Table1[[#This Row],[Audio Url]],Qc!C:C,Qc!E:E),"") -> Taking From Friends And Family | AL54: - | AM54: - | AN54: =VLOOKUP(Table1[[#This Row],[LOCALITY]],Sheet2!$F:$H,3,0) -> Urban | AO54: No | AP54: =IF(Table1[[#This Row],[Audio Duration (in secs)]]>180,"Greater than 3 Minutes","Less than 3 Minutes") -> Greater than 3 Minutes | AQ54: =IFERROR(VLOOKUP(Table1[[#This Row],[சாதி/Caste]],MApping!$E$1:$F$10,2,0),"Others") -> PALLAR SC | AR54: =VLOOKUP(Table1[[#This Row],[பாலினம்/Gender]],Factor!$F$26:$I$28,4,0) -> 1.0470348 | AS54: =VLOOKUP(Table1[[#This Row],[பதிலளித்தவரின் வயது/Age Group]],Factor!$F$35:$I$39,4,0) -> 0.9752381 | AT54: =VLOOKUP(Table1[[#This Row],[பதிலளித்தவரின் வயது/Age Group]]&Table1[[#This Row],[பாலினம்/Gender]],Factor!$A$45:$G$53,7,0) -> 0.89824561 | AU54: =VLOOKUP(Table1[[#This Row],[2021 சட்டமன்றத் தேர்தலில் நீங்கள் எந்தக் கட்சிக்கு வாக்களித்தீர்கள்?/ Which party did you vote in 2021 Assembly Elections? ]],Factor!$F$9:$J$14,5,0) -> 1 | AV54: =VLOOKUP(Table1[[#This Row],[Rev Caste]],Factor!$F$59:$I$68,4,0) -> 1.28 | AW54: =Table1[[#This Row],[2021 Ae Factor]]*Table1[[#This Row],[Age & Gender Factor]] -> 0.89824561 | AX54: =Table1[[#This Row],[2021 Ae Factor]]*Table1[[#This Row],[Caste Factor]] -> 1.28 | AY54: =VALUE(MID(D54, FIND(",",D54)+2, FIND(")",D54)-FIND(",",D54)-2)) -> 78.699893
... A74: yJxCHpruHIo3Z7ks1pFq | B74: 2025-07-31 11:47:44.795498 | C74: 45869 | D74: (10.4140376, 78.6612648) | E74: CM76+J69,,Kudumiyamalai,622104,Tamil Nadu,India. | F74: https://firebasestorage.googleapis.com/v0/b/mindbrink-survey-production.appspot.com/o/audioFiles%2FAtznECuQc6klLPsRR6u2%2F2ukCmICpvKWhqTT6dgmjG6nFGjc2%2F2025-07-31%2011%3A47%3A41.237147.m4a?alt=media&token=94dde514-3e11-4f88-9fad-6c096ef793a9 | G74: 89 | H74: false | I74: U.Amir nisha | J74: +919698565662 | K74: Subramanian | L74: ILLUPUR | M74: KUDUMIYANMALAI | N74: Deivanai | O74: பெண்/Female | P74: 9514560831 | Q74: 46-60 | R74: இல்லத்தரசி/ Housewife | S74: 10,000க்கும் குறைவானது/Less than 10,000 | T74: திருப்திகரமானது / Satisfactory | U74: இல்லை/ No | V74: திமுக கூட்டணி / DMK Alliance | W74: மு.க. ஸ்டாலின் (திமுக) / M.K. Stalin (DMK) | X74: திமுக / DMK | Y74: DMK | Z74: - | AA74: இல்லை / No | AB74: - | AC74: திருப்திகரமல்ல / Unsatisfactory | AD74: பயனில்லை / Not effective | AE74: • ஆமாம்: அதிமுக கூட்டணி உடையும்/ Yes: AIADMK alliance will break up | AF74: தனித்துப் போட்டியிட வேண்டும் / Contest Independently | AG74: விவசாய நெருக்கடி / Agricultural crisis | AH74: BC | AI74: MUTTARAIYAR | AJ74: =IFERROR(_xlfn.XLOOKUP(Table1[[#This Row],[Audio Url]],Qc!C:C,Qc!F:F),"") -> 0 | AK74: =IFERROR(_xlfn.XLOOKUP(Table1[[#This Row],[Audio Url]],Qc!C:C,Qc!E:E),"") -> Not Asking All The Questions | AL74: - | AM74: - | AN74: =VLOOKUP(Table1[[#This Row],[LOCALITY]],Sheet2!$F:$H,3,0) -> Rural | AO74: Yes | AP74: =IF(Table1[[#This Row],[Audio Duration (in secs)]]>180,"Greater than 3 Minutes","Less than 3 Minutes") -> Less than 3 Minutes | AQ74: =IFERROR(VLOOKUP(Table1[[#This Row],[சாதி/Caste]],MApping!$E$1:$F$10,2,0),"Others") -> MUTTARAIYAR | AR74: =VLOOKUP(Table1[[#This Row],[பாலினம்/Gender]],Factor!$F$26:$I$28,4,0) -> 1.0470348 | AS74: =VLOOKUP(Table1[[#This Row],[பதிலளித்தவரின் வயது/Age Group]],Factor!$F$35:$I$39,4,0) -> 0.87972509 | AT74: =VLOOKUP(Table1[[#This Row],[பதிலளித்தவரின் வயது/Age Group]]&Table1[[#This Row],[பாலினம்/Gender]],Factor!$A$45:$G$53,7,0) -> 0.98461538 | AU74: =VLOOKUP(Table1[[#This Row],[2021 சட்டமன்றத் தேர்தலில் நீங்கள் எந்தக் கட்சிக்கு வாக்களித்தீர்கள்?/ Which party did you vote in 2021 Assembly Elections? ]],Factor!$F$9:$J$14,5,0) -> 0.73680082 | AV74: =VLOOKUP(Table1[[#This Row],[Rev Caste]],Factor!$F$59:$I$68,4,0) -> 1.2358621 | AW74: =Table1[[#This Row],[2021 Ae Factor]]*Table1[[#This Row],[Age & Gender Factor]] -> 0.72546543 | AX74: =Table1[[#This Row],[2021 Ae Factor]]*Table1[[#This Row],[Caste Factor]] -> 0.91058419 | AY74: =VALUE(MID(D74, FIND(",",D74)+2, FIND(")",D74)-FIND(",",D74)-2)) -> 78.661265
A75: 0ucC2BIAiNzc2dNOoVkR | B75: 2025-07-31 11:49:35.682915 | C75: 45869 | D75: (10.4557503, 78.7050881) | E75: FP44+82G,,Annavasal,622101,Tamil Nadu,India. | F75: https://firebasestorage.googleapis.com/v0/b/mindbrink-survey-production.appspot.com/o/audioFiles%2FAtznECuQc6klLPsRR6u2%2Fe5risFoEPidDckOLperfsZqxzae2%2F2025-07-31%2011%3A49%3A30.126787.m4a?alt=media&token=3b5577a6-5869-4459-8c0f-0375b79d5603 | G75: 265 | H75: false | I75: Sinthanai selvi | J75: +918508766594 | K75: Subramanian | L75: ILLUPUR | M75: ANNAVASAL | N75: கிருஷ்ணன் | O75: ஆண்/Male | P75: No Number | Q75: 60+ | R75: சொந்த தொழில் / சுயதொழில் செய்பவர்/ Self Employed/Business | S75: 10,000 - 25,000 | T75: திருப்திகரமல்ல/ Unsatisfactory | U75: இல்லை/ No | V75: அதிமுக கூட்டணி / AIADMK Alliance | W75: எடப்பாடி பழனிசாமி (அதிமுக) / Edappadi K. Palaniswami (AIADMK) | X75: அதிமுக / AIADMK | Y75: AIADMK | Z75: இல்லை, நான் அந்த கூட்டணிக்கு வாக்களிக்க மாட்டேன். / No, I will not vote for the alliance | AA75: இல்லை / No | AB75: - | AC75: திருப்திகரமல்ல / Unsatisfactory | AD75: பயனில்லை / Not effective | AE75: • இல்லை: திமுக மற்றும் அதிமுக கூட்டணிகள் இரண்டும் உடையாது/ No: Both DMK & AIADMK alliances will not break up | AF75: அதிமுக + பா.ஜ.க/ AIADMK + BJP | AG75: மதுபானம் / போதைப்பொருள் பழக்கம்/ Alcohol/Drug abuse | AH75: OBC | AI75: வண்ணார் | AJ75: =IFERROR(_xlfn.XLOOKUP(Table1[[#This Row],[Audio Url]],Qc!C:C,Qc!F:F),"") -> 0 | AK75: =IFERROR(_xlfn.XLOOKUP(Table1[[#This Row],[Audio Url]],Qc!C:C,Qc!E:E),"") -> Correctly Done | AL75: - | AM75: - | AN75: =VLOOKUP(Table1[[#This Row],[LOCALITY]],Sheet2!$F:$H,3,0) -> Urban | AO75: Yes | AP75: =IF(Table1[[#This Row],[Audio Duration (in secs)]]>180,"Greater than 3 Minutes","Less than 3 Minutes") -> Greater than 3 Minutes | AQ75: =IFERROR(VLOOKUP(Table1[[#This Row],[சாதி/Caste]],MApping!$E$1:$F$10,2,0),"Others") -> Others | AR75: =VLOOKUP(Table1[[#This Row],[பாலினம்/Gender]],Factor!$F$26:$I$28,4,0) -> 0.95700935 | AS75: =VLOOKUP(Table1[[#This Row],[பதிலளித்தவரின் வயது/Age Group]],Factor!$F$35:$I$39,4,0) -> 1.0308725 | AT75: =VLOOKUP(Table1[[#This Row],[பதிலளித்தவரின் வயது/Age Group]]&Table1[[#This Row],[பாலினம்/Gender]],Factor!$A$45:$G$53,7,0) -> 0.86292135 | AU75: =VLOOKUP(Table1[[#This Row],[2021 சட்டமன்றத் தேர்தலில் நீங்கள் எந்தக் கட்சிக்கு வாக்களித்தீர்கள்?/ Which party did you vote in 2021 Assembly Elections? ]],Factor!$F$9:$J$14,5,0) -> 1.3119425 | AV75: =VLOOKUP(Table1[[#This Row],[Rev Caste]],Factor!$F$59:$I$68,4,0) -> 0.14422535 | AW75: =Table1[[#This Row],[2021 Ae Factor]]*Table1[[#This Row],[Age & Gender Factor]] -> 1.1321032 | AX75: =Table1[[#This Row],[2021 Ae Factor]]*Table1[[#This Row],[Caste Factor]] -> 0.18921537 | AY75: =VALUE(MID(D75, FIND(",",D75)+2, FIND(")",D75)-FIND(",",D75)-2)) -> 78.705088
A76: RtHf60Y9eAmvwpX9bIqt | B76: 2025-07-31 11:51:10.734939 | C76: 45869 | D76: (10.413926, 78.6626696) | E76: Pudukottai - Manapparai Road,,Kudumiyamalai,622104,Tamil Nadu,India. | F76: https://firebasestorage.googleapis.com/v0/b/mindbrink-survey-production.appspot.com/o/audioFiles%2FAtznECuQc6klLPsRR6u2%2F2ukCmICpvKWhqTT6dgmjG6nFGjc2%2F2025-07-31%2011%3A51%3A07.084608.m4a?alt=media&token=83b01f36-06ed-41fd-b6eb-d2148c5b1cad | G76: 112 | H76: false | I76: U.Amir nisha | J76: +919698565662 | K76: Subramanian | L76: ILLUPUR | M76: KUDUMIYANMALAI | N76: Kalingasen | O76: ஆண்/Male | P76: 9786518127 | Q76: 60+ | R76: சொந்த தொழில் / சுயதொழில் செய்பவர்/ Self Employed/Business | S76: 10,000க்கும் குறைவானது/Less than 10,000 | T76: மேம்பாடு தேவை / Needs improvement | U76: ஆம் / Yes | V76: அதிமுக கூட்டணி / AIADMK Alliance | W76: எடப்பாடி பழனிசாமி (அதிமுக) / Edappadi K. Palaniswami (AIADMK) | X76: அதிமுக / AIADMK | Y76: AIADMK | Z76: உறுதி இல்லை / வேட்பாளரைப் பொறுத்தது/ Not sure / Depends on candidate | AA76: இல்லை / No | AB76: - | AC76: வேகம் குறைபாடுடன் செயல்படுகிறது / Needs more momentum | AD76: குறைவான ஈடுபாடு / Inadequate | AE76: • ஆமாம்: திமுக கூட்டணி உடையும் / Yes: DMK Alliance will break up | AF76: தனித்துப் போட்டியிட வேண்டும் / Contest Independently | AG76: விவசாய நெருக்கடி / Agricultural crisis | AH76: BC | AI76: MUTTARAIYAR | AJ76: =IFERROR(_xlfn.XLOOKUP(Table1[[#This Row],[Audio Url]],Qc!C:C,Qc!F:F),"") -> surveyor asking first two questions only | AK76: =IFERROR(_xlfn.XLOOKUP(Table1[[#This Row],[Audio Url]],Qc!C:C,Qc!E:E),"") -> Not Asking All The Questions | AL76: - | AM76: - | AN76: =VLOOKUP(Table1[[#This Row],[LOCALITY]],Sheet2!$F:$H,3,0) -> Rural | AO76: Yes | AP76: =IF(Table1[[#This Row],[Audio Duration (in secs)]]>180,"Greater than 3 Minutes","Less than 3 Minutes") -> Less than 3 Minutes | AQ76: =IFERROR(VLOOKUP(Table1[[#This Row],[சாதி/Caste]],MApping!$E$1:$F$10,2,0),"Others") -> MUTTARAIYAR | AR76: =VLOOKUP(Table1[[#This Row],[பாலினம்/Gender]],Factor!$F$26:$I$28,4,0) -> 0.95700935 | AS76: =VLOOKUP(Table1[[#This Row],[பதிலளித்தவரின் வயது/Age Group]],Factor!$F$35:$I$39,4,0) -> 1.0308725 | AT76: =VLOOKUP(Table1[[#This Row],[பதிலளித்தவரின் வயது/Age Group]]&Table1[[#This Row],[பாலினம்/Gender]],Factor!$A$45:$G$53,7,0) -> 0.86292135 | AU76: =VLOOKUP(Table1[[#This Row],[2021 சட்டமன்றத் தேர்தலில் நீங்கள் எந்தக் கட்சிக்கு வாக்களித்தீர்கள்?/ Which party did you vote in 2021 Assembly Elections? ]],Factor!$F$9:$J$14,5,0) -> 1.3119425 | AV76: =VLOOKUP(Table1[[#This Row],[Rev Caste]],Factor!$F$59:$I$68,4,0) -> 1.2358621 | AW76: =Table1[[#This Row],[2021 Ae Factor]]*Table1[[#This Row],[Age & Gender Factor]] -> 1.1321032 | AX76: =Table1[[#This Row],[2021 Ae Factor]]*Table1[[#This Row],[Caste Factor]] -> 1.62138 | AY76: =VALUE(MID(D76, FIND(",",D76)+2, FIND(")",D76)-FIND(",",D76)-2)) -> 78.66267
A77: 5xqt6Zzh33uxIz76NpHq | B77: 2025-07-31 11:56:07.640150 | C77: 45869 | D77: (10.4564413, 78.7044716) | E77: FP43+MRX,,Annavasal,622101,Tamil Nadu,India. | F77: https://firebasestorage.googleapis.com/v0/b/mindbrink-survey-production.appspot.com/o/audioFiles%2FAtznECuQc6klLPsRR6u2%2Fe5risFoEPidDckOLperfsZqxzae2%2F2025-07-31%2011%3A56%3A02.713735.m4a?alt=media&token=3fef27ca-553c-42d7-b302-23c2549cb1b4 | G77: 270 | H77: false | I77: Sinthanai selvi | J77: +918508766594 | K77: Subramanian | L77: ILLUPUR | M77: ANNAVASAL | N77: சின்னம்மாள் | O77: பெண்/Female | P77: 7825973595 | Q77: 31-45 | R77: இல்லத்தரசி/ Housewife | S77: 10,000 - 25,000 | T77: திருப்திகரமல்ல/ Unsatisfactory | U77: ஆம் / Yes | V77: அதிமுக கூட்டணி / AIADMK Alliance | W77: விஜய் (தமிழக வெற்றி கழகம்) / Vijay (TVK) | X77: தமிழக வெற்றி கழகம் / TVK | Y77: TVK | Z77: - | AA77: ஆமாம் / Yes | AB77: திமுக கூட்டணி / DMK Alliance | AC77: வேகம் குறைபாடுடன் செயல்படுகிறது / Needs more momentum | AD77: குறைவான ஈடுபாடு / Inadequate | AE77: • இல்லை: திமுக மற்றும் அதிமுக கூட்டணிகள் இரண்டும் உடையாது/ No: Both DMK & AIADMK alliances will not break up | AF77: தனித்துப் போட்டியிட வேண்டும் / Contest Independently | AG77: மதுபானம் / போதைப்பொருள் பழக்கம்/ Alcohol/Drug abuse | AH77: General | AI77: நாயக்கர் | AJ77: =IFERROR(_xlfn.XLOOKUP(Table1[[#This Row],[Audio Url]],Qc!C:C,Qc!F:F),"") -> 0 | AK77: =IFERROR(_xlfn.XLOOKUP(Table1[[#This Row],[Audio Url]],Qc!C:C,Qc!E:E),"") -> Correctly Done | AL77: - | AM77: - | AN77: =VLOOKUP(Table1[[#This Row],[LOCALITY]],Sheet2!$F:$H,3,0) -> Urban | AO77: Yes | AP77: =IF(Table1[[#This Row],[Audio Duration (in secs)]]>180,"Greater than 3 Minutes","Less than 3 Minutes") -> Greater than 3 Minutes | AQ77: =IFERROR(VLOOKUP(Table1[[#This Row],[சாதி/Caste]],MApping!$E$1:$F$10,2,0),"Others") -> Others | AR77: =VLOOKUP(Table1[[#This Row],[பாலினம்/Gender]],Factor!$F$26:$I$28,4,0) -> 1.0470348 | AS77: =VLOOKUP(Table1[[#This Row],[பதிலளித்தவரின் வயது/Age Group]],Factor!$F$35:$I$39,4,0) -> 1.0951872 | AT77: =VLOOKUP(Table1[[#This Row],[பதிலளித்தவரின் வயது/Age Group]]&Table1[[#This Row],[பாலினம்/Gender]],Factor!$A$45:$G$53,7,0) -> 1.107027 | AU77: =VLOOKUP(Table1[[#This Row],[2021 சட்டமன்றத் தேர்தலில் நீங்கள் எந்தக் கட்சிக்கு வாக்களித்தீர்கள்?/ Which party did you vote in 2021 Assembly Elections? ]],Factor!$F$9:$J$14,5,0) -> 1.3119425 | AV77: =VLOOKUP(Table1[[#This Row],[Rev Caste]],Factor!$F$59:$I$68,4,0) -> 0.14422535 | AW77: =Table1[[#This Row],[2021 Ae Factor]]*Table1[[#This Row],[Age & Gender Factor]] -> 1.4523558 | AX77: =Table1[[#This Row],[2021 Ae Factor]]*Table1[[#This Row],[Caste Factor]] -> 0.18921537 | AY77: =VALUE(MID(D77, FIND(",",D77)+2, FIND(")",D77)-FIND(",",D77)-2)) -> 78.704472
A78: gGmTtw0LNeciPOrr2Z2y | B78: 2025-07-31 11:58:23.749571 | C78: 45869 | D78: (10.4112259, 78.6638583) | E78: CM68+R3J,,Kudumiyamalai,622104,Tamil Nadu,India. | F78: https://firebasestorage.googleapis.com/v0/b/mindbrink-survey-production.appspot.com/o/audioFiles%2FAtznECuQc6klLPsRR6u2%2F2ukCmICpvKWhqTT6dgmjG6nFGjc2%2F2025-07-31%2011%3A58%3A18.146512.m4a?alt=media&token=def0b0d3-383f-4b02-900c-eeb1701db445 | G78: 225 | H78: false | I78: U.Amir nisha | J78: +919698565662 | K78: Subramanian | L78: ILLUPUR | M78: KUDUMIYANMALAI | N78: vasantha | O78: பெண்/Female | P78: 6379686026 | Q78: 31-45 | R78: இல்லத்தரசி/ Housewife | S78: 10,000க்கும் குறைவானது/Less than 10,000 | T78: மேம்பாடு தேவை / Needs improvement | U78: ஆம் / Yes | V78: நினைவில் இல்லை / Don’t Remember | W78: விஜய் (தமிழக வெற்றி கழகம்) / Vijay (TVK) | X78: திமுக / DMK | Y78: DMK | Z78: - | AA78: ஆமாம் / Yes | AB78: திமுக கூட்டணி / DMK Alliance | AC78: திருப்திகரமானது / Satisfactory | AD78: போதுமான ஈடுபாடு / Adequate | AE78: • ஆமாம்: திமுக மற்றும் அதிமுக கூட்டணிகள் இரண்டும் உடையும்/ Yes: Both DMK & AIADMK alliances will break up | AF78: தனித்துப் போட்டியிட வேண்டும் / Contest Independently | AG78: சட்டம் மற்றும் ஒழுங்கு/ Law and order | AH78: BC | AI78: CHOLIA VELLALAR | AJ78: =IFERROR(_xlfn.XLOOKUP(Table1[[#This Row],[Audio Url]],Qc!C:C,Qc!F:F),"") -> 0 | AK78: =IFERROR(_xlfn.XLOOKUP(Table1[[#This Row],[Audio Url]],Qc!C:C,Qc!E:E),"") -> Correctly Done | AL78: - | AM78: - | AN78: =VLOOKUP(Table1[[#This Row],[LOCALITY]],Sheet2!$F:$H,3,0) -> Rural | AO78: Yes | AP78: =IF(Table1[[#This Row],[Audio Duration (in secs)]]>180,"Greater than 3 Minutes","Less than 3 Minutes") -> Greater than 3 Minutes | AQ78: =IFERROR(VLOOKUP(Table1[[#This Row],[சாதி/Caste]],MApping!$E$1:$F$10,2,0),"Others") -> CHOLIA VELLALAR | AR78: =VLOOKUP(Table1[[#This Row],[பாலினம்/Gender]],Factor!$F$26:$I$28,4,0) -> 1.0470348 | AS78: =VLOOKUP(Table1[[#This Row],[பதிலளித்தவரின் வயது/Age Group]],Factor!$F$35:$I$39,4,0) -> 1.0951872 | AT78: =VLOOKUP(Table1[[#This Row],[பதிலளித்தவரின் வயது/Age Group]]&Table1[[#This Row],[பாலினம்/Gender]],Factor!$A$45:$G$53,7,0) -> 1.107027 | AU78: =VLOOKUP(Table1[[#This Row],[2021 சட்டமன்றத் தேர்தலில் நீங்கள் எந்தக் கட்சிக்கு வாக்களித்தீர்கள்?/ Which party did you vote in 2021 Assembly Elections? ]],Factor!$F$9:$J$14,5,0) -> 1 | AV78: =VLOOKUP(Table1[[#This Row],[Rev Caste]],Factor!$F$59:$I$68,4,0) -> 1.0666667 | AW78: =Table1[[#This Row],[2021 Ae Factor]]*Table1[[#This Row],[Age & Gender Factor]] -> 1.107027 | AX78: =Table1[[#This Row],[2021 Ae Factor]]*Table1[[#This Row],[Caste Factor]] -> 1.0666667 | AY78: =VALUE(MID(D78, FIND(",",D78)+2, FIND(")",D78)-FIND(",",D78)-2)) -> 78.663858
A79: peBZosCHNSqG3KLBKYvr | B79: 2025-07-31 12:01:42.914078 | C79: 45869 | D79: (10.4559999, 78.7047606) | E79: FP44+836,,Annavasal,622101,Tamil Nadu,India. | F79: https://firebasestorage.googleapis.com/v0/b/mindbrink-survey-production.appspot.com/o/audioFiles%2FAtznECuQc6klLPsRR6u2%2Fe5risFoEPidDckOLperfsZqxzae2%2F2025-07-31%2012%3A01%3A37.640419.m4a?alt=media&token=e11375f1-072a-4f08-92af-873eabf1b6cd | G79: 206 | H79: false | I79: Sinthanai selvi | J79: +918508766594 | K79: Subramanian | L79: ILLUPUR | M79: ANNAVASAL | N79: ஜோதி | O79: பெண்/Female | P79: 8489743837 | Q79: 31-45 | R79: இல்லத்தரசி/ Housewife | S79: 10,000 - 25,000 | T79: மேம்பாடு தேவை / Needs improvement | U79: ஆம் / Yes | V79: அதிமுக கூட்டணி / AIADMK Alliance | W79: விஜய் (தமிழக வெற்றி கழகம்) / Vijay (TVK) | X79: தமிழக வெற்றி கழகம் / TVK | Y79: TVK | Z79: - | AA79: ஆமாம் / Yes | AB79: திமுக கூட்டணி / DMK Alliance | AC79: வேகம் குறைபாடுடன் செயல்படுகிறது / Needs more momentum | AD79: குறைவான ஈடுபாடு / Inadequate | AE79: • ஆமாம்: திமுக கூட்டணி உடையும் / Yes: DMK Alliance will break up | AF79: அதிமுக / AIADMK | AG79: வேலைவாய்ப்பு குறைபாடு / Unemployment | AH79: General | AI79: நாயக்கர் | AJ79: =IFERROR(_xlfn.XLOOKUP(Table1[[#This Row],[Audio Url]],Qc!C:C,Qc!F:F),"") -> 0 | AK79: =IFERROR(_xlfn.XLOOKUP(Table1[[#This Row],[Audio Url]],Qc!C:C,Qc!E:E),"") -> Correctly Done | AL79: - | AM79: - | AN79: =VLOOKUP(Table1[[#This Row],[LOCALITY]],Sheet2!$F:$H,3,0) -> Urban | AO79: Yes | AP79: =IF(Table1[[#This Row],[Audio Duration (in secs)]]>180,"Greater than 3 Minutes","Less than 3 Minutes") -> Greater than 3 Minutes | AQ79: =IFERROR(VLOOKUP(Table1[[#This Row],[சாதி/Caste]],MApping!$E$1:$F$10,2,0),"Others") -> Others | AR79: =VLOOKUP(Table1[[#This Row],[பாலினம்/Gender]],Factor!$F$26:$I$28,4,0) -> 1.0470348 | AS79: =VLOOKUP(Table1[[#This Row],[பதிலளித்தவரின் வயது/Age Group]],Factor!$F$35:$I$39,4,0) -> 1.0951872 | AT79: =VLOOKUP(Table1[[#This Row],[பதிலளித்தவரின் வயது/Age Group]]&Table1[[#This Row],[பாலினம்/Gender]],Factor!$A$45:$G$53,7,0) -> 1.107027 | AU79: =VLOOKUP(Table1[[#This Row],[2021 சட்டமன்றத் தேர்தலில் நீங்கள் எந்தக் கட்சிக்கு வாக்களித்தீர்கள்?/ Which party did you vote in 2021 Assembly Elections? ]],Factor!$F$9:$J$14,5,0) -> 1.3119425 | AV79: =VLOOKUP(Table1[[#This Row],[Rev Caste]],Factor!$F$59:$I$68,4,0) -> 0.14422535 | AW79: =Table1[[#This Row],[2021 Ae Factor]]*Table1[[#This Row],[Age & Gender Factor]] -> 1.4523558 | AX79: =Table1[[#This Row],[2021 Ae Factor]]*Table1[[#This Row],[Caste Factor]] -> 0.18921537 | AY79: =VALUE(MID(D79, FIND(",",D79)+2, FIND(")",D79)-FIND(",",D79)-2)) -> 78.704761
A80: iZkVnvdVESGZzLFapHzZ | B80: 2025-07-31 12:02:03.858134 | C80: 45869 | D80: (10.4117986, 78.66373) | E80: CM68+R3J,,Kudumiyamalai,622104,Tamil Nadu,India. | F80: https://firebasestorage.googleapis.com/v0/b/mindbrink-survey-production.appspot.com/o/audioFiles%2FAtznECuQc6klLPsRR6u2%2F2ukCmICpvKWhqTT6dgmjG6nFGjc2%2F2025-07-31%2012%3A02%3A00.545967.m4a?alt=media&token=07dc2432-1808-454e-a12e-45bd8c4e8792 | G80: 115 | H80: false | I80: U.Amir nisha | J80: +919698565662 | K80: Subramanian | L80: ILLUPUR | M80: KUDUMIYANMALAI | N80: Govindasamy | O80: ஆண்/Male | P80: 9655474614 | Q80: 60+ | R80: விவசாயி/ Farmer | S80: 10,000 - 25,000 | T80: மேம்பாடு தேவை / Needs improvement | U80: ஆம் / Yes | V80: அதிமுக கூட்டணி / AIADMK Alliance | W80: விஜய் (தமிழக வெற்றி கழகம்) / Vijay (TVK) | X80: அதிமுக / AIADMK | Y80: TVK | Z80: ஆம், TVK கூட்டணிக்கு வாக்களிப்பேன் / Yes, I will shift my vote to the TVK alliance | AA80: ஆமாம் / Yes | AB80: திமுக கூட்டணி / DMK Alliance | AC80: திருப்திகரமானது / Satisfactory | AD80: போதுமான ஈடுபாடு / Adequate | AE80: • ஆமாம்: திமுக கூட்டணி உடையும் / Yes: DMK Alliance will break up | AF80: தனித்துப் போட்டியிட வேண்டும் / Contest Independently | AG80: சட்டம் மற்றும் ஒழுங்கு/ Law and order | AH80: BC | AI80: CHOLIA VELLALAR | AJ80: =IFERROR(_xlfn.XLOOKUP(Table1[[#This Row],[Audio Url]],Qc!C:C,Qc!F:F),"") -> 0 | AK80: =IFERROR(_xlfn.XLOOKUP(Table1[[#This Row],[Audio Url]],Qc!C:C,Qc!E:E),"") -> Fake Audio/Empty Audio | AL80: - | AM80: - | AN80: =VLOOKUP(Table1[[#This Row],[LOCALITY]],Sheet2!$F:$H,3,0) -> Rural | AO80: No | AP80: =IF(Table1[[#This Row],[Audio Duration (in secs)]]>180,"Greater than 3 Minutes","Less than 3 Minutes") -> Less than 3 Minutes | AQ80: =IFERROR(VLOOKUP(Table1[[#This Row],[சாதி/Caste]],MApping!$E$1:$F$10,2,0),"Others") -> CHOLIA VELLALAR | AR80: =VLOOKUP(Table1[[#This Row],[பாலினம்/Gender]],Factor!$F$26:$I$28,4,0) -> 0.95700935 | AS80: =VLOOKUP(Table1[[#This Row],[பதிலளித்தவரின் வயது/Age Group]],Factor!$F$35:$I$39,4,0) -> 1.0308725 | AT80: =VLOOKUP(Table1[[#This Row],[பதிலளித்தவரின் வயது/Age Group]]&Table1[[#This Row],[பாலினம்/Gender]],Factor!$A$45:$G$53,7,0) -> 0.86292135 | AU80: =VLOOKUP(Table1[[#This Row],[2021 சட்டமன்றத் தேர்தலில் நீங்கள் எந்தக் கட்சிக்கு வாக்களித்தீர்கள்?/ Which party did you vote in 2021 Assembly Elections? ]],Factor!$F$9:$J$14,5,0) -> 1.3119425 | AV80: =VLOOKUP(Table1[[#This Row],[Rev Caste]],Factor!$F$59:$I$68,4,0) -> 1.0666667 | AW80: =Table1[[#This Row],[2021 Ae Factor]]*Table1[[#This Row],[Age & Gender Factor]] -> 1.1321032 | AX80: =Table1[[#This Row],[2021 Ae Factor]]*Table1[[#This Row],[Caste Factor]] -> 1.3994054 | AY80: =VALUE(MID(D80, FIND(",",D80)+2, FIND(")",D80)-FIND(",",D80)-2)) -> 78.66373
A81: lwdKkhaXYzudTNNxznZO | B81: 2025-07-31 12:11:28.302699 | C81: 45869 | D81: (10.4126633, 78.6616787) | E81: Kudumiyamalai,,Kudumiyamalai,622104,Tamil Nadu,India. | F81: https://firebasestorage.googleapis.com/v0/b/mindbrink-survey-production.appspot.com/o/audioFiles%2FAtznECuQc6klLPsRR6u2%2F2ukCmICpvKWhqTT6dgmjG6nFGjc2%2F2025-07-31%2012%3A11%3A21.370367.m4a?alt=media&token=db1019b7-3c84-49d9-923b-98e35d77dee0 | G81: 274 | H81: false | I81: U.Amir nisha | J81: +919698565662 | K81: Subramanian | L81: ILLUPUR | M81: KUDUMIYANMALAI | N81: 6385107834 | O81: பெண்/Female | P81: 6385107834 | Q81: 46-60 | R81: இல்லத்தரசி/ Housewife | S81: 10,000க்கும் குறைவானது/Less than 10,000 | T81: மேம்பாடு தேவை / Needs improvement | U81: உறுதியாக தெரியவில்லை / Not Sure | V81: நினைவில் இல்லை / Don’t Remember | W81: விஜய் (தமிழக வெற்றி கழகம்) / Vijay (TVK) | X81: அதிமுக / AIADMK | Y81: TVK | Z81: ஆம், TVK கூட்டணிக்கு வாக்களிப்பேன் / Yes, I will shift my vote to the TVK alliance | AA81: ஆமாம் / Yes | AB81: திமுக கூட்டணி / DMK Alliance | AC81: வேகம் குறைபாடுடன் செயல்படுகிறது / Needs more momentum | AD81: குறைவான ஈடுபாடு / Inadequate | AE81: • ஆமாம்: திமுக கூட்டணி உடையும் / Yes: DMK Alliance will break up | AF81: தனித்துப் போட்டியிட வேண்டும் / Contest Independently | AG81: விவசாய நெருக்கடி / Agricultural crisis | AH81: BC | AI81: MUTTARAIYAR | AJ81: =IFERROR(_xlfn.XLOOKUP(Table1[[#This Row],[Audio Url]],Qc!C:C,Qc!F:F),"") -> 0 | AK81: =IFERROR(_xlfn.XLOOKUP(Table1[[#This Row],[Audio Url]],Qc!C:C,Qc!E:E),"") -> Not Doing It Properly | AL81: - | AM81: - | AN81: =VLOOKUP(Table1[[#This Row],[LOCALITY]],Sheet2!$F:$H,3,0) -> Rural | AO81: Yes | AP81: =IF(Table1[[#This Row],[Audio Duration (in secs)]]>180,"Greater than 3 Minutes","Less than 3 Minutes") -> Greater than 3 Minutes | AQ81: =IFERROR(VLOOKUP(Table1[[#This Row],[சாதி/Caste]],MApping!$E$1:$F$10,2,0),"Others") -> MUTTARAIYAR | AR81: =VLOOKUP(Table1[[#This Row],[பாலினம்/Gender]],Factor!$F$26:$I$28,4,0) -> 1.0470348 | AS81: =VLOOKUP(Table1[[#This Row],[பதிலளித்தவரின் வயது/Age Group]],Factor!$F$35:$I$39,4,0) -> 0.87972509 | AT81: =VLOOKUP(Table1[[#This Row],[பதிலளித்தவரின் வயது/Age Group]]&Table1[[#This Row],[பாலினம்/Gender]],Factor!$A$45:$G$53,7,0) -> 0.98461538 | AU81: =VLOOKUP(Table1[[#This Row],[2021 சட்டமன்றத் தேர்தலில் நீங்கள் எந்தக் கட்சிக்கு வாக்களித்தீர்கள்?/ Which party did you vote in 2021 Assembly Elections? ]],Factor!$F$9:$J$14,5,0) -> 1 | AV81: =VLOOKUP(Table1[[#This Row],[Rev Caste]],Factor!$F$59:$I$68,4,0) -> 1.2358621 | AW81: =Table1[[#This Row],[2021 Ae Factor]]*Table1[[#This Row],[Age & Gender Factor]] -> 0.98461538 | AX81: =Table1[[#This Row],[2021 Ae Factor]]*Table1[[#This Row],[Caste Factor]] -> 1.2358621 | AY81: =VALUE(MID(D81, FIND(",",D81)+2, FIND(")",D81)-FIND(",",D81)-2)) -> 78.661679
A82: s5QhZOc9bClBQwVqegli | B82: 2025-07-31 12:26:03.844985 | C82: 45869 | D82: (10.4138537, 78.6639229) | E82: CM77+FQ8,,Illupur,622104,Tamil Nadu,India. | F82: https://firebasestorage.googleapis.com/v0/b/mindbrink-survey-production.appspot.com/o/audioFiles%2FAtznECuQc6klLPsRR6u2%2F2ukCmICpvKWhqTT6dgmjG6nFGjc2%2F2025-07-31%2012%3A25%3A59.298188.m4a?alt=media&token=18327583-6bb7-4347-a3fb-3a10972c9127 | G82: 167 | H82: false | I82: U.Amir nisha | J82: +919698565662 | K82: Subramanian | L82: ILLUPUR | M82: KUDUMIYANMALAI | N82: Vellaisamy | O82: ஆண்/Male | P82: 9787167694 | Q82: 46-60 | R82: சொந்த தொழில் / சுயதொழில் செய்பவர்/ Self Employed/Business | S82: 10,000 - 25,000 | T82: திருப்திகரமானது / Satisfactory | U82: இல்லை/ No | V82: திமுக கூட்டணி / DMK Alliance | W82: மு.க. ஸ்டாலின் (திமுக) / M.K. Stalin (DMK) | X82: திமுக / DMK | Y82: DMK | Z82: - | AA82: இல்லை / No | AB82: - | AC82: வேகம் குறைபாடுடன் செயல்படுகிறது / Needs more momentum | AD82: குறைவான ஈடுபாடு / Inadequate | AE82: • ஆமாம்: அதிமுக கூட்டணி உடையும்/ Yes: AIADMK alliance will break up | AF82: தனித்துப் போட்டியிட வேண்டும் / Contest Independently | AG82: மதுபானம் / போதைப்பொருள் பழக்கம்/ Alcohol/Drug abuse | AH82: BC | AI82: MUKKULATHOR | AJ82: =IFERROR(_xlfn.XLOOKUP(Table1[[#This Row],[Audio Url]],Qc!C:C,Qc!F:F),"") -> 0 | AK82: =IFERROR(_xlfn.XLOOKUP(Table1[[#This Row],[Audio Url]],Qc!C:C,Qc!E:E),"") -> Not Asking All The Questions | AL82: - | AM82: - | AN82: =VLOOKUP(Table1[[#This Row],[LOCALITY]],Sheet2!$F:$H,3,0) -> Rural | AO82: Yes | AP82: =IF(Table1[[#This Row],[Audio Duration (in secs)]]>180,"Greater than 3 Minutes","Less than 3 Minutes") -> Less than 3 Minutes | AQ82: =IFERROR(VLOOKUP(Table1[[#This Row],[சாதி/Caste]],MApping!$E$1:$F$10,2,0),"Others") -> MUKKULATHOR | AR82: =VLOOKUP(Table1[[#This Row],[பாலினம்/Gender]],Factor!$F$26:$I$28,4,0) -> 0.95700935 | AS82: =VLOOKUP(Table1[[#This Row],[பதிலளித்தவரின் வயது/Age Group]],Factor!$F$35:$I$39,4,0) -> 0.87972509 | AT82: =VLOOKUP(Table1[[#This Row],[பதிலளித்தவரின் வயது/Age Group]]&Table1[[#This Row],[பாலினம்/Gender]],Factor!$A$45:$G$53,7,0) -> 0.79503106 | AU82: =VLOOKUP(Table1[[#This Row],[2021 சட்டமன்றத் தேர்தலில் நீங்கள் எந்தக் கட்சிக்கு வாக்களித்தீர்கள்?/ Which party did you vote in 2021 Assembly Elections? ]],Factor!$F$9:$J$14,5,0) -> 0.73680082 | AV82: =VLOOKUP(Table1[[#This Row],[Rev Caste]],Factor!$F$59:$I$68,4,0) -> 1.3479184 | AW82: =Table1[[#This Row],[2021 Ae Factor]]*Table1[[#This Row],[Age & Gender Factor]] -> 0.58577954 | AX82: =Table1[[#This Row],[2021 Ae Factor]]*Table1[[#This Row],[Caste Factor]] -> 0.99314736 | AY82: =VALUE(MID(D82, FIND(",",D82)+2, FIND(")",D82)-FIND(",",D82)-2)) -> 78.663923
A83: YgdS2uqAxqme4GLxIVco | B83: 2025-07-31 12:30:02.268182 | C83: 45869 | D83: (10.4136401, 78.6638611) | E83: - | F83: https://firebasestorage.googleapis.com/v0/b/mindbrink-survey-production.appspot.com/o/audioFiles%2FAtznECuQc6klLPsRR6u2%2F2ukCmICpvKWhqTT6dgmjG6nFGjc2%2F2025-07-31%2012%3A29%3A58.585006.m4a?alt=media&token=948c5246-12c2-4dba-8b3f-abf8e40cef51 | G83: 115 | H83: false | I83: U.Amir nisha | J83: +919698565662 | K83: Subramanian | L83: ILLUPUR | M83: KUDUMIYANMALAI | N83: Vijay | O83: ஆண்/Male | P83: 9360147834 | Q83: 18-30 | R83: மாணவர்/ Student | S83: 10,000க்கும் குறைவானது/Less than 10,000 | T83: திருப்திகரமல்ல/ Unsatisfactory | U83: ஆம் / Yes | V83: வாக்களிக்கவில்லை / Did not Vote | W83: விஜய் (தமிழக வெற்றி கழகம்) / Vijay (TVK) | X83: தமிழக வெற்றி கழகம் / TVK | Y83: TVK | Z83: - | AA83: ஆமாம் / Yes | AB83: திமுக கூட்டணி / DMK Alliance | AC83: திருப்திகரமானது / Satisfactory | AD83: போதுமான ஈடுபாடு / Adequate | AE83: • ஆமாம்: திமுக மற்றும் அதிமுக கூட்டணிகள் இரண்டும் உடையும்/ Yes: Both DMK & AIADMK alliances will break up | AF83: தனித்துப் போட்டியிட வேண்டும் / Contest Independently | AG83: வேலைவாய்ப்பு குறைபாடு / Unemployment | AH83: BC | AI83: MUKKULATHOR | AJ83: =IFERROR(_xlfn.XLOOKUP(Table1[[#This Row],[Audio Url]],Qc!C:C,Qc!F:F),"") -> 0 | AK83: =IFERROR(_xlfn.XLOOKUP(Table1[[#This Row],[Audio Url]],Qc!C:C,Qc!E:E),"") -> Not Asking All The Questions | AL83: - | AM83: - | AN83: =VLOOKUP(Table1[[#This Row],[LOCALITY]],Sheet2!$F:$H,3,0) -> Rural | AO83: Yes | AP83: =IF(Table1[[#This Row],[Audio Duration (in secs)]]>180,"Greater than 3 Minutes","Less than 3 Minutes") -> Less than 3 Minutes | AQ83: =IFERROR(VLOOKUP(Table1[[#This Row],[சாதி/Caste]],MApping!$E$1:$F$10,2,0),"Others") -> MUKKULATHOR | AR83: =VLOOKUP(Table1[[#This Row],[பாலினம்/Gender]],Factor!$F$26:$I$28,4,0) -> 0.95700935 | AS83: =VLOOKUP(Table1[[#This Row],[பதிலளித்தவரின் வயது/Age Group]],Factor!$F$35:$I$39,4,0) -> 0.9752381 | AT83: =VLOOKUP(Table1[[#This Row],[பதிலளித்தவரின் வயது/Age Group]]&Table1[[#This Row],[பாலினம்/Gender]],Factor!$A$45:$G$53,7,0) -> 1.0666667 | AU83: =VLOOKUP(Table1[[#This Row],[2021 சட்டமன்றத் தேர்தலில் நீங்கள் எந்தக் கட்சிக்கு வாக்களித்தீர்கள்?/ Which party did you vote in 2021 Assembly Elections? ]],Factor!$F$9:$J$14,5,0) -> 1 | AV83: =VLOOKUP(Table1[[#This Row],[Rev Caste]],Factor!$F$59:$I$68,4,0) -> 1.3479184 | AW83: =Table1[[#This Row],[2021 Ae Factor]]*Table1[[#This Row],[Age & Gender Factor]] -> 1.0666667 | AX83: =Table1[[#This Row],[2021 Ae Factor]]*Table1[[#This Row],[Caste Factor]] -> 1.3479184 | AY83: =VALUE(MID(D83, FIND(",",D83)+2, FIND(")",D83)-FIND(",",D83)-2)) -> 78.663861
A84: vngmGT6wtz3y245u27iX | B84: 2025-07-31 12:54:02.522546 | C84: 45869 | D84: (10.4140833, 78.6614676) | E84: CM76+J69,,Kudumiyamalai,622104,Tamil Nadu,India. | F84: https://firebasestorage.googleapis.com/v0/b/mindbrink-survey-production.appspot.com/o/audioFiles%2FAtznECuQc6klLPsRR6u2%2FfYiv0HvGk4VbFlXYwsKbSZ6fwXI2%2F2025-07-31%2012%3A53%3A58.664428.m4a?alt=media&token=975e795a-f41a-4e55-ac3d-f6e9588e9e35 | G84: 116 | H84: false | I84: A.Banu | J84: +919443892814 | K84: Subramanian | L84: ILLUPUR | M84: KUDUMIYANMALAI | N84: Santhi | O84: பெண்/Female | P84: 8940461677 | Q84: 31-45 | R84: இல்லத்தரசி/ Housewife | S84: 10,000க்கும் குறைவானது/Less than 10,000 | T84: மேம்பாடு தேவை / Needs improvement | U84: ஆம் / Yes | V84: நினைவில் இல்லை / Don’t Remember | W84: விஜய் (தமிழக வெற்றி கழகம்) / Vijay (TVK) | X84: அதிமுக / AIADMK | Y84: TVK | Z84: உறுதி இல்லை / வேட்பாளரைப் பொறுத்தது/ Not sure / Depends on candidate | AA84: ஆமாம் / Yes | AB84: திமுக கூட்டணி / DMK Alliance | AC84: வேகம் குறைபாடுடன் செயல்படுகிறது / Needs more momentum | AD84: குறைவான ஈடுபாடு / Inadequate | AE84: • ஆமாம்: திமுக கூட்டணி உடையும் / Yes: DMK Alliance will break up | AF84: தனித்துப் போட்டியிட வேண்டும் / Contest Independently | AG84: வேலைவாய்ப்பு குறைபாடு / Unemployment | AH84: BC | AI84: MUKKULATHOR | AJ84: =IFERROR(_xlfn.XLOOKUP(Table1[[#This Row],[Audio Url]],Qc!C:C,Qc!F:F),"") -> 0 | AK84: =IFERROR(_xlfn.XLOOKUP(Table1[[#This Row],[Audio Url]],Qc!C:C,Qc!E:E),"") -> Fake Audio/Empty Audio | AL84: - | AM84: - | AN84: =VLOOKUP(Table1[[#This Row],[LOCALITY]],Sheet2!$F:$H,3,0) -> Rural | AO84: No | AP84: =IF(Table1[[#This Row],[Audio Duration (in secs)]]>180,"Greater than 3 Minutes","Less than 3 Minutes") -> Less than 3 Minutes | AQ84: =IFERROR(VLOOKUP(Table1[[#This Row],[சாதி/Caste]],MApping!$E$1:$F$10,2,0),"Others") -> MUKKULATHOR | AR84: =VLOOKUP(Table1[[#This Row],[பாலினம்/Gender]],Factor!$F$26:$I$28,4,0) -> 1.0470348 | AS84: =VLOOKUP(Table1[[#This Row],[பதிலளித்தவரின் வயது/Age Group]],Factor!$F$35:$I$39,4,0) -> 1.0951872 | AT84: =VLOOKUP(Table1[[#This Row],[பதிலளித்தவரின் வயது/Age Group]]&Table1[[#This Row],[பாலினம்/Gender]],Factor!$A$45:$G$53,7,0) -> 1.107027 | AU84: =VLOOKUP(Table1[[#This Row],[2021 சட்டமன்றத் தேர்தலில் நீங்கள் எந்தக் கட்சிக்கு வாக்களித்தீர்கள்?/ Which party did you vote in 2021 Assembly Elections? ]],Factor!$F$9:$J$14,5,0) -> 1 | AV84: =VLOOKUP(Table1[[#This Row],[Rev Caste]],Factor!$F$59:$I$68,4,0) -> 1.3479184 | AW84: =Table1[[#This Row],[2021 Ae Factor]]*Table1[[#This Row],[Age & Gender Factor]] -> 1.107027 | AX84: =Table1[[#This Row],[2021 Ae Factor]]*Table1[[#This Row],[Caste Factor]] -> 1.3479184 | AY84: =VALUE(MID(D84, FIND(",",D84)+2, FIND(")",D84)-FIND(",",D84)-2)) -> 78.661468
A85: leEADqwPcKz6BotL4x9N | B85: 2025-07-31 12:57:44.968910 | C85: 45869 | D85: (10.41389, 78.6607633) | E85: CM76+J69,,Kudumiyamalai,622104,Tamil Nadu,India. | F85: https://firebasestorage.googleapis.com/v0/b/mindbrink-survey-production.appspot.com/o/audioFiles%2FAtznECuQc6klLPsRR6u2%2FfYiv0HvGk4VbFlXYwsKbSZ6fwXI2%2F2025-07-31%2012%3A57%3A40.831785.m4a?alt=media&token=225cfa40-7366-4ae9-8caf-a6337dacedaf | G85: 125 | H85: false | I85: A.Banu | J85: +919443892814 | K85: Subramanian | L85: ILLUPUR | M85: KUDUMIYANMALAI | N85: sugumar | O85: ஆண்/Male | P85: 7094139842 | Q85: 31-45 | R85: சொந்த தொழில் / சுயதொழில் செய்பவர்/ Self Employed/Business | S85: 10,000 - 25,000 | T85: திருப்திகரமானது / Satisfactory | U85: ஆம் / Yes | V85: திமுக கூட்டணி / DMK Alliance | W85: மு.க. ஸ்டாலின் (திமுக) / M.K. Stalin (DMK) | X85: திமுக / DMK | Y85: DMK | Z85: - | AA85: ஆமாம் / Yes | AB85: அதிமுக கூட்டணி / AIADMK Alliance | AC85: வேகம் குறைபாடுடன் செயல்படுகிறது / Needs more momentum | AD85: குறைவான ஈடுபாடு / Inadequate | AE85: • ஆமாம்: அதிமுக கூட்டணி உடையும்/ Yes: AIADMK alliance will break up | AF85: தனித்துப் போட்டியிட வேண்டும் / Contest Independently | AG85: சட்டம் மற்றும் ஒழுங்கு/ Law and order | AH85: BC | AI85: MUKKULATHOR | AJ85: =IFERROR(_xlfn.XLOOKUP(Table1[[#This Row],[Audio Url]],Qc!C:C,Qc!F:F),"") -> 0 | AK85: =IFERROR(_xlfn.XLOOKUP(Table1[[#This Row],[Audio Url]],Qc!C:C,Qc!E:E),"") -> Fake Audio/Empty Audio | AL85: - | AM85: - | AN85: =VLOOKUP(Table1[[#This Row],[LOCALITY]],Sheet2!$F:$H,3,0) -> Rural | AO85: No | AP85: =IF(Table1[[#This Row],[Audio Duration (in secs)]]>180,"Greater than 3 Minutes","Less than 3 Minutes") -> Less than 3 Minutes | AQ85: =IFERROR(VLOOKUP(Table1[[#This Row],[சாதி/Caste]],MApping!$E$1:$F$10,2,0),"Others") -> MUKKULATHOR | AR85: =VLOOKUP(Table1[[#This Row],[பாலினம்/Gender]],Factor!$F$26:$I$28,4,0) -> 0.95700935 | AS85: =VLOOKUP(Table1[[#This Row],[பதிலளித்தவரின் வயது/Age Group]],Factor!$F$35:$I$39,4,0) -> 1.0951872 | AT85: =VLOOKUP(Table1[[#This Row],[பதிலளித்தவரின் வயது/Age Group]]&Table1[[#This Row],[பாலினம்/Gender]],Factor!$A$45:$G$53,7,0) -> 1.0835979 | AU85: =VLOOKUP(Table1[[#This Row],[2021 சட்டமன்றத் தேர்தலில் நீங்கள் எந்தக் கட்சிக்கு வாக்களித்தீர்கள்?/ Which party did you vote in 2021 Assembly Elections? ]],Factor!$F$9:$J$14,5,0) -> 0.73680082 | AV85: =VLOOKUP(Table1[[#This Row],[Rev Caste]],Factor!$F$59:$I$68,4,0) -> 1.3479184 | AW85: =Table1[[#This Row],[2021 Ae Factor]]*Table1[[#This Row],[Age & Gender Factor]] -> 0.79839581 | AX85: =Table1[[#This Row],[2021 Ae Factor]]*Table1[[#This Row],[Caste Factor]] -> 0.99314736 | AY85: =VALUE(MID(D85, FIND(",",D85)+2, FIND(")",D85)-FIND(",",D85)-2)) -> 78.660763
A86: bpigyKPstYjv6bOZoVvd | B86: 2025-07-31 13:01:40.802502 | C86: 45869 | D86: (10.4139133, 78.6610367) | E86: CM76+J69,,Kudumiyamalai,622104,Tamil Nadu,India. | F86: https://firebasestorage.googleapis.com/v0/b/mindbrink-survey-production.appspot.com/o/audioFiles%2FAtznECuQc6klLPsRR6u2%2FfYiv0HvGk4VbFlXYwsKbSZ6fwXI2%2F2025-07-31%2013%3A01%3A36.586293.m4a?alt=media&token=50619f91-5f83-476b-9cb0-b841b3c6727f | G86: 208 | H86: false | I86: A.Banu | J86: +919443892814 | K86: Subramanian | L86: ILLUPUR | M86: KUDUMIYANMALAI | N86: Subramaniyan | O86: ஆண்/Male | P86: 7538805131 | Q86: 46-60 | R86: சொந்த தொழில் / சுயதொழில் செய்பவர்/ Self Employed/Business | S86: 10,000க்கும் குறைவானது/Less than 10,000 | T86: திருப்திகரமல்ல/ Unsatisfactory | U86: ஆம் / Yes | V86: திமுக கூட்டணி / DMK Alliance | W86: விஜய் (தமிழக வெற்றி கழகம்) / Vijay (TVK) | X86: அதிமுக / AIADMK | Y86: TVK | Z86: உறுதி இல்லை / வேட்பாளரைப் பொறுத்தது/ Not sure / Depends on candidate | AA86: ஆமாம் / Yes | AB86: திமுக கூட்டணி / DMK Alliance | AC86: வேகம் குறைபாடுடன் செயல்படுகிறது / Needs more momentum | AD86: போதுமான ஈடுபாடு / Adequate | AE86: • ஆமாம்: திமுக கூட்டணி உடையும் / Yes: DMK Alliance will break up | AF86: அதிமுக / AIADMK | AG86: வேலைவாய்ப்பு குறைபாடு / Unemployment | AH86: OBC | AI86: URALI GOUNDER | AJ86: =IFERROR(_xlfn.XLOOKUP(Table1[[#This Row],[Audio Url]],Qc!C:C,Qc!F:F),"") -> randomly asking questions | AK86: =IFERROR(_xlfn.XLOOKUP(Table1[[#This Row],[Audio Url]],Qc!C:C,Qc!E:E),"") -> Not Asking All The Questions | AL86: - | AM86: - | AN86: =VLOOKUP(Table1[[#This Row],[LOCALITY]],Sheet2!$F:$H,3,0) -> Rural | AO86: Yes | AP86: =IF(Table1[[#This Row],[Audio Duration (in secs)]]>180,"Greater than 3 Minutes","Less than 3 Minutes") -> Greater than 3 Minutes | AQ86: =IFERROR(VLOOKUP(Table1[[#This Row],[சாதி/Caste]],MApping!$E$1:$F$10,2,0),"Others") -> URALI GOUNDER | AR86: =VLOOKUP(Table1[[#This Row],[பாலினம்/Gender]],Factor!$F$26:$I$28,4,0) -> 0.95700935 | AS86: =VLOOKUP(Table1[[#This Row],[பதிலளித்தவரின் வயது/Age Group]],Factor!$F$35:$I$39,4,0) -> 0.87972509 | AT86: =VLOOKUP(Table1[[#This Row],[பதிலளித்தவரின் வயது/Age Group]]&Table1[[#This Row],[பாலினம்/Gender]],Factor!$A$45:$G$53,7,0) -> 0.79503106 | AU86: =VLOOKUP(Table1[[#This Row],[2021 சட்டமன்றத் தேர்தலில் நீங்கள் எந்தக் கட்சிக்கு வாக்களித்தீர்கள்?/ Which party did you vote in 2021 Assembly Elections? ]],Factor!$F$9:$J$14,5,0) -> 0.73680082 | AV86: =VLOOKUP(Table1[[#This Row],[Rev Caste]],Factor!$F$59:$I$68,4,0) -> 1.0593103 | AW86: =Table1[[#This Row],[2021 Ae Factor]]*Table1[[#This Row],[Age & Gender Factor]] -> 0.58577954 | AX86: =Table1[[#This Row],[2021 Ae Factor]]*Table1[[#This Row],[Caste Factor]] -> 0.78050074 | AY86: =VALUE(MID(D86, FIND(",",D86)+2, FIND(")",D86)-FIND(",",D86)-2)) -> 78.661037
A87: k8b4aQ72bKTMtVChUlsS | B87: 2025-07-31 13:06:01.478204 | C87: 45869 | D87: (10.41423, 78.6605833) | E87: CM76+J69,,Kudumiyamalai,622104,Tamil Nadu,India. | F87: https://firebasestorage.googleapis.com/v0/b/mindbrink-survey-production.appspot.com/o/audioFiles%2FAtznECuQc6klLPsRR6u2%2FfYiv0HvGk4VbFlXYwsKbSZ6fwXI2%2F2025-07-31%2013%3A05%3A57.499829.m4a?alt=media&token=ddcea48e-2693-418a-893d-507b4eb2b2ea | G87: 134 | H87: false | I87: A.Banu | J87: +919443892814 | K87: Subramanian | L87: ILLUPUR | M87: KUDUMIYANMALAI | N87: Pugothai | O87: பெண்/Female | P87: 9159121208 | Q87: 46-60 | R87: இல்லத்தரசி/ Housewife | S87: 10,000க்கும் குறைவானது/Less than 10,000 | T87: திருப்திகரமானது / Satisfactory | U87: இல்லை/ No | V87: திமுக கூட்டணி / DMK Alliance | W87: மு.க. ஸ்டாலின் (திமுக) / M.K. Stalin (DMK) | X87: திமுக / DMK | Y87: DMK | Z87: - | AA87: இல்லை / No | AB87: - | AC87: வேகம் குறைபாடுடன் செயல்படுகிறது / Needs more momentum | AD87: போதுமான ஈடுபாடு / Adequate | AE87: • ஆமாம்: அதிமுக கூட்டணி உடையும்/ Yes: AIADMK alliance will break up | AF87: தி.மு.க/DMK | AG87: மதுபானம் / போதைப்பொருள் பழக்கம்/ Alcohol/Drug abuse | AH87: BC | AI87: MUTTARAIYAR | AJ87: =IFERROR(_xlfn.XLOOKUP(Table1[[#This Row],[Audio Url]],Qc!C:C,Qc!F:F),"") -> randomly asking questions | AK87: =IFERROR(_xlfn.XLOOKUP(Table1[[#This Row],[Audio Url]],Qc!C:C,Qc!E:E),"") -> Not Asking All The Questions | AL87: - | AM87: - | AN87: =VLOOKUP(Table1[[#This Row],[LOCALITY]],Sheet2!$F:$H,3,0) -> Rural | AO87: Yes | AP87: =IF(Table1[[#This Row],[Audio Duration (in secs)]]>180,"Greater than 3 Minutes","Less than 3 Minutes") -> Less than 3 Minutes | AQ87: =IFERROR(VLOOKUP(Table1[[#This Row],[சாதி/Caste]],MApping!$E$1:$F$10,2,0),"Others") -> MUTTARAIYAR | AR87: =VLOOKUP(Table1[[#This Row],[பாலினம்/Gender]],Factor!$F$26:$I$28,4,0) -> 1.0470348 | AS87: =VLOOKUP(Table1[[#This Row],[பதிலளித்தவரின் வயது/Age Group]],Factor!$F$35:$I$39,4,0) -> 0.87972509 | AT87: =VLOOKUP(Table1[[#This Row],[பதிலளித்தவரின் வயது/Age Group]]&Table1[[#This Row],[பாலினம்/Gender]],Factor!$A$45:$G$53,7,0) -> 0.98461538 | AU87: =VLOOKUP(Table1[[#This Row],[2021 சட்டமன்றத் தேர்தலில் நீங்கள் எந்தக் கட்சிக்கு வாக்களித்தீர்கள்?/ Which party did you vote in 2021 Assembly Elections? ]],Factor!$F$9:$J$14,5,0) -> 0.73680082 | AV87: =VLOOKUP(Table1[[#This Row],[Rev Caste]],Factor!$F$59:$I$68,4,0) -> 1.2358621 | AW87: =Table1[[#This Row],[2021 Ae Factor]]*Table1[[#This Row],[Age & Gender Factor]] -> 0.72546543 | AX87: =Table1[[#This Row],[2021 Ae Factor]]*Table1[[#This Row],[Caste Factor]] -> 0.91058419 | AY87: =VALUE(MID(D87, FIND(",",D87)+2, FIND(")",D87)-FIND(",",D87)-2)) -> 78.660583
... A367: LutL3M0323I4O1K6k5ri | B367: 2025-08-06 19:06:06.924054 | C367: 45875 | D367: (10.6036541, 78.5470533) | E367: 558/4,மதுரை ரோடு,விராலிமலை,621316,தமிழ் நாடு,India. | F367: https://firebasestorage.googleapis.com/v0/b/mindbrink-survey-production.appspot.com/o/audioFiles%2FAtznECuQc6klLPsRR6u2%2FvgezSzrsuLVlWSdHweefXnEvA793%2F2025-08-06%2019%3A05%3A55.027674.m4a?alt=media&token=a10e9689-46fa-4d97-b3f3-c4f1d42433f6 | G367: 272 | H367: false | I367: pantyan | J367: +919976239565 | K367: Subramanian | L367: VIRALIMALAI | M367: VIRALIMALAI | N367: geetha | O367: பெண்/Female | P367: 9629001929 | Q367: 46-60 | R367: சொந்த தொழில் / சுயதொழில் செய்பவர்/ Self Employed/Business | S367: 10,000 - 25,000 | T367: திருப்திகரமானது / Satisfactory | U367: இல்லை/ No | V367: திமுக கூட்டணி / DMK Alliance | W367: மு.க. ஸ்டாலின் (திமுக) / M.K. Stalin (DMK) | X367: திமுக / DMK | Y367: DMK | Z367: - | AA367: ஆமாம் / Yes | AB367: திமுக கூட்டணி / DMK Alliance | AC367: திருப்திகரமானது / Satisfactory | AD367: பயனில்லை / Not effective | AE367: • இல்லை: திமுக மற்றும் அதிமுக கூட்டணிகள் இரண்டும் உடையாது/ No: Both DMK & AIADMK alliances will not break up | AF367: காங்கிரஸ் / INC | AG367: மதுபானம் / போதைப்பொருள் பழக்கம்/ Alcohol/Drug abuse | AH367: BC | AI367: andipandaram | AJ367: =IFERROR(_xlfn.XLOOKUP(Table1[[#This Row],[Audio Url]],Qc!C:C,Qc!F:F),"") -> 0 | AK367: =IFERROR(_xlfn.XLOOKUP(Table1[[#This Row],[Audio Url]],Qc!C:C,Qc!E:E),"") -> Correctly Done | AL367: - | AM367: - | AN367: =VLOOKUP(Table1[[#This Row],[LOCALITY]],Sheet2!$F:$H,3,0) -> Urban | AO367: Yes | AP367: =IF(Table1[[#This Row],[Audio Duration (in secs)]]>180,"Greater than 3 Minutes","Less than 3 Minutes") -> Greater than 3 Minutes | AQ367: =IFERROR(VLOOKUP(Table1[[#This Row],[சாதி/Caste]],MApping!$E$1:$F$10,2,0),"Others") -> Others | AR367: =VLOOKUP(Table1[[#This Row],[பாலினம்/Gender]],Factor!$F$26:$I$28,4,0) -> 1.0470348 | AS367: =VLOOKUP(Table1[[#This Row],[பதிலளித்தவரின் வயது/Age Group]],Factor!$F$35:$I$39,4,0) -> 0.87972509 | AT367: =VLOOKUP(Table1[[#This Row],[பதிலளித்தவரின் வயது/Age Group]]&Table1[[#This Row],[பாலினம்/Gender]],Factor!$A$45:$G$53,7,0) -> 0.98461538 | AU367: =VLOOKUP(Table1[[#This Row],[2021 சட்டமன்றத் தேர்தலில் நீங்கள் எந்தக் கட்சிக்கு வாக்களித்தீர்கள்?/ Which party did you vote in 2021 Assembly Elections? ]],Factor!$F$9:$J$14,5,0) -> 0.73680082 | AV367: =VLOOKUP(Table1[[#This Row],[Rev Caste]],Factor!$F$59:$I$68,4,0) -> 0.14422535 | AW367: =Table1[[#This Row],[2021 Ae Factor]]*Table1[[#This Row],[Age & Gender Factor]] -> 0.72546543 | AX367: =Table1[[#This Row],[2021 Ae Factor]]*Table1[[#This Row],[Caste Factor]] -> 0.10626536 | AY367: =VALUE(MID(D367, FIND(",",D367)+2, FIND(")",D367)-FIND(",",D367)-2)) -> 78.547053
A368: VTPmGWUPyYic8rNJgUEf | B368: 2025-08-07 09:56:55.244825 | C368: 45876 | D368: (10.6039056, 78.5525596) | E368: JH33+H39,,Viralimalai,621316,Tamil Nadu,India. | F368: https://firebasestorage.googleapis.com/v0/b/mindbrink-survey-production.appspot.com/o/audioFiles%2FAtznECuQc6klLPsRR6u2%2FnV4IA56gMWWp4NfG0H1PGfyqfM92%2F2025-08-07%2009%3A56%3A44.005917.m4a?alt=media&token=62967e84-57d0-47bf-8f2c-63e57457e6f0 | G368: 323 | H368: false | I368: G.muthukumar | J368: +918940041476 | K368: Subramanian | L368: VIRALIMALAI | M368: VIRALIMALAI | N368: K.Raju | O368: ஆண்/Male | P368: 7010464812 | Q368: 46-60 | R368: விவசாயி/ Farmer | S368: 10,000 - 25,000 | T368: திருப்திகரமல்ல/ Unsatisfactory | U368: ஆம் / Yes | V368: திமுக கூட்டணி / DMK Alliance | W368: எடப்பாடி பழனிசாமி (அதிமுக) / Edappadi K. Palaniswami (AIADMK) | X368: அதிமுக / AIADMK | Y368: AIADMK | Z368: உறுதி இல்லை / வேட்பாளரைப் பொறுத்தது/ Not sure / Depends on candidate | AA368: இல்லை / No | AB368: - | AC368: திருப்திகரமல்ல / Unsatisfactory | AD368: பயனில்லை / Not effective | AE368: • இல்லை: திமுக மற்றும் அதிமுக கூட்டணிகள் இரண்டும் உடையாது/ No: Both DMK & AIADMK alliances will not break up | AF368: அதிமுக + பா.ஜ.க/ AIADMK + BJP | AG368: மதுபானம் / போதைப்பொருள் பழக்கம்/ Alcohol/Drug abuse | AH368: BC | AI368: URALI GOUNDER | AJ368: =IFERROR(_xlfn.XLOOKUP(Table1[[#This Row],[Audio Url]],Qc!C:C,Qc!F:F),"") -> 0 | AK368: - | AL368: - | AM368: - | AN368: =VLOOKUP(Table1[[#This Row],[LOCALITY]],Sheet2!$F:$H,3,0) -> Urban | AO368: Yes | AP368: =IF(Table1[[#This Row],[Audio Duration (in secs)]]>180,"Greater than 3 Minutes","Less than 3 Minutes") -> Greater than 3 Minutes | AQ368: =IFERROR(VLOOKUP(Table1[[#This Row],[சாதி/Caste]],MApping!$E$1:$F$10,2,0),"Others") -> URALI GOUNDER | AR368: =VLOOKUP(Table1[[#This Row],[பாலினம்/Gender]],Factor!$F$26:$I$28,4,0) -> 0.95700935 | AS368: =VLOOKUP(Table1[[#This Row],[பதிலளித்தவரின் வயது/Age Group]],Factor!$F$35:$I$39,4,0) -> 0.87972509 | AT368: =VLOOKUP(Table1[[#This Row],[பதிலளித்தவரின் வயது/Age Group]]&Table1[[#This Row],[பாலினம்/Gender]],Factor!$A$45:$G$53,7,0) -> 0.79503106 | AU368: =VLOOKUP(Table1[[#This Row],[2021 சட்டமன்றத் தேர்தலில் நீங்கள் எந்தக் கட்சிக்கு வாக்களித்தீர்கள்?/ Which party did you vote in 2021 Assembly Elections? ]],Factor!$F$9:$J$14,5,0) -> 0.73680082 | AV368: =VLOOKUP(Table1[[#This Row],[Rev Caste]],Factor!$F$59:$I$68,4,0) -> 1.0593103 | AW368: =Table1[[#This Row],[2021 Ae Factor]]*Table1[[#This Row],[Age & Gender Factor]] -> 0.58577954 | AX368: =Table1[[#This Row],[2021 Ae Factor]]*Table1[[#This Row],[Caste Factor]] -> 0.78050074 | AY368: =VALUE(MID(D368, FIND(",",D368)+2, FIND(")",D368)-FIND(",",D368)-2)) -> 78.55256
A369: BbuxoHCzUYQ8ym27Z0EG | B369: 2025-08-07 10:03:30.984023 | C369: 45876 | D369: (10.6039062, 78.5525612) | E369: JH33+H39,,Viralimalai,621316,Tamil Nadu,India. | F369: https://firebasestorage.googleapis.com/v0/b/mindbrink-survey-production.appspot.com/o/audioFiles%2FAtznECuQc6klLPsRR6u2%2FnV4IA56gMWWp4NfG0H1PGfyqfM92%2F2025-08-07%2010%3A02%3A53.990901.m4a?alt=media&token=46aab7d5-69eb-4592-899b-677c08c30923 | G369: 272 | H369: false | I369: G.muthukumar | J369: +918940041476 | K369: Subramanian | L369: VIRALIMALAI | M369: VIRALIMALAI | N369: Harisuthan | O369: ஆண்/Male | P369: 8870631556 | Q369: 18-30 | R369: சொந்த தொழில் / சுயதொழில் செய்பவர்/ Self Employed/Business | S369: 10,000 - 25,000 | T369: மேம்பாடு தேவை / Needs improvement | U369: உறுதியாக தெரியவில்லை / Not Sure | V369: அதிமுக கூட்டணி / AIADMK Alliance | W369: எடப்பாடி பழனிசாமி (அதிமுக) / Edappadi K. Palaniswami (AIADMK) | X369: அதிமுக / AIADMK | Y369: AIADMK | Z369: உறுதி இல்லை / வேட்பாளரைப் பொறுத்தது/ Not sure / Depends on candidate | AA369: ஆமாம் / Yes | AB369: திமுக கூட்டணி / DMK Alliance | AC369: வேகம் குறைபாடுடன் செயல்படுகிறது / Needs more momentum | AD369: குறைவான ஈடுபாடு / Inadequate | AE369: • ஆமாம்: திமுக மற்றும் அதிமுக கூட்டணிகள் இரண்டும் உடையும்/ Yes: Both DMK & AIADMK alliances will break up | AF369: அதிமுக + பா.ஜ.க/ AIADMK + BJP | AG369: மதுபானம் / போதைப்பொருள் பழக்கம்/ Alcohol/Drug abuse | AH369: SC | AI369: DEVENDRA KULA VELLALAR | AJ369: =IFERROR(_xlfn.XLOOKUP(Table1[[#This Row],[Audio Url]],Qc!C:C,Qc!F:F),"") -> 0 | AK369: - | AL369: - | AM369: - | AN369: =VLOOKUP(Table1[[#This Row],[LOCALITY]],Sheet2!$F:$H,3,0) -> Urban | AO369: Yes | AP369: =IF(Table1[[#This Row],[Audio Duration (in secs)]]>180,"Greater than 3 Minutes","Less than 3 Minutes") -> Greater than 3 Minutes | AQ369: =IFERROR(VLOOKUP(Table1[[#This Row],[சாதி/Caste]],MApping!$E$1:$F$10,2,0),"Others") -> DEVENDRA KULA VELLALAR | AR369: =VLOOKUP(Table1[[#This Row],[பாலினம்/Gender]],Factor!$F$26:$I$28,4,0) -> 0.95700935 | AS369: =VLOOKUP(Table1[[#This Row],[பதிலளித்தவரின் வயது/Age Group]],Factor!$F$35:$I$39,4,0) -> 0.9752381 | AT369: =VLOOKUP(Table1[[#This Row],[பதிலளித்தவரின் வயது/Age Group]]&Table1[[#This Row],[பாலினம்/Gender]],Factor!$A$45:$G$53,7,0) -> 1.0666667 | AU369: =VLOOKUP(Table1[[#This Row],[2021 சட்டமன்றத் தேர்தலில் நீங்கள் எந்தக் கட்சிக்கு வாக்களித்தீர்கள்?/ Which party did you vote in 2021 Assembly Elections? ]],Factor!$F$9:$J$14,5,0) -> 1.3119425 | AV369: =VLOOKUP(Table1[[#This Row],[Rev Caste]],Factor!$F$59:$I$68,4,0) -> 0.99902439 | AW369: =Table1[[#This Row],[2021 Ae Factor]]*Table1[[#This Row],[Age & Gender Factor]] -> 1.3994054 | AX369: =Table1[[#This Row],[2021 Ae Factor]]*Table1[[#This Row],[Caste Factor]] -> 1.3106626 | AY369: =VALUE(MID(D369, FIND(",",D369)+2, FIND(")",D369)-FIND(",",D369)-2)) -> 78.552561
A370: OyxU0xHKuzgFZ6KMLZn8 | B370: 2025-08-07 10:03:59.345229 | C370: 45876 | D370: (10.5965574, 78.5427732) | E370: HGWV+H4H,,Viralimalai,621316,Tamil Nadu,India. | F370: https://firebasestorage.googleapis.com/v0/b/mindbrink-survey-production.appspot.com/o/audioFiles%2FAtznECuQc6klLPsRR6u2%2FvgezSzrsuLVlWSdHweefXnEvA793%2F2025-08-07%2010%3A03%3A50.965972.m4a?alt=media&token=2663a2b1-b8d9-4474-9008-c7df6ec51c27 | G370: 587 | H370: false | I370: pantyan | J370: +919976239565 | K370: Subramanian | L370: VIRALIMALAI | M370: VIRALIMALAI | N370: s.kathiresan | O370: ஆண்/Male | P370: 9894812901 | Q370: 60+ | R370: கூலி தொழில்/ Daily Wage | S370: 25,000 - 50,000 | T370: திருப்திகரமானது / Satisfactory | U370: ஆம் / Yes | V370: நினைவில் இல்லை / Don’t Remember | W370: மு.க. ஸ்டாலின் (திமுக) / M.K. Stalin (DMK) | X370: தே.மு.தி.க / DMDK | Y370: DMDK | Z370: உறுதி இல்லை / வேட்பாளரைப் பொறுத்தது/ Not sure / Depends on candidate | AA370: ஆமாம் / Yes | AB370: அதிமுக கூட்டணி / AIADMK Alliance | AC370: வேகம் குறைபாடுடன் செயல்படுகிறது / Needs more momentum | AD370: போதுமான ஈடுபாடு / Adequate | AE370: • இல்லை: திமுக மற்றும் அதிமுக கூட்டணிகள் இரண்டும் உடையாது/ No: Both DMK & AIADMK alliances will not break up | AF370: தனித்துப் போட்டியிட வேண்டும் / Contest Independently | AG370: மதுபானம் / போதைப்பொருள் பழக்கம்/ Alcohol/Drug abuse | AH370: BC | AI370: CHOLIA VELLALAR | AJ370: =IFERROR(_xlfn.XLOOKUP(Table1[[#This Row],[Audio Url]],Qc!C:C,Qc!F:F),"") -> he said based on the candidates | AK370: - | AL370: - | AM370: - | AN370: =VLOOKUP(Table1[[#This Row],[LOCALITY]],Sheet2!$F:$H,3,0) -> Urban | AO370: Yes | AP370: =IF(Table1[[#This Row],[Audio Duration (in secs)]]>180,"Greater than 3 Minutes","Less than 3 Minutes") -> Greater than 3 Minutes | AQ370: =IFERROR(VLOOKUP(Table1[[#This Row],[சாதி/Caste]],MApping!$E$1:$F$10,2,0),"Others") -> CHOLIA VELLALAR | AR370: =VLOOKUP(Table1[[#This Row],[பாலினம்/Gender]],Factor!$F$26:$I$28,4,0) -> 0.95700935 | AS370: =VLOOKUP(Table1[[#This Row],[பதிலளித்தவரின் வயது/Age Group]],Factor!$F$35:$I$39,4,0) -> 1.0308725 | AT370: =VLOOKUP(Table1[[#This Row],[பதிலளித்தவரின் வயது/Age Group]]&Table1[[#This Row],[பாலினம்/Gender]],Factor!$A$45:$G$53,7,0) -> 0.86292135 | AU370: =VLOOKUP(Table1[[#This Row],[2021 சட்டமன்றத் தேர்தலில் நீங்கள் எந்தக் கட்சிக்கு வாக்களித்தீர்கள்?/ Which party did you vote in 2021 Assembly Elections? ]],Factor!$F$9:$J$14,5,0) -> 1 | AV370: =VLOOKUP(Table1[[#This Row],[Rev Caste]],Factor!$F$59:$I$68,4,0) -> 1.0666667 | AW370: =Table1[[#This Row],[2021 Ae Factor]]*Table1[[#This Row],[Age & Gender Factor]] -> 0.86292135 | AX370: =Table1[[#This Row],[2021 Ae Factor]]*Table1[[#This Row],[Caste Factor]] -> 1.0666667 | AY370: =VALUE(MID(D370, FIND(",",D370)+2, FIND(")",D370)-FIND(",",D370)-2)) -> 78.542773
A371: yujmuyhf9vgx177iZiZo | B371: 2025-08-07 10:10:56.530890 | C371: 45876 | D371: (10.6041421, 78.5527393) | E371: JH33+H39,,Viralimalai,621316,Tamil Nadu,India. | F371: https://firebasestorage.googleapis.com/v0/b/mindbrink-survey-production.appspot.com/o/audioFiles%2FAtznECuQc6klLPsRR6u2%2FnV4IA56gMWWp4NfG0H1PGfyqfM92%2F2025-08-07%2010%3A10%3A39.273174.m4a?alt=media&token=65edfac4-cede-43a6-a164-becbc8430c58 | G371: 257 | H371: false | I371: G.muthukumar | J371: +918940041476 | K371: Subramanian | L371: VIRALIMALAI | M371: VIRALIMALAI | N371: Surya | O371: ஆண்/Male | P371: 7010958198 | Q371: 18-30 | R371: சொந்த தொழில் / சுயதொழில் செய்பவர்/ Self Employed/Business | S371: 10,000 - 25,000 | T371: மேம்பாடு தேவை / Needs improvement | U371: ஆம் / Yes | V371: பிற கட்சிகள் / Others | W371: Others | X371: அதிமுக / AIADMK | Y371: Others | Z371: ஆம், TVK கூட்டணிக்கு வாக்களிப்பேன் / Yes, I will shift my vote to the TVK alliance | AA371: ஆமாம் / Yes | AB371: திமுக கூட்டணி / DMK Alliance | AC371: வேகம் குறைபாடுடன் செயல்படுகிறது / Needs more momentum | AD371: போதுமான ஈடுபாடு / Adequate | AE371: • ஆமாம்: அதிமுக கூட்டணி உடையும்/ Yes: AIADMK alliance will break up | AF371: தே.மு.தி.க / DMDK | AG371: மதுபானம் / போதைப்பொருள் பழக்கம்/ Alcohol/Drug abuse | AH371: BC | AI371: CHOLIA VELLALAR | AJ371: =IFERROR(_xlfn.XLOOKUP(Table1[[#This Row],[Audio Url]],Qc!C:C,Qc!F:F),"") -> 0 | AK371: - | AL371: - | AM371: - | AN371: =VLOOKUP(Table1[[#This Row],[LOCALITY]],Sheet2!$F:$H,3,0) -> Urban | AO371: Yes | AP371: =IF(Table1[[#This Row],[Audio Duration (in secs)]]>180,"Greater than 3 Minutes","Less than 3 Minutes") -> Greater than 3 Minutes | AQ371: =IFERROR(VLOOKUP(Table1[[#This Row],[சாதி/Caste]],MApping!$E$1:$F$10,2,0),"Others") -> CHOLIA VELLALAR | AR371: =VLOOKUP(Table1[[#This Row],[பாலினம்/Gender]],Factor!$F$26:$I$28,4,0) -> 0.95700935 | AS371: =VLOOKUP(Table1[[#This Row],[பதிலளித்தவரின் வயது/Age Group]],Factor!$F$35:$I$39,4,0) -> 0.9752381 | AT371: =VLOOKUP(Table1[[#This Row],[பதிலளித்தவரின் வயது/Age Group]]&Table1[[#This Row],[பாலினம்/Gender]],Factor!$A$45:$G$53,7,0) -> 1.0666667 | AU371: =VLOOKUP(Table1[[#This Row],[2021 சட்டமன்றத் தேர்தலில் நீங்கள் எந்தக் கட்சிக்கு வாக்களித்தீர்கள்?/ Which party did you vote in 2021 Assembly Elections? ]],Factor!$F$9:$J$14,5,0) -> 1.4247885 | AV371: =VLOOKUP(Table1[[#This Row],[Rev Caste]],Factor!$F$59:$I$68,4,0) -> 1.0666667 | AW371: =Table1[[#This Row],[2021 Ae Factor]]*Table1[[#This Row],[Age & Gender Factor]] -> 1.5197744 | AX371: =Table1[[#This Row],[2021 Ae Factor]]*Table1[[#This Row],[Caste Factor]] -> 1.5197744 | AY371: =VALUE(MID(D371, FIND(",",D371)+2, FIND(")",D371)-FIND(",",D371)-2)) -> 78.552739
A372: Nel5Ua5uJg4aQYY17PaZ | B372: 2025-08-07 10:30:53.611112 | C372: 45876 | D372: (10.6099344, 78.5537054) | E372: JH63+55H,,Viralimalai,621316,Tamil Nadu,India. | F372: https://firebasestorage.googleapis.com/v0/b/mindbrink-survey-production.appspot.com/o/audioFiles%2FAtznECuQc6klLPsRR6u2%2FnV4IA56gMWWp4NfG0H1PGfyqfM92%2F2025-08-07%2010%3A30%3A44.697955.m4a?alt=media&token=f70ccb56-04b3-444b-a30a-f2c52ff92fb5 | G372: 307 | H372: false | I372: G.muthukumar | J372: +918940041476 | K372: Subramanian | L372: VIRALIMALAI | M372: VIRALIMALAI | N372: Ramachandran | O372: ஆண்/Male | P372: 9361441386 | Q372: 18-30 | R372: கூலி தொழில்/ Daily Wage | S372: 10,000 - 25,000 | T372: மேம்பாடு தேவை / Needs improvement | U372: இல்லை/ No | V372: பிற கட்சிகள் / Others | W372: விஜய் (தமிழக வெற்றி கழகம்) / Vijay (TVK) | X372: தமிழக வெற்றி கழகம் / TVK | Y372: DMK | Z372: - | AA372: இல்லை / No | AB372: - | AC372: திருப்திகரமல்ல / Unsatisfactory | AD372: பயனில்லை / Not effective | AE372: • ஆமாம்: திமுக மற்றும் அதிமுக கூட்டணிகள் இரண்டும் உடையும்/ Yes: Both DMK & AIADMK alliances will break up | AF372: தனித்துப் போட்டியிட வேண்டும் / Contest Independently | AG372: வேலைவாய்ப்பு குறைபாடு / Unemployment | AH372: OBC | AI372: MUTTARAIYAR | AJ372: =IFERROR(_xlfn.XLOOKUP(Table1[[#This Row],[Audio Url]],Qc!C:C,Qc!F:F),"") -> he said "i just want to vote nota" | AK372: - | AL372: - | AM372: - | AN372: =VLOOKUP(Table1[[#This Row],[LOCALITY]],Sheet2!$F:$H,3,0) -> Urban | AO372: Yes | AP372: =IF(Table1[[#This Row],[Audio Duration (in secs)]]>180,"Greater than 3 Minutes","Less than 3 Minutes") -> Greater than 3 Minutes | AQ372: =IFERROR(VLOOKUP(Table1[[#This Row],[சாதி/Caste]],MApping!$E$1:$F$10,2,0),"Others") -> MUTTARAIYAR | AR372: =VLOOKUP(Table1[[#This Row],[பாலினம்/Gender]],Factor!$F$26:$I$28,4,0) -> 0.95700935 | AS372: =VLOOKUP(Table1[[#This Row],[பதிலளித்தவரின் வயது/Age Group]],Factor!$F$35:$I$39,4,0) -> 0.9752381 | AT372: =VLOOKUP(Table1[[#This Row],[பதிலளித்தவரின் வயது/Age Group]]&Table1[[#This Row],[பாலினம்/Gender]],Factor!$A$45:$G$53,7,0) -> 1.0666667 | AU372: =VLOOKUP(Table1[[#This Row],[2021 சட்டமன்றத் தேர்தலில் நீங்கள் எந்தக் கட்சிக்கு வாக்களித்தீர்கள்?/ Which party did you vote in 2021 Assembly Elections? ]],Factor!$F$9:$J$14,5,0) -> 1.4247885 | AV372: =VLOOKUP(Table1[[#This Row],[Rev Caste]],Factor!$F$59:$I$68,4,0) -> 1.2358621 | AW372: =Table1[[#This Row],[2021 Ae Factor]]*Table1[[#This Row],[Age & Gender Factor]] -> 1.5197744 | AX372: =Table1[[#This Row],[2021 Ae Factor]]*Table1[[#This Row],[Caste Factor]] -> 1.7608421 | AY372: =VALUE(MID(D372, FIND(",",D372)+2, FIND(")",D372)-FIND(",",D372)-2)) -> 78.553705
A373: EPqxMsZPMXbpQBHnn5zu | B373: 2025-08-07 10:49:04.969867 | C373: 45876 | D373: (10.6137703, 78.5547391) | E373: JH73+GVR,,Viralimalai,621316,Tamil Nadu,India. | F373: https://firebasestorage.googleapis.com/v0/b/mindbrink-survey-production.appspot.com/o/audioFiles%2FAtznECuQc6klLPsRR6u2%2FnV4IA56gMWWp4NfG0H1PGfyqfM92%2F2025-08-07%2010%3A48%3A44.309222.m4a?alt=media&token=75976cf8-7219-42b8-88e9-9687fce894c6 | G373: 444 | H373: false | I373: G.muthukumar | J373: +918940041476 | K373: Subramanian | L373: VIRALIMALAI | M373: VIRALIMALAI | N373: Manikandan | O373: ஆண்/Male | P373: 9865865810 | Q373: 18-30 | R373: சொந்த தொழில் / சுயதொழில் செய்பவர்/ Self Employed/Business | S373: 10,000க்கும் குறைவானது/Less than 10,000 | T373: மேம்பாடு தேவை / Needs improvement | U373: உறுதியாக தெரியவில்லை / Not Sure | V373: நினைவில் இல்லை / Don’t Remember | W373: எடப்பாடி பழனிசாமி (அதிமுக) / Edappadi K. Palaniswami (AIADMK) | X373: அதிமுக / AIADMK | Y373: AIADMK | Z373: உறுதி இல்லை / வேட்பாளரைப் பொறுத்தது/ Not sure / Depends on candidate | AA373: இல்லை / No | AB373: - | AC373: திருப்திகரமானது / Satisfactory | AD373: போதுமான ஈடுபாடு / Adequate | AE373: • இல்லை: திமுக மற்றும் அதிமுக கூட்டணிகள் இரண்டும் உடையாது/ No: Both DMK & AIADMK alliances will not break up | AF373: அதிமுக / AIADMK | AG373: வேலைவாய்ப்பு குறைபாடு / Unemployment | AH373: OBC | AI373: Hindu Vannar | AJ373: =IFERROR(_xlfn.XLOOKUP(Table1[[#This Row],[Audio Url]],Qc!C:C,Qc!F:F),"") -> 0 | AK373: - | AL373: - | AM373: - | AN373: =VLOOKUP(Table1[[#This Row],[LOCALITY]],Sheet2!$F:$H,3,0) -> Urban | AO373: Yes | AP373: =IF(Table1[[#This Row],[Audio Duration (in secs)]]>180,"Greater than 3 Minutes","Less than 3 Minutes") -> Greater than 3 Minutes | AQ373: =IFERROR(VLOOKUP(Table1[[#This Row],[சாதி/Caste]],MApping!$E$1:$F$10,2,0),"Others") -> Others | AR373: =VLOOKUP(Table1[[#This Row],[பாலினம்/Gender]],Factor!$F$26:$I$28,4,0) -> 0.95700935 | AS373: =VLOOKUP(Table1[[#This Row],[பதிலளித்தவரின் வயது/Age Group]],Factor!$F$35:$I$39,4,0) -> 0.9752381 | AT373: =VLOOKUP(Table1[[#This Row],[பதிலளித்தவரின் வயது/Age Group]]&Table1[[#This Row],[பாலினம்/Gender]],Factor!$A$45:$G$53,7,0) -> 1.0666667 | AU373: =VLOOKUP(Table1[[#This Row],[2021 சட்டமன்றத் தேர்தலில் நீங்கள் எந்தக் கட்சிக்கு வாக்களித்தீர்கள்?/ Which party did you vote in 2021 Assembly Elections? ]],Factor!$F$9:$J$14,5,0) -> 1 | AV373: =VLOOKUP(Table1[[#This Row],[Rev Caste]],Factor!$F$59:$I$68,4,0) -> 0.14422535 | AW373: =Table1[[#This Row],[2021 Ae Factor]]*Table1[[#This Row],[Age & Gender Factor]] -> 1.0666667 | AX373: =Table1[[#This Row],[2021 Ae Factor]]*Table1[[#This Row],[Caste Factor]] -> 0.14422535 | AY373: =VALUE(MID(D373, FIND(",",D373)+2, FIND(")",D373)-FIND(",",D373)-2)) -> 78.554739
A374: aYUtZrYYq6GuEy4qYoek | B374: 2025-08-07 11:01:39.412743 | C374: 45876 | D374: (10.6152258, 78.5541801) | E374: 1,,Viralimalai,621316,Tamil Nadu,India. | F374: https://firebasestorage.googleapis.com/v0/b/mindbrink-survey-production.appspot.com/o/audioFiles%2FAtznECuQc6klLPsRR6u2%2FnV4IA56gMWWp4NfG0H1PGfyqfM92%2F2025-08-07%2011%3A01%3A23.928028.m4a?alt=media&token=93622c61-14c6-4e7a-b4e9-01dd5ac66a78 | G374: 363 | H374: false | I374: G.muthukumar | J374: +918940041476 | K374: Subramanian | L374: VIRALIMALAI | M374: VIRALIMALAI | N374: Murugan | O374: ஆண்/Male | P374: 9952707146 | Q374: 46-60 | R374: சொந்த தொழில் / சுயதொழில் செய்பவர்/ Self Employed/Business | S374: 10,000க்கும் குறைவானது/Less than 10,000 | T374: திருப்திகரமல்ல/ Unsatisfactory | U374: ஆம் / Yes | V374: அதிமுக கூட்டணி / AIADMK Alliance | W374: எடப்பாடி பழனிசாமி (அதிமுக) / Edappadi K. Palaniswami (AIADMK) | X374: அதிமுக / AIADMK | Y374: AIADMK | Z374: உறுதி இல்லை / வேட்பாளரைப் பொறுத்தது/ Not sure / Depends on candidate | AA374: இல்லை / No | AB374: - | AC374: திருப்திகரமானது / Satisfactory | AD374: குறைவான ஈடுபாடு / Inadequate | AE374: • ஆமாம்: திமுக மற்றும் அதிமுக கூட்டணிகள் இரண்டும் உடையும்/ Yes: Both DMK & AIADMK alliances will break up | AF374: அதிமுக / AIADMK | AG374: விவசாய நெருக்கடி / Agricultural crisis | AH374: SC | AI374: DEVENDRA KULA VELLALAR | AJ374: =IFERROR(_xlfn.XLOOKUP(Table1[[#This Row],[Audio Url]],Qc!C:C,Qc!F:F),"") -> SUDDENLY PHONE RANG AND THE AUDIO MUTED | AK374: - | AL374: - | AM374: - | AN374: =VLOOKUP(Table1[[#This Row],[LOCALITY]],Sheet2!$F:$H,3,0) -> Urban | AO374: Yes | AP374: =IF(Table1[[#This Row],[Audio Duration (in secs)]]>180,"Greater than 3 Minutes","Less than 3 Minutes") -> Greater than 3 Minutes | AQ374: =IFERROR(VLOOKUP(Table1[[#This Row],[சாதி/Caste]],MApping!$E$1:$F$10,2,0),"Others") -> DEVENDRA KULA VELLALAR | AR374: =VLOOKUP(Table1[[#This Row],[பாலினம்/Gender]],Factor!$F$26:$I$28,4,0) -> 0.95700935 | AS374: =VLOOKUP(Table1[[#This Row],[பதிலளித்தவரின் வயது/Age Group]],Factor!$F$35:$I$39,4,0) -> 0.87972509 | AT374: =VLOOKUP(Table1[[#This Row],[பதிலளித்தவரின் வயது/Age Group]]&Table1[[#This Row],[பாலினம்/Gender]],Factor!$A$45:$G$53,7,0) -> 0.79503106 | AU374: =VLOOKUP(Table1[[#This Row],[2021 சட்டமன்றத் தேர்தலில் நீங்கள் எந்தக் கட்சிக்கு வாக்களித்தீர்கள்?/ Which party did you vote in 2021 Assembly Elections? ]],Factor!$F$9:$J$14,5,0) -> 1.3119425 | AV374: =VLOOKUP(Table1[[#This Row],[Rev Caste]],Factor!$F$59:$I$68,4,0) -> 0.99902439 | AW374: =Table1[[#This Row],[2021 Ae Factor]]*Table1[[#This Row],[Age & Gender Factor]] -> 1.0430351 | AX374: =Table1[[#This Row],[2021 Ae Factor]]*Table1[[#This Row],[Caste Factor]] -> 1.3106626 | AY374: =VALUE(MID(D374, FIND(",",D374)+2, FIND(")",D374)-FIND(",",D374)-2)) -> 78.55418
A375: BTjZRQp90IFzXdq58jMC | B375: 2025-08-07 11:12:34.940965 | C375: 45876 | D375: (10.6153486, 78.5543439) | E375: 1,,Viralimalai,621316,Tamil Nadu,India. | F375: https://firebasestorage.googleapis.com/v0/b/mindbrink-survey-production.appspot.com/o/audioFiles%2FAtznECuQc6klLPsRR6u2%2FnV4IA56gMWWp4NfG0H1PGfyqfM92%2F2025-08-07%2011%3A11%3A59.471491.m4a?alt=media&token=11279e2f-4067-451b-b078-bcf7ab85e0a4 | G375: 448 | H375: false | I375: G.muthukumar | J375: +918940041476 | K375: Subramanian | L375: VIRALIMALAI | M375: VIRALIMALAI | N375: Subramanian | O375: ஆண்/Male | P375: 9787328819 | Q375: 60+ | R375: சொந்த தொழில் / சுயதொழில் செய்பவர்/ Self Employed/Business | S375: 10,000க்கும் குறைவானது/Less than 10,000 | T375: திருப்திகரமல்ல/ Unsatisfactory | U375: ஆம் / Yes | V375: அதிமுக கூட்டணி / AIADMK Alliance | W375: எடப்பாடி பழனிசாமி (அதிமுக) / Edappadi K. Palaniswami (AIADMK) | X375: அதிமுக / AIADMK | Y375: AIADMK | Z375: உறுதி இல்லை / வேட்பாளரைப் பொறுத்தது/ Not sure / Depends on candidate | AA375: இல்லை / No | AB375: - | AC375: திருப்திகரமானது / Satisfactory | AD375: பயனில்லை / Not effective | AE375: • ஆமாம்: திமுக மற்றும் அதிமுக கூட்டணிகள் இரண்டும் உடையும்/ Yes: Both DMK & AIADMK alliances will break up | AF375: தனித்துப் போட்டியிட வேண்டும் / Contest Independently | AG375: சட்டம் மற்றும் ஒழுங்கு/ Law and order | AH375: BC | AI375: URALI GOUNDER | AJ375: =IFERROR(_xlfn.XLOOKUP(Table1[[#This Row],[Audio Url]],Qc!C:C,Qc!F:F),"") -> HE STARTS SPEAKING WITH THEM | AK375: - | AL375: - | AM375: - | AN375: =VLOOKUP(Table1[[#This Row],[LOCALITY]],Sheet2!$F:$H,3,0) -> Urban | AO375: Yes | AP375: =IF(Table1[[#This Row],[Audio Duration (in secs)]]>180,"Greater than 3 Minutes","Less than 3 Minutes") -> Greater than 3 Minutes | AQ375: =IFERROR(VLOOKUP(Table1[[#This Row],[சாதி/Caste]],MApping!$E$1:$F$10,2,0),"Others") -> URALI GOUNDER | AR375: =VLOOKUP(Table1[[#This Row],[பாலினம்/Gender]],Factor!$F$26:$I$28,4,0) -> 0.95700935 | AS375: =VLOOKUP(Table1[[#This Row],[பதிலளித்தவரின் வயது/Age Group]],Factor!$F$35:$I$39,4,0) -> 1.0308725 | AT375: =VLOOKUP(Table1[[#This Row],[பதிலளித்தவரின் வயது/Age Group]]&Table1[[#This Row],[பாலினம்/Gender]],Factor!$A$45:$G$53,7,0) -> 0.86292135 | AU375: =VLOOKUP(Table1[[#This Row],[2021 சட்டமன்றத் தேர்தலில் நீங்கள் எந்தக் கட்சிக்கு வாக்களித்தீர்கள்?/ Which party did you vote in 2021 Assembly Elections? ]],Factor!$F$9:$J$14,5,0) -> 1.3119425 | AV375: =VLOOKUP(Table1[[#This Row],[Rev Caste]],Factor!$F$59:$I$68,4,0) -> 1.0593103 | AW375: =Table1[[#This Row],[2021 Ae Factor]]*Table1[[#This Row],[Age & Gender Factor]] -> 1.1321032 | AX375: =Table1[[#This Row],[2021 Ae Factor]]*Table1[[#This Row],[Caste Factor]] -> 1.3897543 | AY375: =VALUE(MID(D375, FIND(",",D375)+2, FIND(")",D375)-FIND(",",D375)-2)) -> 78.554344
A376: lJ3XYkqNzwTBuFOiDZAk | B376: 2025-08-07 11:14:19.155558 | C376: 45876 | D376: (10.601052, 78.5453223) | E376: JG2W+F44,,Viralimalai,621316,Tamil Nadu,India. | F376: https://firebasestorage.googleapis.com/v0/b/mindbrink-survey-production.appspot.com/o/audioFiles%2FAtznECuQc6klLPsRR6u2%2Fi7rHaGVsQtUuH9WIbNPBcYow6HH3%2F2025-08-07%2011%3A14%3A12.803971.m4a?alt=media&token=74538d95-16e7-4baa-8f6d-d91b44683aa4 | G376: 411 | H376: false | I376: Immaculatebanumathi | J376: +917395821468 | K376: Subramanian | L376: VIRALIMALAI | M376: VIRALIMALAI | N376: Ammala | O376: பெண்/Female | P376: 7639814378 | Q376: 31-45 | R376: இல்லத்தரசி/ Housewife | S376: 10,000 - 25,000 | T376: மேம்பாடு தேவை / Needs improvement | U376: ஆம் / Yes | V376: அதிமுக கூட்டணி / AIADMK Alliance | W376: எடப்பாடி பழனிசாமி (அதிமுக) / Edappadi K. Palaniswami (AIADMK) | X376: அதிமுக / AIADMK | Y376: AIADMK | Z376: இல்லை, நான் அந்த கூட்டணிக்கு வாக்களிக்க மாட்டேன். / No, I will not vote for the alliance | AA376: ஆமாம் / Yes | AB376: பிறவை / Others | AC376: திருப்திகரமானது / Satisfactory | AD376: போதுமான ஈடுபாடு / Adequate | AE376: • ஆமாம்: திமுக மற்றும் அதிமுக கூட்டணிகள் இரண்டும் உடையும்/ Yes: Both DMK & AIADMK alliances will break up | AF376: அதிமுக / AIADMK | AG376: மதுபானம் / போதைப்பொருள் பழக்கம்/ Alcohol/Drug abuse | AH376: BC | AI376: MUTTARAIYAR | AJ376: =IFERROR(_xlfn.XLOOKUP(Table1[[#This Row],[Audio Url]],Qc!C:C,Qc!F:F),"") -> 0 | AK376: - | AL376: - | AM376: - | AN376: =VLOOKUP(Table1[[#This Row],[LOCALITY]],Sheet2!$F:$H,3,0) -> Urban | AO376: Yes | AP376: =IF(Table1[[#This Row],[Audio Duration (in secs)]]>180,"Greater than 3 Minutes","Less than 3 Minutes") -> Greater than 3 Minutes | AQ376: =IFERROR(VLOOKUP(Table1[[#This Row],[சாதி/Caste]],MApping!$E$1:$F$10,2,0),"Others") -> MUTTARAIYAR | AR376: =VLOOKUP(Table1[[#This Row],[பாலினம்/Gender]],Factor!$F$26:$I$28,4,0) -> 1.0470348 | AS376: =VLOOKUP(Table1[[#This Row],[பதிலளித்தவரின் வயது/Age Group]],Factor!$F$35:$I$39,4,0) -> 1.0951872 | AT376: =VLOOKUP(Table1[[#This Row],[பதிலளித்தவரின் வயது/Age Group]]&Table1[[#This Row],[பாலினம்/Gender]],Factor!$A$45:$G$53,7,0) -> 1.107027 | AU376: =VLOOKUP(Table1[[#This Row],[2021 சட்டமன்றத் தேர்தலில் நீங்கள் எந்தக் கட்சிக்கு வாக்களித்தீர்கள்?/ Which party did you vote in 2021 Assembly Elections? ]],Factor!$F$9:$J$14,5,0) -> 1.3119425 | AV376: =VLOOKUP(Table1[[#This Row],[Rev Caste]],Factor!$F$59:$I$68,4,0) -> 1.2358621 | AW376: =Table1[[#This Row],[2021 Ae Factor]]*Table1[[#This Row],[Age & Gender Factor]] -> 1.4523558 | AX376: =Table1[[#This Row],[2021 Ae Factor]]*Table1[[#This Row],[Caste Factor]] -> 1.62138 | AY376: =VALUE(MID(D376, FIND(",",D376)+2, FIND(")",D376)-FIND(",",D376)-2)) -> 78.545322
A377: I5u7AG6rmHkaUDhf4yLP | B377: 2025-08-07 11:15:12.626664 | C377: 45876 | D377: (10.6017311, 78.5449674) | E377: West,,Viralimalai,621316,Tamil Nadu,India. | F377: https://firebasestorage.googleapis.com/v0/b/mindbrink-survey-production.appspot.com/o/audioFiles%2FAtznECuQc6klLPsRR6u2%2Fio3eMuqyU5eWdOSV7NnjRG3eOnc2%2F2025-08-07%2011%3A15%3A03.651994.m4a?alt=media&token=ed841dc9-1e52-4eca-9e02-61d03208d2e4 | G377: 323 | H377: false | I377: priya | J377: +919790903597 | K377: Subramanian | L377: VIRALIMALAI | M377: VIRALIMALAI | N377: marakatham | O377: பெண்/Female | P377: 9655584316 | Q377: 46-60 | R377: இல்லத்தரசி/ Housewife | S377: 10,000 - 25,000 | T377: திருப்திகரமல்ல/ Unsatisfactory | U377: உறுதியாக தெரியவில்லை / Not Sure | V377: திமுக கூட்டணி / DMK Alliance | W377: விஜய் (தமிழக வெற்றி கழகம்) / Vijay (TVK) | X377: பிற கட்சிகள் / Others | Y377: TVK | Z377: - | AA377: இல்லை / No | AB377: - | AC377: வேகம் குறைபாடுடன் செயல்படுகிறது / Needs more momentum | AD377: போதுமான ஈடுபாடு / Adequate | AE377: • இல்லை: திமுக மற்றும் அதிமுக கூட்டணிகள் இரண்டும் உடையாது/ No: Both DMK & AIADMK alliances will not break up | AF377: தனித்துப் போட்டியிட வேண்டும் / Contest Independently | AG377: மதுபானம் / போதைப்பொருள் பழக்கம்/ Alcohol/Drug abuse | AH377: BC | AI377: MUTTARAIYAR | AJ377: =IFERROR(_xlfn.XLOOKUP(Table1[[#This Row],[Audio Url]],Qc!C:C,Qc!F:F),"") -> SHE SAID HER CASTE AS MUTTARAIYAR | AK377: - | AL377: - | AM377: - | AN377: =VLOOKUP(Table1[[#This Row],[LOCALITY]],Sheet2!$F:$H,3,0) -> Urban | AO377: Yes | AP377: =IF(Table1[[#This Row],[Audio Duration (in secs)]]>180,"Greater than 3 Minutes","Less than 3 Minutes") -> Greater than 3 Minutes | AQ377: =IFERROR(VLOOKUP(Table1[[#This Row],[சாதி/Caste]],MApping!$E$1:$F$10,2,0),"Others") -> MUTTARAIYAR | AR377: =VLOOKUP(Table1[[#This Row],[பாலினம்/Gender]],Factor!$F$26:$I$28,4,0) -> 1.0470348 | AS377: =VLOOKUP(Table1[[#This Row],[பதிலளித்தவரின் வயது/Age Group]],Factor!$F$35:$I$39,4,0) -> 0.87972509 | AT377: =VLOOKUP(Table1[[#This Row],[பதிலளித்தவரின் வயது/Age Group]]&Table1[[#This Row],[பாலினம்/Gender]],Factor!$A$45:$G$53,7,0) -> 0.98461538 | AU377: =VLOOKUP(Table1[[#This Row],[2021 சட்டமன்றத் தேர்தலில் நீங்கள் எந்தக் கட்சிக்கு வாக்களித்தீர்கள்?/ Which party did you vote in 2021 Assembly Elections? ]],Factor!$F$9:$J$14,5,0) -> 0.73680082 | AV377: =VLOOKUP(Table1[[#This Row],[Rev Caste]],Factor!$F$59:$I$68,4,0) -> 1.2358621 | AW377: =Table1[[#This Row],[2021 Ae Factor]]*Table1[[#This Row],[Age & Gender Factor]] -> 0.72546543 | AX377: =Table1[[#This Row],[2021 Ae Factor]]*Table1[[#This Row],[Caste Factor]] -> 0.91058419 | AY377: =VALUE(MID(D377, FIND(",",D377)+2, FIND(")",D377)-FIND(",",D377)-2)) -> 78.544967
A378: JDwngGfvF74ascNwKGu9 | B378: 2025-08-07 11:25:00.184131 | C378: 45876 | D378: (10.6007189, 78.5456773) | E378: JG2W+78C,,Viralimalai,621316,Tamil Nadu,India. | F378: https://firebasestorage.googleapis.com/v0/b/mindbrink-survey-production.appspot.com/o/audioFiles%2FAtznECuQc6klLPsRR6u2%2Fi7rHaGVsQtUuH9WIbNPBcYow6HH3%2F2025-08-07%2011%3A24%3A54.713387.m4a?alt=media&token=f83136a0-11fa-4e2a-8c28-3e5f45442d35 | G378: 353 | H378: false | I378: Immaculatebanumathi | J378: +917395821468 | K378: Subramanian | L378: VIRALIMALAI | M378: VIRALIMALAI | N378: Jagathis | O378: ஆண்/Male | P378: 9087174251 | Q378: 18-30 | R378: பணியாளர்/ Employee | S378: 10,000 - 25,000 | T378: திருப்திகரமல்ல/ Unsatisfactory | U378: ஆம் / Yes | V378: வாக்களிக்கவில்லை / Did not Vote | W378: விஜய் (தமிழக வெற்றி கழகம்) / Vijay (TVK) | X378: அதிமுக / AIADMK | Y378: TVK | Z378: ஆம், TVK கூட்டணிக்கு வாக்களிப்பேன் / Yes, I will shift my vote to the TVK alliance | AA378: ஆமாம் / Yes | AB378: திமுக கூட்டணி / DMK Alliance | AC378: திருப்திகரமானது / Satisfactory | AD378: போதுமான ஈடுபாடு / Adequate | AE378: • ஆமாம்: அதிமுக கூட்டணி உடையும்/ Yes: AIADMK alliance will break up | AF378: அதிமுக / AIADMK | AG378: சாதி வேறுபாடு/ Caste discrimination | AH378: BC | AI378: Kammalar | AJ378: =IFERROR(_xlfn.XLOOKUP(Table1[[#This Row],[Audio Url]],Qc!C:C,Qc!F:F),"") -> HE SAID HIS CASTE KAMMALAR | AK378: - | AL378: - | AM378: - | AN378: =VLOOKUP(Table1[[#This Row],[LOCALITY]],Sheet2!$F:$H,3,0) -> Urban | AO378: Yes | AP378: =IF(Table1[[#This Row],[Audio Duration (in secs)]]>180,"Greater than 3 Minutes","Less than 3 Minutes") -> Greater than 3 Minutes | AQ378: =IFERROR(VLOOKUP(Table1[[#This Row],[சாதி/Caste]],MApping!$E$1:$F$10,2,0),"Others") -> Others | AR378: =VLOOKUP(Table1[[#This Row],[பாலினம்/Gender]],Factor!$F$26:$I$28,4,0) -> 0.95700935 | AS378: =VLOOKUP(Table1[[#This Row],[பதிலளித்தவரின் வயது/Age Group]],Factor!$F$35:$I$39,4,0) -> 0.9752381 | AT378: =VLOOKUP(Table1[[#This Row],[பதிலளித்தவரின் வயது/Age Group]]&Table1[[#This Row],[பாலினம்/Gender]],Factor!$A$45:$G$53,7,0) -> 1.0666667 | AU378: =VLOOKUP(Table1[[#This Row],[2021 சட்டமன்றத் தேர்தலில் நீங்கள் எந்தக் கட்சிக்கு வாக்களித்தீர்கள்?/ Which party did you vote in 2021 Assembly Elections? ]],Factor!$F$9:$J$14,5,0) -> 1 | AV378: =VLOOKUP(Table1[[#This Row],[Rev Caste]],Factor!$F$59:$I$68,4,0) -> 0.14422535 | AW378: =Table1[[#This Row],[2021 Ae Factor]]*Table1[[#This Row],[Age & Gender Factor]] -> 1.0666667 | AX378: =Table1[[#This Row],[2021 Ae Factor]]*Table1[[#This Row],[Caste Factor]] -> 0.14422535 | AY378: =VALUE(MID(D378, FIND(",",D378)+2, FIND(")",D378)-FIND(",",D378)-2)) -> 78.545677
A379: zEQdnYcj4XeYJUoPnLG1 | B379: 2025-08-07 11:27:23.775922 | C379: 45876 | D379: (10.6004667, 78.5451483) | E379: 1017,,Viralimalai,621316,Tamil Nadu,India. | F379: https://firebasestorage.googleapis.com/v0/b/mindbrink-survey-production.appspot.com/o/audioFiles%2FAtznECuQc6klLPsRR6u2%2Fio3eMuqyU5eWdOSV7NnjRG3eOnc2%2F2025-08-07%2011%3A27%3A18.577389.m4a?alt=media&token=afc5ecb1-b99e-48e5-90d0-ad348e2e950e | G379: 289 | H379: false | I379: priya | J379: +919790903597 | K379: Subramanian | L379: VIRALIMALAI | M379: VIRALIMALAI | N379: kannavali | O379: பெண்/Female | P379: 9994368498 | Q379: 46-60 | R379: இல்லத்தரசி/ Housewife | S379: 10,000 - 25,000 | T379: திருப்திகரமல்ல/ Unsatisfactory | U379: ஆம் / Yes | V379: அதிமுக கூட்டணி / AIADMK Alliance | W379: எடப்பாடி பழனிசாமி (அதிமுக) / Edappadi K. Palaniswami (AIADMK) | X379: அதிமுக / AIADMK | Y379: AIADMK | Z379: ஆம், TVK கூட்டணிக்கு வாக்களிப்பேன் / Yes, I will shift my vote to the TVK alliance | AA379: இல்லை / No | AB379: - | AC379: வேகம் குறைபாடுடன் செயல்படுகிறது / Needs more momentum | AD379: பயனில்லை / Not effective | AE379: • இல்லை: திமுக மற்றும் அதிமுக கூட்டணிகள் இரண்டும் உடையாது/ No: Both DMK & AIADMK alliances will not break up | AF379: அதிமுக / AIADMK | AG379: மதுபானம் / போதைப்பொருள் பழக்கம்/ Alcohol/Drug abuse | AH379: BC | AI379: MUTTARAIYAR | AJ379: =IFERROR(_xlfn.XLOOKUP(Table1[[#This Row],[Audio Url]],Qc!C:C,Qc!F:F),"") -> HE SAID HIS CASTE MUTTARAIYAR | AK379: - | AL379: - | AM379: - | AN379: =VLOOKUP(Table1[[#This Row],[LOCALITY]],Sheet2!$F:$H,3,0) -> Urban | AO379: Yes | AP379: =IF(Table1[[#This Row],[Audio Duration (in secs)]]>180,"Greater than 3 Minutes","Less than 3 Minutes") -> Greater than 3 Minutes | AQ379: =IFERROR(VLOOKUP(Table1[[#This Row],[சாதி/Caste]],MApping!$E$1:$F$10,2,0),"Others") -> MUTTARAIYAR | AR379: =VLOOKUP(Table1[[#This Row],[பாலினம்/Gender]],Factor!$F$26:$I$28,4,0) -> 1.0470348 | AS379: =VLOOKUP(Table1[[#This Row],[பதிலளித்தவரின் வயது/Age Group]],Factor!$F$35:$I$39,4,0) -> 0.87972509 | AT379: =VLOOKUP(Table1[[#This Row],[பதிலளித்தவரின் வயது/Age Group]]&Table1[[#This Row],[பாலினம்/Gender]],Factor!$A$45:$G$53,7,0) -> 0.98461538 | AU379: =VLOOKUP(Table1[[#This Row],[2021 சட்டமன்றத் தேர்தலில் நீங்கள் எந்தக் கட்சிக்கு வாக்களித்தீர்கள்?/ Which party did you vote in 2021 Assembly Elections? ]],Factor!$F$9:$J$14,5,0) -> 1.3119425 | AV379: =VLOOKUP(Table1[[#This Row],[Rev Caste]],Factor!$F$59:$I$68,4,0) -> 1.2358621 | AW379: =Table1[[#This Row],[2021 Ae Factor]]*Table1[[#This Row],[Age & Gender Factor]] -> 1.2917588 | AX379: =Table1[[#This Row],[2021 Ae Factor]]*Table1[[#This Row],[Caste Factor]] -> 1.62138 | AY379: =VALUE(MID(D379, FIND(",",D379)+2, FIND(")",D379)-FIND(",",D379)-2)) -> 78.545148
... A459: A08DVPN1Zzn5D2oR54XV | B459: 2025-08-07 18:59:46.108034 | C459: 45876 | D459: (10.6029765, 78.4565447) | E459: 3c,,Rasalipatti,621312,Tamil Nadu,India. | F459: https://firebasestorage.googleapis.com/v0/b/mindbrink-survey-production.appspot.com/o/audioFiles%2FAtznECuQc6klLPsRR6u2%2FvgezSzrsuLVlWSdHweefXnEvA793%2F2025-08-07%2018%3A59%3A16.060040.m4a?alt=media&token=b7f76394-8d09-4537-8dc9-9f809e2001cf | G459: 281 | H459: false | I459: pantyan | J459: +919976239565 | K459: Subramanian | L459: VIRALIMALAI | M459: RAJALIPATTI | N459: Natarajkumar | O459: ஆண்/Male | P459: 9944276614 | Q459: 31-45 | R459: விவசாயி/ Farmer | S459: 10,000க்கும் குறைவானது/Less than 10,000 | T459: திருப்திகரமானது / Satisfactory | U459: இல்லை/ No | V459: திமுக கூட்டணி / DMK Alliance | W459: மு.க. ஸ்டாலின் (திமுக) / M.K. Stalin (DMK) | X459: திமுக / DMK | Y459: DMK | Z459: - | AA459: இல்லை / No | AB459: - | AC459: வேகம் குறைபாடுடன் செயல்படுகிறது / Needs more momentum | AD459: பயனில்லை / Not effective | AE459: • ஆமாம்: அதிமுக கூட்டணி உடையும்/ Yes: AIADMK alliance will break up | AF459: தனித்துப் போட்டியிட வேண்டும் / Contest Independently | AG459: விவசாய நெருக்கடி / Agricultural crisis | AH459: BC | AI459: URALI GOUNDER | AJ459: =IFERROR(_xlfn.XLOOKUP(Table1[[#This Row],[Audio Url]],Qc!C:C,Qc!F:F),"") -> 0 | AK459: - | AL459: - | AM459: - | AN459: =VLOOKUP(Table1[[#This Row],[LOCALITY]],Sheet2!$F:$H,3,0) -> Rural | AO459: Yes | AP459: =IF(Table1[[#This Row],[Audio Duration (in secs)]]>180,"Greater than 3 Minutes","Less than 3 Minutes") -> Greater than 3 Minutes | AQ459: =IFERROR(VLOOKUP(Table1[[#This Row],[சாதி/Caste]],MApping!$E$1:$F$10,2,0),"Others") -> URALI GOUNDER | AR459: =VLOOKUP(Table1[[#This Row],[பாலினம்/Gender]],Factor!$F$26:$I$28,4,0) -> 0.95700935 | AS459: =VLOOKUP(Table1[[#This Row],[பதிலளித்தவரின் வயது/Age Group]],Factor!$F$35:$I$39,4,0) -> 1.0951872 | AT459: =VLOOKUP(Table1[[#This Row],[பதிலளித்தவரின் வயது/Age Group]]&Table1[[#This Row],[பாலினம்/Gender]],Factor!$A$45:$G$53,7,0) -> 1.0835979 | AU459: =VLOOKUP(Table1[[#This Row],[2021 சட்டமன்றத் தேர்தலில் நீங்கள் எந்தக் கட்சிக்கு வாக்களித்தீர்கள்?/ Which party did you vote in 2021 Assembly Elections? ]],Factor!$F$9:$J$14,5,0) -> 0.73680082 | AV459: =VLOOKUP(Table1[[#This Row],[Rev Caste]],Factor!$F$59:$I$68,4,0) -> 1.0593103 | AW459: =Table1[[#This Row],[2021 Ae Factor]]*Table1[[#This Row],[Age & Gender Factor]] -> 0.79839581 | AX459: =Table1[[#This Row],[2021 Ae Factor]]*Table1[[#This Row],[Caste Factor]] -> 0.78050074 | AY459: =VALUE(MID(D459, FIND(",",D459)+2, FIND(")",D459)-FIND(",",D459)-2)) -> 78.456545
A460: Z7wjShyR7ZNftNhyGSYk | B460: 2025-08-07 19:27:10.801143 | C460: 45876 | D460: (10.6054133, 78.4712883) | E460: - | F460: https://firebasestorage.googleapis.com/v0/b/mindbrink-survey-production.appspot.com/o/audioFiles%2FAtznECuQc6klLPsRR6u2%2FnV4IA56gMWWp4NfG0H1PGfyqfM92%2F2025-08-07%2019%3A20%3A31.075771.m4a?alt=media&token=a8c0e26f-9c9f-412e-bbcf-e1a42e8734a9 | G460: 256 | H460: false | I460: G.muthukumar | J460: +918940041476 | K460: Subramanian | L460: VIRALIMALAI | M460: RAJALIPATTI | N460: Subramani | O460: ஆண்/Male | P460: 7200432701p | Q460: 31-45 | R460: கூலி தொழில்/ Daily Wage | S460: 10,000 - 25,000 | T460: திருப்திகரமானது / Satisfactory | U460: இல்லை/ No | V460: திமுக கூட்டணி / DMK Alliance | W460: மு.க. ஸ்டாலின் (திமுக) / M.K. Stalin (DMK) | X460: திமுக / DMK | Y460: DMK | Z460: - | AA460: இல்லை / No | AB460: - | AC460: திருப்திகரமல்ல / Unsatisfactory | AD460: பயனில்லை / Not effective | AE460: • இல்லை: திமுக மற்றும் அதிமுக கூட்டணிகள் இரண்டும் உடையாது/ No: Both DMK & AIADMK alliances will not break up | AF460: தனித்துப் போட்டியிட வேண்டும் / Contest Independently | AG460: விவசாய நெருக்கடி / Agricultural crisis | AH460: BC | AI460: yadavar | AJ460: =IFERROR(_xlfn.XLOOKUP(Table1[[#This Row],[Audio Url]],Qc!C:C,Qc!F:F),"") -> 0 | AK460: - | AL460: - | AM460: - | AN460: =VLOOKUP(Table1[[#This Row],[LOCALITY]],Sheet2!$F:$H,3,0) -> Rural | AO460: Yes | AP460: =IF(Table1[[#This Row],[Audio Duration (in secs)]]>180,"Greater than 3 Minutes","Less than 3 Minutes") -> Greater than 3 Minutes | AQ460: =IFERROR(VLOOKUP(Table1[[#This Row],[சாதி/Caste]],MApping!$E$1:$F$10,2,0),"Others") -> Others | AR460: =VLOOKUP(Table1[[#This Row],[பாலினம்/Gender]],Factor!$F$26:$I$28,4,0) -> 0.95700935 | AS460: =VLOOKUP(Table1[[#This Row],[பதிலளித்தவரின் வயது/Age Group]],Factor!$F$35:$I$39,4,0) -> 1.0951872 | AT460: =VLOOKUP(Table1[[#This Row],[பதிலளித்தவரின் வயது/Age Group]]&Table1[[#This Row],[பாலினம்/Gender]],Factor!$A$45:$G$53,7,0) -> 1.0835979 | AU460: =VLOOKUP(Table1[[#This Row],[2021 சட்டமன்றத் தேர்தலில் நீங்கள் எந்தக் கட்சிக்கு வாக்களித்தீர்கள்?/ Which party did you vote in 2021 Assembly Elections? ]],Factor!$F$9:$J$14,5,0) -> 0.73680082 | AV460: =VLOOKUP(Table1[[#This Row],[Rev Caste]],Factor!$F$59:$I$68,4,0) -> 0.14422535 | AW460: =Table1[[#This Row],[2021 Ae Factor]]*Table1[[#This Row],[Age & Gender Factor]] -> 0.79839581 | AX460: =Table1[[#This Row],[2021 Ae Factor]]*Table1[[#This Row],[Caste Factor]] -> 0.10626536 | AY460: =VALUE(MID(D460, FIND(",",D460)+2, FIND(")",D460)-FIND(",",D460)-2)) -> 78.471288
A461: mTAs6Ct1wVCw22eFqmRS | B461: 2025-08-07 19:36:05.711479 | C461: 45876 | D461: (10.6057719, 78.4708416) | E461: JF4C+66Q,,Nambampatty,621312,Tamil Nadu,India. | F461: https://firebasestorage.googleapis.com/v0/b/mindbrink-survey-production.appspot.com/o/audioFiles%2FAtznECuQc6klLPsRR6u2%2FnV4IA56gMWWp4NfG0H1PGfyqfM92%2F2025-08-07%2019%3A35%3A15.050608.m4a?alt=media&token=760b0f6d-4752-4ab1-8948-64f17d2ddbc1 | G461: 375 | H461: false | I461: G.muthukumar | J461: +918940041476 | K461: Subramanian | L461: VIRALIMALAI | M461: RAJALIPATTI | N461: Durairaj | O461: ஆண்/Male | P461: 9994525156 | Q461: 60+ | R461: சொந்த தொழில் / சுயதொழில் செய்பவர்/ Self Employed/Business | S461: 10,000க்கும் குறைவானது/Less than 10,000 | T461: திருப்திகரமானது / Satisfactory | U461: ஆம் / Yes | V461: திமுக கூட்டணி / DMK Alliance | W461: மு.க. ஸ்டாலின் (திமுக) / M.K. Stalin (DMK) | X461: திமுக / DMK | Y461: DMK | Z461: - | AA461: இல்லை / No | AB461: - | AC461: திருப்திகரமல்ல / Unsatisfactory | AD461: பயனில்லை / Not effective | AE461: • ஆமாம்: அதிமுக கூட்டணி உடையும்/ Yes: AIADMK alliance will break up | AF461: தி.மு.க/DMK | AG461: மதுபானம் / போதைப்பொருள் பழக்கம்/ Alcohol/Drug abuse | AH461: BC | AI461: chettiyar | AJ461: =IFERROR(_xlfn.XLOOKUP(Table1[[#This Row],[Audio Url]],Qc!C:C,Qc!F:F),"") -> 0 | AK461: - | AL461: - | AM461: - | AN461: =VLOOKUP(Table1[[#This Row],[LOCALITY]],Sheet2!$F:$H,3,0) -> Rural | AO461: Yes | AP461: =IF(Table1[[#This Row],[Audio Duration (in secs)]]>180,"Greater than 3 Minutes","Less than 3 Minutes") -> Greater than 3 Minutes | AQ461: =IFERROR(VLOOKUP(Table1[[#This Row],[சாதி/Caste]],MApping!$E$1:$F$10,2,0),"Others") -> Others | AR461: =VLOOKUP(Table1[[#This Row],[பாலினம்/Gender]],Factor!$F$26:$I$28,4,0) -> 0.95700935 | AS461: =VLOOKUP(Table1[[#This Row],[பதிலளித்தவரின் வயது/Age Group]],Factor!$F$35:$I$39,4,0) -> 1.0308725 | AT461: =VLOOKUP(Table1[[#This Row],[பதிலளித்தவரின் வயது/Age Group]]&Table1[[#This Row],[பாலினம்/Gender]],Factor!$A$45:$G$53,7,0) -> 0.86292135 | AU461: =VLOOKUP(Table1[[#This Row],[2021 சட்டமன்றத் தேர்தலில் நீங்கள் எந்தக் கட்சிக்கு வாக்களித்தீர்கள்?/ Which party did you vote in 2021 Assembly Elections? ]],Factor!$F$9:$J$14,5,0) -> 0.73680082 | AV461: =VLOOKUP(Table1[[#This Row],[Rev Caste]],Factor!$F$59:$I$68,4,0) -> 0.14422535 | AW461: =Table1[[#This Row],[2021 Ae Factor]]*Table1[[#This Row],[Age & Gender Factor]] -> 0.63580116 | AX461: =Table1[[#This Row],[2021 Ae Factor]]*Table1[[#This Row],[Caste Factor]] -> 0.10626536 | AY461: =VALUE(MID(D461, FIND(",",D461)+2, FIND(")",D461)-FIND(",",D461)-2)) -> 78.470842
A462: VbmKTLSyM8HjThpAECHV | B462: 2025-08-07 19:48:18.233794 | C462: 45876 | D462: (10.6052488, 78.4704825) | E462: - | F462: https://firebasestorage.googleapis.com/v0/b/mindbrink-survey-production.appspot.com/o/audioFiles%2FAtznECuQc6klLPsRR6u2%2FnV4IA56gMWWp4NfG0H1PGfyqfM92%2F2025-08-07%2019%3A45%3A43.595974.m4a?alt=media&token=022444cd-d7a3-4c30-a62c-0146d94f2424 | G462: 270 | H462: false | I462: G.muthukumar | J462: +918940041476 | K462: Subramanian | L462: VIRALIMALAI | M462: RAJALIPATTI | N462: viduthalaimani | O462: ஆண்/Male | P462: 9095706030 | Q462: 31-45 | R462: கூலி தொழில்/ Daily Wage | S462: 10,000 - 25,000 | T462: திருப்திகரமானது / Satisfactory | U462: இல்லை/ No | V462: திமுக கூட்டணி / DMK Alliance | W462: மு.க. ஸ்டாலின் (திமுக) / M.K. Stalin (DMK) | X462: திமுக / DMK | Y462: DMK | Z462: - | AA462: இல்லை / No | AB462: - | AC462: திருப்திகரமல்ல / Unsatisfactory | AD462: பயனில்லை / Not effective | AE462: • இல்லை: திமுக மற்றும் அதிமுக கூட்டணிகள் இரண்டும் உடையாது/ No: Both DMK & AIADMK alliances will not break up | AF462: தனித்துப் போட்டியிட வேண்டும் / Contest Independently | AG462: விவசாய நெருக்கடி / Agricultural crisis | AH462: OBC | AI462: URALI GOUNDER | AJ462: =IFERROR(_xlfn.XLOOKUP(Table1[[#This Row],[Audio Url]],Qc!C:C,Qc!F:F),"") -> 0 | AK462: - | AL462: - | AM462: - | AN462: =VLOOKUP(Table1[[#This Row],[LOCALITY]],Sheet2!$F:$H,3,0) -> Rural | AO462: Yes | AP462: =IF(Table1[[#This Row],[Audio Duration (in secs)]]>180,"Greater than 3 Minutes","Less than 3 Minutes") -> Greater than 3 Minutes | AQ462: =IFERROR(VLOOKUP(Table1[[#This Row],[சாதி/Caste]],MApping!$E$1:$F$10,2,0),"Others") -> URALI GOUNDER | AR462: =VLOOKUP(Table1[[#This Row],[பாலினம்/Gender]],Factor!$F$26:$I$28,4,0) -> 0.95700935 | AS462: =VLOOKUP(Table1[[#This Row],[பதிலளித்தவரின் வயது/Age Group]],Factor!$F$35:$I$39,4,0) -> 1.0951872 | AT462: =VLOOKUP(Table1[[#This Row],[பதிலளித்தவரின் வயது/Age Group]]&Table1[[#This Row],[பாலினம்/Gender]],Factor!$A$45:$G$53,7,0) -> 1.0835979 | AU462: =VLOOKUP(Table1[[#This Row],[2021 சட்டமன்றத் தேர்தலில் நீங்கள் எந்தக் கட்சிக்கு வாக்களித்தீர்கள்?/ Which party did you vote in 2021 Assembly Elections? ]],Factor!$F$9:$J$14,5,0) -> 0.73680082 | AV462: =VLOOKUP(Table1[[#This Row],[Rev Caste]],Factor!$F$59:$I$68,4,0) -> 1.0593103 | AW462: =Table1[[#This Row],[2021 Ae Factor]]*Table1[[#This Row],[Age & Gender Factor]] -> 0.79839581 | AX462: =Table1[[#This Row],[2021 Ae Factor]]*Table1[[#This Row],[Caste Factor]] -> 0.78050074 | AY462: =VALUE(MID(D462, FIND(",",D462)+2, FIND(")",D462)-FIND(",",D462)-2)) -> 78.470483
A463: v46GZqrqyYSN8GwaHByD | B463: 2025-08-08 12:19:14.226524 | C463: 45877 | D463: (10.7196967, 78.7251983) | E463: PP9G+Q4M,Burma Colony,Tiruchirappalli,620007,Tamil Nadu,India. | F463: https://firebasestorage.googleapis.com/v0/b/mindbrink-survey-production.appspot.com/o/audioFiles%2FAtznECuQc6klLPsRR6u2%2Fio3eMuqyU5eWdOSV7NnjRG3eOnc2%2F2025-08-08%2012%3A19%3A05.721896.m4a?alt=media&token=29e0afe0-a84c-485c-b390-05054012dfbe | G463: 290 | H463: false | I463: priya | J463: +919790903597 | K463: Subramanian | L463: KULATHUR | M463: KUMARAMANGALAM | N463: balachandran | O463: ஆண்/Male | P463: 8667348601 | Q463: 31-45 | R463: பணியாளர்/ Employee | S463: 10,000 - 25,000 | T463: திருப்திகரமானது / Satisfactory | U463: ஆம் / Yes | V463: திமுக கூட்டணி / DMK Alliance | W463: மு.க. ஸ்டாலின் (திமுக) / M.K. Stalin (DMK) | X463: திமுக / DMK | Y463: DMK | Z463: - | AA463: ஆமாம் / Yes | AB463: திமுக கூட்டணி / DMK Alliance | AC463: திருப்திகரமானது / Satisfactory | AD463: போதுமான ஈடுபாடு / Adequate | AE463: • ஆமாம்: திமுக கூட்டணி உடையும் / Yes: DMK Alliance will break up | AF463: தி.மு.க/DMK | AG463: மதுபானம் / போதைப்பொருள் பழக்கம்/ Alcohol/Drug abuse | AH463: General | AI463: - | AJ463: - | AK463: - | AL463: - | AM463: - | AN463: =VLOOKUP(Table1[[#This Row],[LOCALITY]],Sheet2!$F:$H,3,0) -> Rural | AO463: No | AP463: =IF(Table1[[#This Row],[Audio Duration (in secs)]]>180,"Greater than 3 Minutes","Less than 3 Minutes") -> Greater than 3 Minutes | AQ463: =IFERROR(VLOOKUP(Table1[[#This Row],[சாதி/Caste]],MApping!$E$1:$F$10,2,0),"Others") -> Others | AR463: =VLOOKUP(Table1[[#This Row],[பாலினம்/Gender]],Factor!$F$26:$I$28,4,0) -> 0.95700935 | AS463: =VLOOKUP(Table1[[#This Row],[பதிலளித்தவரின் வயது/Age Group]],Factor!$F$35:$I$39,4,0) -> 1.0951872 | AT463: =VLOOKUP(Table1[[#This Row],[பதிலளித்தவரின் வயது/Age Group]]&Table1[[#This Row],[பாலினம்/Gender]],Factor!$A$45:$G$53,7,0) -> 1.0835979 | AU463: =VLOOKUP(Table1[[#This Row],[2021 சட்டமன்றத் தேர்தலில் நீங்கள் எந்தக் கட்சிக்கு வாக்களித்தீர்கள்?/ Which party did you vote in 2021 Assembly Elections? ]],Factor!$F$9:$J$14,5,0) -> 0.73680082 | AV463: =VLOOKUP(Table1[[#This Row],[Rev Caste]],Factor!$F$59:$I$68,4,0) -> 0.14422535 | AW463: =Table1[[#This Row],[2021 Ae Factor]]*Table1[[#This Row],[Age & Gender Factor]] -> 0.79839581 | AX463: =Table1[[#This Row],[2021 Ae Factor]]*Table1[[#This Row],[Caste Factor]] -> 0.10626536 | AY463: =VALUE(MID(D463, FIND(",",D463)+2, FIND(")",D463)-FIND(",",D463)-2)) -> 78.725198
A464: hkPQnrPC1L94wGNeXt9Q | B464: 2025-08-08 12:20:26.894425 | C464: 45877 | D464: (10.7183166, 78.7232604) | E464: 8/8,Gundur Burma Colony,Tiruchirappalli,620007,Tamil Nadu,India. | F464: https://firebasestorage.googleapis.com/v0/b/mindbrink-survey-production.appspot.com/o/audioFiles%2FAtznECuQc6klLPsRR6u2%2Fi7rHaGVsQtUuH9WIbNPBcYow6HH3%2F2025-08-08%2012%3A20%3A13.149990.m4a?alt=media&token=939f658a-1b2a-4b95-82a2-9c59e34d6903 | G464: 326 | H464: false | I464: Immaculatebanumathi | J464: +917395821468 | K464: Subramanian | L464: KULATHUR | M464: KUMARAMANGALAM | N464: Geetha | O464: பெண்/Female | P464: 6369121343 | Q464: 31-45 | R464: இல்லத்தரசி/ Housewife | S464: 10,000க்கும் குறைவானது/Less than 10,000 | T464: மேம்பாடு தேவை / Needs improvement | U464: உறுதியாக தெரியவில்லை / Not Sure | V464: அதிமுக கூட்டணி / AIADMK Alliance | W464: மு.க. ஸ்டாலின் (திமுக) / M.K. Stalin (DMK) | X464: திமுக / DMK | Y464: DMK | Z464: - | AA464: ஆமாம் / Yes | AB464: பிறவை / Others | AC464: திருப்திகரமானது / Satisfactory | AD464: போதுமான ஈடுபாடு / Adequate | AE464: • இல்லை: திமுக மற்றும் அதிமுக கூட்டணிகள் இரண்டும் உடையாது/ No: Both DMK & AIADMK alliances will not break up | AF464: தி.மு.க/DMK | AG464: மதுபானம் / போதைப்பொருள் பழக்கம்/ Alcohol/Drug abuse | AH464: BC | AI464: - | AJ464: - | AK464: - | AL464: - | AM464: - | AN464: =VLOOKUP(Table1[[#This Row],[LOCALITY]],Sheet2!$F:$H,3,0) -> Rural | AO464: No | AP464: =IF(Table1[[#This Row],[Audio Duration (in secs)]]>180,"Greater than 3 Minutes","Less than 3 Minutes") -> Greater than 3 Minutes | AQ464: =IFERROR(VLOOKUP(Table1[[#This Row],[சாதி/Caste]],MApping!$E$1:$F$10,2,0),"Others") -> Others | AR464: =VLOOKUP(Table1[[#This Row],[பாலினம்/Gender]],Factor!$F$26:$I$28,4,0) -> 1.0470348 | AS464: =VLOOKUP(Table1[[#This Row],[பதிலளித்தவரின் வயது/Age Group]],Factor!$F$35:$I$39,4,0) -> 1.0951872 | AT464: =VLOOKUP(Table1[[#This Row],[பதிலளித்தவரின் வயது/Age Group]]&Table1[[#This Row],[பாலினம்/Gender]],Factor!$A$45:$G$53,7,0) -> 1.107027 | AU464: =VLOOKUP(Table1[[#This Row],[2021 சட்டமன்றத் தேர்தலில் நீங்கள் எந்தக் கட்சிக்கு வாக்களித்தீர்கள்?/ Which party did you vote in 2021 Assembly Elections? ]],Factor!$F$9:$J$14,5,0) -> 1.3119425 | AV464: =VLOOKUP(Table1[[#This Row],[Rev Caste]],Factor!$F$59:$I$68,4,0) -> 0.14422535 | AW464: =Table1[[#This Row],[2021 Ae Factor]]*Table1[[#This Row],[Age & Gender Factor]] -> 1.4523558 | AX464: =Table1[[#This Row],[2021 Ae Factor]]*Table1[[#This Row],[Caste Factor]] -> 0.18921537 | AY464: =VALUE(MID(D464, FIND(",",D464)+2, FIND(")",D464)-FIND(",",D464)-2)) -> 78.72326
A465: oI5BD5GKUD6HYqj6xTI7 | B465: 2025-08-08 12:23:14.939891 | C465: 45877 | D465: (10.7170172, 78.7233524) | E465: 1,Gundur Burma Colony,Tiruchirappalli,620007,Tamil Nadu,India. | F465: https://firebasestorage.googleapis.com/v0/b/mindbrink-survey-production.appspot.com/o/audioFiles%2FAtznECuQc6klLPsRR6u2%2Fio3eMuqyU5eWdOSV7NnjRG3eOnc2%2F2025-08-08%2012%3A23%3A09.529005.m4a?alt=media&token=bf3a2d68-0987-46cb-a37e-2876463d5815 | G465: 212 | H465: false | I465: priya | J465: +919790903597 | K465: Subramanian | L465: KULATHUR | M465: KUMARAMANGALAM | N465: sagayamary | O465: பெண்/Female | P465: 9750195552 | Q465: 60+ | R465: கூலி தொழில்/ Daily Wage | S465: 10,000 - 25,000 | T465: திருப்திகரமானது / Satisfactory | U465: இல்லை/ No | V465: திமுக கூட்டணி / DMK Alliance | W465: மு.க. ஸ்டாலின் (திமுக) / M.K. Stalin (DMK) | X465: திமுக / DMK | Y465: DMK | Z465: - | AA465: இல்லை / No | AB465: - | AC465: திருப்திகரமல்ல / Unsatisfactory | AD465: பயனில்லை / Not effective | AE465: • இல்லை: திமுக மற்றும் அதிமுக கூட்டணிகள் இரண்டும் உடையாது/ No: Both DMK & AIADMK alliances will not break up | AF465: தனித்துப் போட்டியிட வேண்டும் / Contest Independently | AG465: மதுபானம் / போதைப்பொருள் பழக்கம்/ Alcohol/Drug abuse | AH465: Christian | AI465: CHRISTIAN | AJ465: - | AK465: - | AL465: - | AM465: - | AN465: =VLOOKUP(Table1[[#This Row],[LOCALITY]],Sheet2!$F:$H,3,0) -> Rural | AO465: No | AP465: =IF(Table1[[#This Row],[Audio Duration (in secs)]]>180,"Greater than 3 Minutes","Less than 3 Minutes") -> Greater than 3 Minutes | AQ465: =IFERROR(VLOOKUP(Table1[[#This Row],[சாதி/Caste]],MApping!$E$1:$F$10,2,0),"Others") -> CHRISTIAN | AR465: =VLOOKUP(Table1[[#This Row],[பாலினம்/Gender]],Factor!$F$26:$I$28,4,0) -> 1.0470348 | AS465: =VLOOKUP(Table1[[#This Row],[பதிலளித்தவரின் வயது/Age Group]],Factor!$F$35:$I$39,4,0) -> 1.0308725 | AT465: =VLOOKUP(Table1[[#This Row],[பதிலளித்தவரின் வயது/Age Group]]&Table1[[#This Row],[பாலினம்/Gender]],Factor!$A$45:$G$53,7,0) -> 1.28 | AU465: =VLOOKUP(Table1[[#This Row],[2021 சட்டமன்றத் தேர்தலில் நீங்கள் எந்தக் கட்சிக்கு வாக்களித்தீர்கள்?/ Which party did you vote in 2021 Assembly Elections? ]],Factor!$F$9:$J$14,5,0) -> 0.73680082 | AV465: =VLOOKUP(Table1[[#This Row],[Rev Caste]],Factor!$F$59:$I$68,4,0) -> 0.93090909 | AW465: =Table1[[#This Row],[2021 Ae Factor]]*Table1[[#This Row],[Age & Gender Factor]] -> 0.94310506 | AX465: =Table1[[#This Row],[2021 Ae Factor]]*Table1[[#This Row],[Caste Factor]] -> 0.68589459 | AY465: =VALUE(MID(D465, FIND(",",D465)+2, FIND(")",D465)-FIND(",",D465)-2)) -> 78.723352
A466: HSmYaFgwNAMmIOoaKFoh | B466: 2025-08-08 12:27:30.563940 | C466: 45877 | D466: (10.7182879, 78.7233706) | E466: - | F466: https://firebasestorage.googleapis.com/v0/b/mindbrink-survey-production.appspot.com/o/audioFiles%2FAtznECuQc6klLPsRR6u2%2Fi7rHaGVsQtUuH9WIbNPBcYow6HH3%2F2025-08-08%2012%3A26%3A40.733367.m4a?alt=media&token=39f8ed65-a723-4882-8f35-83db0c7f1a30 | G466: 340 | H466: false | I466: Immaculatebanumathi | J466: +917395821468 | K466: Subramanian | L466: KULATHUR | M466: KUMARAMANGALAM | N466: Elagovan | O466: ஆண்/Male | P466: 8220990438 | Q466: 60+ | R466: சொந்த தொழில் / சுயதொழில் செய்பவர்/ Self Employed/Business | S466: 10,000க்கும் குறைவானது/Less than 10,000 | T466: மேம்பாடு தேவை / Needs improvement | U466: உறுதியாக தெரியவில்லை / Not Sure | V466: திமுக கூட்டணி / DMK Alliance | W466: Others | X466: திமுக / DMK | Y466: DMK | Z466: - | AA466: இல்லை / No | AB466: - | AC466: திருப்திகரமல்ல / Unsatisfactory | AD466: பயனில்லை / Not effective | AE466: • இல்லை: திமுக மற்றும் அதிமுக கூட்டணிகள் இரண்டும் உடையாது/ No: Both DMK & AIADMK alliances will not break up | AF466: தனித்துப் போட்டியிட வேண்டும் / Contest Independently | AG466: மதுபானம் / போதைப்பொருள் பழக்கம்/ Alcohol/Drug abuse | AH466: OBC | AI466: - | AJ466: - | AK466: - | AL466: - | AM466: - | AN466: =VLOOKUP(Table1[[#This Row],[LOCALITY]],Sheet2!$F:$H,3,0) -> Rural | AO466: No | AP466: =IF(Table1[[#This Row],[Audio Duration (in secs)]]>180,"Greater than 3 Minutes","Less than 3 Minutes") -> Greater than 3 Minutes | AQ466: =IFERROR(VLOOKUP(Table1[[#This Row],[சாதி/Caste]],MApping!$E$1:$F$10,2,0),"Others") -> Others | AR466: =VLOOKUP(Table1[[#This Row],[பாலினம்/Gender]],Factor!$F$26:$I$28,4,0) -> 0.95700935 | AS466: =VLOOKUP(Table1[[#This Row],[பதிலளித்தவரின் வயது/Age Group]],Factor!$F$35:$I$39,4,0) -> 1.0308725 | AT466: =VLOOKUP(Table1[[#This Row],[பதிலளித்தவரின் வயது/Age Group]]&Table1[[#This Row],[பாலினம்/Gender]],Factor!$A$45:$G$53,7,0) -> 0.86292135 | AU466: =VLOOKUP(Table1[[#This Row],[2021 சட்டமன்றத் தேர்தலில் நீங்கள் எந்தக் கட்சிக்கு வாக்களித்தீர்கள்?/ Which party did you vote in 2021 Assembly Elections? ]],Factor!$F$9:$J$14,5,0) -> 0.73680082 | AV466: =VLOOKUP(Table1[[#This Row],[Rev Caste]],Factor!$F$59:$I$68,4,0) -> 0.14422535 | AW466: =Table1[[#This Row],[2021 Ae Factor]]*Table1[[#This Row],[Age & Gender Factor]] -> 0.63580116 | AX466: =Table1[[#This Row],[2021 Ae Factor]]*Table1[[#This Row],[Caste Factor]] -> 0.10626536 | AY466: =VALUE(MID(D466, FIND(",",D466)+2, FIND(")",D466)-FIND(",",D466)-2)) -> 78.723371
